Workbook
Name StaleDays: 'MASTER DATA'!$B$4
Name CampStaleDays: 'MASTER DATA'!$B$5
Name DueSoonDays: 'MASTER DATA'!$B$6
Name OnTrackPct: 'MASTER DATA'!$B$7
Name WatchPct: 'MASTER DATA'!$B$8
Name EscalationName: 'MASTER DATA'!$B$9
Name Currency: 'MASTER DATA'!$B$10
Name lst_Team: OFFSET('MASTER DATA'!$A$15,0,0,MAX(1,COUNTA('MASTER DATA'!$A$15:$A$34)),1)
Name lst_Priority: OFFSET('MASTER DATA'!$G$15,0,0,MAX(1,COUNTA('MASTER DATA'!$G$15:$G$54)),1)
Name lst_TaskStatus: OFFSET('MASTER DATA'!$H$15,0,0,MAX(1,COUNTA('MASTER DATA'!$H$15:$H$54)),1)
Name lst_CampStatus: OFFSET('MASTER DATA'!$I$15,0,0,MAX(1,COUNTA('MASTER DATA'!$I$15:$I$54)),1)
Name lst_Workstream: OFFSET('MASTER DATA'!$J$15,0,0,MAX(1,COUNTA('MASTER DATA'!$J$15:$J$54)),1)
Name lst_Channel: OFFSET('MASTER DATA'!$K$15,0,0,MAX(1,COUNTA('MASTER DATA'!$K$15:$K$54)),1)
Name lst_Platform: OFFSET('MASTER DATA'!$L$15,0,0,MAX(1,COUNTA('MASTER DATA'!$L$15:$L$54)),1)
Name lst_Region: OFFSET('MASTER DATA'!$M$15,0,0,MAX(1,COUNTA('MASTER DATA'!$M$15:$M$54)),1)
Name lst_LeadStatus: OFFSET('MASTER DATA'!$N$15,0,0,MAX(1,COUNTA('MASTER DATA'!$N$15:$N$54)),1)
Name lst_MQLStatus: OFFSET('MASTER DATA'!$O$15,0,0,MAX(1,COUNTA('MASTER DATA'!$O$15:$O$54)),1)
Name lst_SQLStatus: OFFSET('MASTER DATA'!$P$15,0,0,MAX(1,COUNTA('MASTER DATA'!$P$15:$P$54)),1)
Name lst_OppStatus: OFFSET('MASTER DATA'!$Q$15,0,0,MAX(1,COUNTA('MASTER DATA'!$Q$15:$Q$54)),1)
Name lst_YesNo: OFFSET('MASTER DATA'!$R$15,0,0,MAX(1,COUNTA('MASTER DATA'!$R$15:$R$54)),1)
Name lst_LeadSource: OFFSET('MASTER DATA'!$S$15,0,0,MAX(1,COUNTA('MASTER DATA'!$S$15:$S$54)),1)
Name lst_ActType: OFFSET('MASTER DATA'!$T$15,0,0,MAX(1,COUNTA('MASTER DATA'!$T$15:$T$54)),1)
Name lst_WebStatus: OFFSET('MASTER DATA'!$U$15,0,0,MAX(1,COUNTA('MASTER DATA'!$U$15:$U$54)),1)
Name lst_EmailStatus: OFFSET('MASTER DATA'!$V$15,0,0,MAX(1,COUNTA('MASTER DATA'!$V$15:$V$54)),1)
Name lst_AdStatus: OFFSET('MASTER DATA'!$W$15,0,0,MAX(1,COUNTA('MASTER DATA'!$W$15:$W$54)),1)
Name lst_AcctStatus: OFFSET('MASTER DATA'!$X$15,0,0,MAX(1,COUNTA('MASTER DATA'!$X$15:$X$54)),1)
Name lst_AcctType: OFFSET('MASTER DATA'!$Y$15,0,0,MAX(1,COUNTA('MASTER DATA'!$Y$15:$Y$54)),1)
Name lst_MilestoneStatus: OFFSET('MASTER DATA'!$Z$15,0,0,MAX(1,COUNTA('MASTER DATA'!$Z$15:$Z$54)),1)
Name lst_AssignedBy: OFFSET('MASTER DATA'!$AA$15,0,0,MAX(1,COUNTA('MASTER DATA'!$AA$15:$AA$54)),1)
Name lst_FClient: OFFSET('MASTER DATA'!$AD$15,0,0,MAX(1,COUNTIF('MASTER DATA'!$AD$15:$AD$75,"?*")),1)
Name lst_FCampaign: OFFSET('MASTER DATA'!$AE$15,0,0,MAX(1,COUNTIF('MASTER DATA'!$AE$15:$AE$215,"?*")),1)
Name lst_FTeam: OFFSET('MASTER DATA'!$AF$15,0,0,MAX(1,COUNTIF('MASTER DATA'!$AF$15:$AF$35,"?*")),1)
Name lst_FChannel: OFFSET('MASTER DATA'!$AG$15,0,0,MAX(1,COUNTIF('MASTER DATA'!$AG$15:$AG$55,"?*")),1)
Name lst_FTStatus: OFFSET('MASTER DATA'!$AH$15,0,0,MAX(1,COUNTIF('MASTER DATA'!$AH$15:$AH$55,"?*")),1)
Name lst_FCStatus: OFFSET('MASTER DATA'!$AI$15,0,0,MAX(1,COUNTIF('MASTER DATA'!$AI$15:$AI$55,"?*")),1)
Name lst_FMonth: OFFSET('MASTER DATA'!$AJ$15,0,0,MAX(1,COUNTIF('MASTER DATA'!$AJ$15:$AJ$51,"?*")),1)
Name lst_Client: OFFSET('CLIENT MASTER'!$A$5,0,0,MAX(1,COUNTA('CLIENT MASTER'!$A$5:$A$64)),1)
Name lst_Campaign: OFFSET('CAMPAIGN MASTER'!$B$5,0,0,MAX(1,COUNTA('CAMPAIGN MASTER'!$B$5:$B$204)),1)
Name ReportDate: 'EXECUTIVE DASHBOARD'!$B$5
Name fMonth: 'EXECUTIVE DASHBOARD'!$D$5
Name fClient: 'EXECUTIVE DASHBOARD'!$F$5
Name fCampaign: 'EXECUTIVE DASHBOARD'!$H$5
Name fTeam: 'EXECUTIVE DASHBOARD'!$K$5
Name fChannel: 'EXECUTIVE DASHBOARD'!$M$5
Name fTStatus: 'EXECUTIVE DASHBOARD'!$O$5
Name fCStatus: 'EXECUTIVE DASHBOARD'!$Q$5
Name tpCrit: 'TEAM PERFORMANCE'!$C$3
Name cpCrit: 'CLIENT PERFORMANCE'!$C$3
Name TCL_Client: 'TCL DIGITAL DASHBOARD'!$B$3
Name MECCA_Client: 'TCL DIGITAL DASHBOARD'!$B$4

Sheet HOW TO USE
B1: HOW TO USE THIS WORKBOOK
B3: 1. THE WORKFLOW IN ONE LINE
B4: Team updates the BLUE input sheets > Excel formulas process everything > Dashboards refresh automatically > Manager reviews the EXECUTIVE DASHBOARD. Nobody types numbers into a dashboard.
B6: 2. COLOUR CODE
B7: BLUE cells (light blue fill) = INPUT. Team members type / pick from dropdowns here.
B8: GREY cells = FORMULA. Automatic - never type over them.
B9: WHITE / navy cards, tables & charts on dashboards = READ-ONLY. Sheets are protected (no password) to prevent accidents.
B11: 3. WHAT EACH SHEET IS FOR
B12: Sheet | C12: Purpose | D12: Who updates | E12: How often
B13: EXECUTIVE DASHBOARD | C13: Single-page management view: KPIs, funnel, daily Management Attention (Q1-Q14), filters. | D13: Nobody (read-only). Manager changes only the blue filters. | E13: Review daily
B14: DAILY TASK TRACKER | C14: THE key sheet. One row per task/update. Drives overdue, blocked, due-today, completion and escalation alerts. | D14: Every team member (own rows) | E14: Daily, before EOD
B15: CAMPAIGN MASTER | C15: One row per campaign: owner, dates, status, targets. Results (leads, MQL, SQL, spend, CPL, performance) pull in automatically. | D15: Campaign owner (status, dates, targets, challenge, next action, Last Updated) | E15: Weekly / on change
B16: LEAD MQL TRACKER | C16: Lead-level funnel records (handraiser > lead > MQL > SQL > opportunity). | D16: Lead owner | E16: Daily when leads move
B17: EMAIL MARKETING | C17: Per-send email performance. Rates calculate automatically. | D17: Email owner | E17: Per deployment
B18: PAID MEDIA ADS | C18: Google / Meta / LinkedIn / other paid: spend, clicks, leads. Period figures, not cumulative. | D18: Paid specialist (Richi) | E18: Daily / weekly
B19: LINKEDIN OUTREACH | C19: Dripify / Sales Navigator outreach counts (added - LinkedIn had no tracker). | D19: LinkedIn campaign owner | E19: Weekly
B20: WEBSITE CONTENT SEO | C20: Website, landing page, blog, SEO, video, webinar assets: status, traffic, leads, rankings. | D20: Content / SEO / web owners | E20: On change
B21: TEAM PERFORMANCE | C21: Workload & delivery by member; matrix of who works on which client. For balancing workload, not ranking. | D21: Nobody (automatic) | E21: Review weekly
B22: CLIENT PERFORMANCE | C22: Per-client tasks, leads, email, paid, health flag + issues/priority/next action. | D22: Nobody (automatic). Issues / priority / next action are edited in CLIENT MASTER. | E22: Review weekly
B23: TCL DIGITAL DASHBOARD | C23: TCL funnel/performance/execution + MECCA readiness tracker. | D23: Automatic; MECCA tracker blue cells by TCL/MECCA owner | E23: Weekly
... B28: BASELINE NOTES | C28: What was loaded from your existing files, assumptions, discrepancies to confirm. | D28: Manager (read, then clear items) | E28: Once
B30: 4. WHAT TEAM MEMBERS UPDATE DAILY
B31: - DAILY TASK TRACKER: add/refresh a row for every task you touched. Always set Status, Due Date, % Complete and Last Updated. Use Blocker + Status = Blocked when stuck; set 'Needs Manager Decision?' / 'Escalate to Rajesh?' = Yes when you need help.
B32: - Planned work: put today's/tomorrow's date in Date, Start Date, Due Date or Next Action Date so it shows under 'Planned today' / 'Top priorities for tomorrow'.
B33: - Results: enter Actual Result and Target (numbers) - Variance and Achievement % calculate automatically.
B34: - Channel owners also update EMAIL MARKETING, PAID MEDIA ADS, LINKEDIN OUTREACH, LEAD MQL TRACKER and WEBSITE CONTENT SEO. Campaign owners keep CAMPAIGN MASTER status & Last Updated current.
B36: 5. WHAT NOT TO EDIT
B37: - Grey cells and the hidden/grouped 'system' columns at the right of each input sheet (click the [+] above the columns to see them).
B38: - Anything on the dashboard sheets (they are protected). Do not rename sheets, tables or column headers, and do not delete columns - formulas depend on them.
B39: - Do not type over the Campaign Name in CAMPAIGN MASTER once rows exist in other sheets (results are matched by name). To rename a campaign, change it everywhere (Find & Replace).
B41: 6. HOW THE DASHBOARD GETS UPDATED
B42: Every input sheet is an Excel Table with pre-built formula columns (rows are pre-filled so just type in the next empty blue row; if you ever reach the last pre-built row, copy the last row down). Hidden helper columns convert each row into flags (Overdue, Blocked, Due today ...) and a 'rank'. Dashboards use COUNTIFS / SUMIFS / INDEX-MATCH over those columns (pre-built rows plus a 500-row buffer), so no pivot refresh is ever needed - results update the moment a cell changes. Change the Reporting Date on the dashboard to review any past day.
B44: 7. KPI DEFINITIONS
B45: KPI | C45: Definition
B46: Completion % | C46: Completed tasks / total tasks (Cancelled tasks are included in total).
B47: Pending / Open task | C47: Any task not Completed or Cancelled (includes blank status, Not Started, In Progress, On Hold, Blocked).
B48: Overdue | C48: Open task whose Due Date is before the Reporting Date. Days Overdue = Reporting Date - Due Date.
B49: Due soon | C49: Open task due between the Reporting Date and +2 days (configurable in MASTER DATA).
B50: No recent update | C50: Open task whose Last Updated is blank or older than 3 days (configurable). Live campaigns: older than 7 days.
B51: Variance / Achievement % | C51: Variance = Actual - Target. Achievement % = Actual / Target.
B52: Leads | C52: Lead-level records (LEAD MQL TRACKER rows with a Lead Name/ID) + summary Leads entered in EMAIL, PAID, LINKEDIN and WEBSITE sheets. Never enter the same lead in both places.
B53: Digital Handraiser | C53: A lead flagged 'Yes' in LEAD MQL TRACKER + Handraisers entered in LINKEDIN OUTREACH. A subset of leads.
B54: MQL / SQL / Opportunity | C54: MQL = MQL Status 'MQL' (+ MQLs in channel sheets). SQL = SQL Status 'SQL'. Opportunity = Opportunity Status Open / Won / Lost. Converted = Lead Status 'Converted' or Opportunity 'Won'.
B55: Funnel step conversion | C55: Each stage / previous stage (MQL/Leads, SQL/MQL, Opportunity/SQL, Converted/Opportunity).
B56: Open rate / CTR / Reply rate / Positive response rate | C56: Opens, Clicks, Replies, Positive Responses divided by Delivered (or by Emails Sent if Delivered is blank).
... B64: Workload index | C64: Member's pending actions / team average pending actions. > 1.3 = 'Workload high'.
B66: 8. WHO IS RESPONSIBLE
B67: Area | C67: Owner | D67: Accountable for
B68: Daily task updates | C68: Each team member | D68: Own rows in DAILY TASK TRACKER by end of day
B69: Email / Paid / LinkedIn / Web / Lead sheets | C69: Channel or lead owner | D69: Accurate counts for every deployment/period
B70: Campaign status, dates, targets | C70: Campaign Owner | D70: CAMPAIGN MASTER accuracy and Last Updated
B71: Clients, team, lists, thresholds | C71: Manager (Sr. Manager - AI Marketing) | D71: CLIENT MASTER and MASTER DATA
B72: Data hygiene check | C72: Program Managers (e.g. Ayush, Richi) | D72: Weekly: no blank Status / Due Date, no overdue tasks without a reason
B73: Decisions & escalations | C73: Manager; escalation to Rajesh | D73: Clear items under Q12 / Q13 daily
B75: 9. COMMON TASKS
B76: - Add a client: CLIENT MASTER > next blue row. Add a campaign: CAMPAIGN MASTER > next blue row (Client, Campaign Name, Owner...). Add a team member: MASTER DATA > Team table. They appear in dropdowns immediately.
B77: - Add a dropdown option: MASTER DATA > type at the bottom of the list (no blank rows between items).
B78: - Review a past day/week/month: change the Reporting Date / Month on the EXECUTIVE DASHBOARD, or the week / first month on WEEKLY REVIEW / MONTHLY PERFORMANCE.
B79: - Filtering sheets: use the filter arrows on each table header. Sharing: store on OneDrive/SharePoint and allow co-authoring so everyone updates at the same time.

Sheet EXECUTIVE DASHBOARD
B1: DIGITAL MARKETING - DAILY REVIEW & PERFORMANCE DASHBOARD
B2: Read-only management view. Everything below is calculated automatically from the input sheets. Only the BLUE filter cells in row 5 can be changed.
B4: REPORTING DATE | D4: MONTH | F4: CLIENT | H4: CAMPAIGN | K4: TEAM MEMBER | M4: CHANNEL | O4: TASK STATUS | Q4: CAMPAIGN STATUS
B5: =TODAY() -> 46300 | D5: All | F5: All | H5: All | K5: All | M5: All | O5: All | Q5: All
B6: Reporting Date drives overdue / due-today / yesterday logic (default = today; type a date to review a past day). KPI cards & funnel respect ALL filters. Daily Management Attention lists respect Client / Campaign / Team / Channel only. Task Status filter applies to tasks; Campaign Status filter to campaigns.
B8: SNAPSHOT
B9: REPORTING DATE | C9: CURRENT WEEK | D9: CURRENT MONTH | E9: ACTIVE CLIENTS | F9: ACTIVE CAMPAIGNS | G9: TOTAL TASKS | H9: COMPLETED TASKS | I9: PENDING TASKS | K9: OVERDUE TASKS | L9: BLOCKED TASKS | M9: LEADS GENERATED | N9: MQLs GENERATED | O9: SQLs GENERATED | P9: DIGITAL HANDRAISERS | Q9: CAMPAIGNS LIVE | R9: UNDER OPTIMIZATION
B10: =ReportDate -> 46300 | C10: ="Wk "&WEEKNUM(ReportDate,21)&CHAR(10)&TEXT(ReportDate-WEEKDAY(ReportDate,2)+1,"dd mmm")&" - "&TEXT(ReportDate-WEEKDAY(ReportDate,2)+7,"dd mmm") -> Wk 41 05 Oct - 11 Oct | D10: =TEXT(ReportDate,"mmm yyyy") -> Oct 2026 | E10: =IF(fClient="All",COUNTIF('CLIENT MASTER'!$D$5:$D$64,"Active"),COUNTIFS('CLIENT MASTER'!$A$5:$A$64,fClient,'CLIENT MASTER'!$D$5:$D$64,"Active")) -> 12 | F10: =COUNTIFS('CAMPAIGN MASTER'!$AK$5:$AK$704,1,'CAMPAIGN MASTER'!$AM$5:$AM$704,1) -> 0 | G10: =COUNTIFS('DAILY TASK TRACKER'!$AI$5:$AI$1504,1) -> 58 | H10: =COUNTIFS('DAILY TASK TRACKER'!$AI$5:$AI$1504,1,'DAILY TASK TRACKER'!$M$5:$M$1504,"Completed") -> 0 | I10: =SUMIFS('DAILY TASK TRACKER'!$AK$5:$AK$1504,'DAILY TASK TRACKER'!$AI$5:$AI$1504,1) -> 58 | K10: =SUMIFS('DAILY TASK TRACKER'!$AL$5:$AL$1504,'DAILY TASK TRACKER'!$AI$5:$AI$1504,1) -> 3 | L10: =SUMIFS('DAILY TASK TRACKER'!$AM$5:$AM$1504,'DAILY TASK TRACKER'!$AI$5:$AI$1504,1) -> 0 | M10: =(COUNTIFS('LEAD MQL TRACKER'!$AH$5:$AH$1004,1)+SUMIFS('EMAIL MARKETING'!$Q$5:$Q$804,'EMAIL MARKETING'!$Y$5:$Y$804,1)+SUMIFS('PAID MEDIA ADS'!$M$5:$M$804,'PAID MEDIA ADS'!$V$5:$V$804,1)+SUMIFS('LINKEDIN OUTREACH'!$N$5:$N$704,'LINKEDIN OUTREACH'!$T$5:$T$704,1)+SUMIFS('WEBSITE CONTENT SEO'!$L$5:$L$804,'WEBSITE CONTENT SEO'!$W$5:$W$804,1)) -> 0 | N10: =(COUNTIFS('LEAD MQL TRACKER'!$AH$5:$AH$1004,1,'LEAD MQL TRACKER'!$AD$5:$AD$1004,1)+SUMIFS('EMAIL MARKETING'!$R$5:$R$804,'EMAIL MARKETING'!$Y$5:$Y$804,1)+SUMIFS('PAID MEDIA ADS'!$N$5:$N$804,'PAID MEDIA ADS'!$V$5:$V$804,1)+SUMIFS('LINKEDIN OUTREACH'!$O$5:$O$704,'LINKEDIN OUTREACH'!$T$5:$T$704,1)) -> 0 | O10: =COUNTIFS('LEAD MQL TRACKER'!$AH$5:$AH$1004,1,'LEAD MQL TRACKER'!$AE$5:$AE$1004,1) -> 0 | P10: =(COUNTIFS('LEAD MQL TRACKER'!$AH$5:$AH$1004,1,'LEAD MQL TRACKER'!$AC$5:$AC$1004,1)+SUMIFS('LINKEDIN OUTREACH'!$M$5:$M$704,'LINKEDIN OUTREACH'!$T$5:$T$704,1)) -> 0 | Q10: =COUNTIFS('CAMPAIGN MASTER'!$AK$5:$AK$704,1,'CAMPAIGN MASTER'!$N$5:$N$704,"Live") -> 0 | R10: =COUNTIFS('CAMPAIGN MASTER'!$AK$5:$AK$704,1,'CAMPAIGN MASTER'!$N$5:$N$704,"Optimizing") -> 0
B12: KPI CARDS
B13: ACTIVITY KPIs | K13: LEAD KPIs
B14: TASKS ASSIGNED | C14: TASKS COMPLETED | D14: COMPLETION % | E14: OVERDUE TASKS | F14: BLOCKED TASKS | G14: DUE TODAY | H14: DUE TOMORROW | I14: NO RECENT UPDATE | K14: LEADS GENERATED | L14: DIGITAL HANDRAISERS | M14: MQLs | N14: SQLs | O14: OPPORTUNITIES | P14: LEAD > MQL % | Q14: MQL > SQL % | R14: SQL > OPP %
B15: =COUNTIFS('DAILY TASK TRACKER'!$AI$5:$AI$1504,1) -> 58 | C15: =COUNTIFS('DAILY TASK TRACKER'!$AI$5:$AI$1504,1,'DAILY TASK TRACKER'!$M$5:$M$1504,"Completed") -> 0 | D15: =IFERROR((COUNTIFS('DAILY TASK TRACKER'!$AI$5:$AI$1504,1,'DAILY TASK TRACKER'!$M$5:$M$1504,"Completed"))/(COUNTIFS('DAILY TASK TRACKER'!$AI$5:$AI$1504,1)),"N/A") -> 0 | E15: =SUMIFS('DAILY TASK TRACKER'!$AL$5:$AL$1504,'DAILY TASK TRACKER'!$AI$5:$AI$1504,1) -> 3 | F15: =SUMIFS('DAILY TASK TRACKER'!$AM$5:$AM$1504,'DAILY TASK TRACKER'!$AI$5:$AI$1504,1) -> 0 | G15: =SUMIFS('DAILY TASK TRACKER'!$AN$5:$AN$1504,'DAILY TASK TRACKER'!$AI$5:$AI$1504,1) -> 0 | H15: =SUMIFS('DAILY TASK TRACKER'!$AO$5:$AO$1504,'DAILY TASK TRACKER'!$AI$5:$AI$1504,1) -> 1 | I15: =SUMIFS('DAILY TASK TRACKER'!$AR$5:$AR$1504,'DAILY TASK TRACKER'!$AI$5:$AI$1504,1) -> 58 | K15: =(COUNTIFS('LEAD MQL TRACKER'!$AH$5:$AH$1004,1)+SUMIFS('EMAIL MARKETING'!$Q$5:$Q$804,'EMAIL MARKETING'!$Y$5:$Y$804,1)+SUMIFS('PAID MEDIA ADS'!$M$5:$M$804,'PAID MEDIA ADS'!$V$5:$V$804,1)+SUMIFS('LINKEDIN OUTREACH'!$N$5:$N$704,'LINKEDIN OUTREACH'!$T$5:$T$704,1)+SUMIFS('WEBSITE CONTENT SEO'!$L$5:$L$804,'WEBSITE CONTENT SEO'!$W$5:$W$804,1)) -> 0 | L15: =(COUNTIFS('LEAD MQL TRACKER'!$AH$5:$AH$1004,1,'LEAD MQL TRACKER'!$AC$5:$AC$1004,1)+SUMIFS('LINKEDIN OUTREACH'!$M$5:$M$704,'LINKEDIN OUTREACH'!$T$5:$T$704,1)) -> 0 | M15: =(COUNTIFS('LEAD MQL TRACKER'!$AH$5:$AH$1004,1,'LEAD MQL TRACKER'!$AD$5:$AD$1004,1)+SUMIFS('EMAIL MARKETING'!$R$5:$R$804,'EMAIL MARKETING'!$Y$5:$Y$804,1)+SUMIFS('PAID MEDIA ADS'!$N$5:$N$804,'PAID MEDIA ADS'!$V$5:$V$804,1)+SUMIFS('LINKEDIN OUTREACH'!$O$5:$O$704,'LINKEDIN OUTREACH'!$T$5:$T$704,1)) -> 0 | N15: =COUNTIFS('LEAD MQL TRACKER'!$AH$5:$AH$1004,1,'LEAD MQL TRACKER'!$AE$5:$AE$1004,1) -> 0 | O15: =COUNTIFS('LEAD MQL TRACKER'!$AH$5:$AH$1004,1,'LEAD MQL TRACKER'!$AF$5:$AF$1004,1) -> 0 | P15: =IFERROR(((COUNTIFS('LEAD MQL TRACKER'!$AH$5:$AH$1004,1,'LEAD MQL TRACKER'!$AD$5:$AD$1004,1)+SUMIFS('EMAIL MARKETING'!$R$5:$R$804,'EMAIL MARKETING'!$Y$5:$Y$804,1)+SUMIFS('PAID MEDIA ADS'!$N$5:$N$804,'PAID MEDIA ADS'!$V$5:$V$804,1)+SUMIFS('LINKEDIN OUTREACH'!$O$5:$O$704,'LINKEDIN OUTREACH'!$T$5:$T$704,1)))/((COUNTIFS('LEAD MQL TRACKER'!$AH$5:$AH$1004,1)+SUMIFS('EMAIL MARKETING'!$Q$5:$Q$804,'EMAIL MARKETING'!$Y$5:$Y$804,1)+SUMIFS('PAID MEDIA ADS'!$M$5:$M$804,'PAID MEDIA ADS'!$V$5:$V$804,1)+SUMIFS('LINKEDIN OUTREACH'!$N$5:$N$704,'LINKEDIN OUTREACH'!$T$5:$T$704,1)+SUMIFS('WEBSITE CONTENT SEO'!$L$5:$L$804,'WEBSITE CONTENT SEO'!$W$5:$W$804,1))),"N/A") -> N/A | Q15: =IFERROR((COUNTIFS('LEAD MQL TRACKER'!$AH$5:$AH$1004,1,'LEAD MQL TRACKER'!$AE$5:$AE$1004,1))/((COUNTIFS('LEAD MQL TRACKER'!$AH$5:$AH$1004,1,'LEAD MQL TRACKER'!$AD$5:$AD$1004,1)+SUMIFS('EMAIL MARKETING'!$R$5:$R$804,'EMAIL MARKETING'!$Y$5:$Y$804,1)+SUMIFS('PAID MEDIA ADS'!$N$5:$N$804,'PAID MEDIA ADS'!$V$5:$V$804,1)+SUMIFS('LINKEDIN OUTREACH'!$O$5:$O$704,'LINKEDIN OUTREACH'!$T$5:$T$704,1))),"N/A") -> N/A | R15: =IFERROR((COUNTIFS('LEAD MQL TRACKER'!$AH$5:$AH$1004,1,'LEAD MQL TRACKER'!$AF$5:$AF$1004,1))/(COUNTIFS('LEAD MQL TRACKER'!$AH$5:$AH$1004,1,'LEAD MQL TRACKER'!$AE$5:$AE$1004,1)),"N/A") -> N/A
B17: CAMPAIGN KPIs | K17: PERFORMANCE KPIs (where data is available)
B18: ACTIVE CAMPAIGNS | C18: CAMPAIGNS LAUNCHED | D18: LIVE | E18: UNDER OPTIMIZATION | F18: REQUIRING ATTENTION | G18: COMPLETED | H18: PAUSED | I18: PLANNED / IN PREP. | K18: EMAILS SENT | L18: OPEN RATE | M18: CTR (EMAIL) | N18: REPLY RATE | O18: POSITIVE RESPONSE % | P18: AD SPEND | Q18: CPL (PAID) | R18: CONV. RATE (PAID)
B19: =COUNTIFS('CAMPAIGN MASTER'!$AK$5:$AK$704,1,'CAMPAIGN MASTER'!$AM$5:$AM$704,1) -> 0 | C19: =COUNTIFS('CAMPAIGN MASTER'!$AK$5:$AK$704,1,'CAMPAIGN MASTER'!$AN$5:$AN$704,1,'CAMPAIGN MASTER'!$AJ$5:$AJ$704,IF(fMonth="All","<>@@",fMonth)) -> 0 | D19: =COUNTIFS('CAMPAIGN MASTER'!$AK$5:$AK$704,1,'CAMPAIGN MASTER'!$N$5:$N$704,"Live") -> 0 | E19: =COUNTIFS('CAMPAIGN MASTER'!$AK$5:$AK$704,1,'CAMPAIGN MASTER'!$N$5:$N$704,"Optimizing") -> 0 | F19: =SUMIFS('CAMPAIGN MASTER'!$AS$5:$AS$704,'CAMPAIGN MASTER'!$AK$5:$AK$704,1) -> 0 | G19: =COUNTIFS('CAMPAIGN MASTER'!$AK$5:$AK$704,1,'CAMPAIGN MASTER'!$N$5:$N$704,"Completed") -> 0 | H19: =COUNTIFS('CAMPAIGN MASTER'!$AK$5:$AK$704,1,'CAMPAIGN MASTER'!$N$5:$N$704,"Paused") -> 0 | I19: =COUNTIFS('CAMPAIGN MASTER'!$AK$5:$AK$704,1,'CAMPAIGN MASTER'!$N$5:$N$704,"Planned")+COUNTIFS('CAMPAIGN MASTER'!$AK$5:$AK$704,1,'CAMPAIGN MASTER'!$N$5:$N$704,"In Preparation") -> 0 | K19: =SUMIFS('EMAIL MARKETING'!$F$5:$F$804,'EMAIL MARKETING'!$Y$5:$Y$804,1) -> 0 | L19: =IFERROR((SUMIFS('EMAIL MARKETING'!$I$5:$I$804,'EMAIL MARKETING'!$Y$5:$Y$804,1))/(SUMIFS('EMAIL MARKETING'!$W$5:$W$804,'EMAIL MARKETING'!$Y$5:$Y$804,1)),"N/A") -> N/A | M19: =IFERROR((SUMIFS('EMAIL MARKETING'!$K$5:$K$804,'EMAIL MARKETING'!$Y$5:$Y$804,1))/(SUMIFS('EMAIL MARKETING'!$W$5:$W$804,'EMAIL MARKETING'!$Y$5:$Y$804,1)),"N/A") -> N/A | N19: =IFERROR((SUMIFS('EMAIL MARKETING'!$M$5:$M$804,'EMAIL MARKETING'!$Y$5:$Y$804,1))/(SUMIFS('EMAIL MARKETING'!$W$5:$W$804,'EMAIL MARKETING'!$Y$5:$Y$804,1)),"N/A") -> N/A | O19: =IFERROR((SUMIFS('EMAIL MARKETING'!$O$5:$O$804,'EMAIL MARKETING'!$Y$5:$Y$804,1))/(SUMIFS('EMAIL MARKETING'!$W$5:$W$804,'EMAIL MARKETING'!$Y$5:$Y$804,1)),"N/A") -> N/A | P19: =SUMIFS('PAID MEDIA ADS'!$G$5:$G$804,'PAID MEDIA ADS'!$V$5:$V$804,1) -> 0 | Q19: =IFERROR((SUMIFS('PAID MEDIA ADS'!$G$5:$G$804,'PAID MEDIA ADS'!$V$5:$V$804,1))/(SUMIFS('PAID MEDIA ADS'!$M$5:$M$804,'PAID MEDIA ADS'!$V$5:$V$804,1)),"N/A") -> N/A | R19: =IFERROR((SUMIFS('PAID MEDIA ADS'!$M$5:$M$804,'PAID MEDIA ADS'!$V$5:$V$804,1))/(SUMIFS('PAID MEDIA ADS'!$J$5:$J$804,'PAID MEDIA ADS'!$V$5:$V$804,1)),"N/A") -> N/A
B22: LEAD FUNNEL (respects filters) | K22: FUNNEL & TASK-STATUS CHARTS
B23: Stage | E23: Count | F23: Step Conv. % | H23: % of Leads
B24: Digital Handraisers | E24: =(COUNTIFS('LEAD MQL TRACKER'!$AH$5:$AH$1004,1,'LEAD MQL TRACKER'!$AC$5:$AC$1004,1)+SUMIFS('LINKEDIN OUTREACH'!$M$5:$M$704,'LINKEDIN OUTREACH'!$T$5:$T$704,1)) -> 0 | F24: ="n/a" -> n/a | H24: =IFERROR(E24/$E$25,"–") -> –
B25: Leads | E25: =(COUNTIFS('LEAD MQL TRACKER'!$AH$5:$AH$1004,1)+SUMIFS('EMAIL MARKETING'!$Q$5:$Q$804,'EMAIL MARKETING'!$Y$5:$Y$804,1)+SUMIFS('PAID MEDIA ADS'!$M$5:$M$804,'PAID MEDIA ADS'!$V$5:$V$804,1)+SUMIFS('LINKEDIN OUTREACH'!$N$5:$N$704,'LINKEDIN OUTREACH'!$T$5:$T$704,1)+SUMIFS('WEBSITE CONTENT SEO'!$L$5:$L$804,'WEBSITE CONTENT SEO'!$W$5:$W$804,1)) -> 0 | F25: ="n/a" -> n/a | H25: =IFERROR(E25/$E$25,"–") -> –
B26: MQLs | E26: =(COUNTIFS('LEAD MQL TRACKER'!$AH$5:$AH$1004,1,'LEAD MQL TRACKER'!$AD$5:$AD$1004,1)+SUMIFS('EMAIL MARKETING'!$R$5:$R$804,'EMAIL MARKETING'!$Y$5:$Y$804,1)+SUMIFS('PAID MEDIA ADS'!$N$5:$N$804,'PAID MEDIA ADS'!$V$5:$V$804,1)+SUMIFS('LINKEDIN OUTREACH'!$O$5:$O$704,'LINKEDIN OUTREACH'!$T$5:$T$704,1)) -> 0 | F26: =IFERROR(E26/E25,"–") -> – | H26: =IFERROR(E26/$E$25,"–") -> –
B27: SQLs | E27: =COUNTIFS('LEAD MQL TRACKER'!$AH$5:$AH$1004,1,'LEAD MQL TRACKER'!$AE$5:$AE$1004,1) -> 0 | F27: =IFERROR(E27/E26,"–") -> – | H27: =IFERROR(E27/$E$25,"–") -> –
B28: Opportunities | E28: =COUNTIFS('LEAD MQL TRACKER'!$AH$5:$AH$1004,1,'LEAD MQL TRACKER'!$AF$5:$AF$1004,1) -> 0 | F28: =IFERROR(E28/E27,"–") -> – | H28: =IFERROR(E28/$E$25,"–") -> –
B29: Converted / Won | E29: =COUNTIFS('LEAD MQL TRACKER'!$AH$5:$AH$1004,1,'LEAD MQL TRACKER'!$AG$5:$AG$1004,1) -> 0 | F29: =IFERROR(E29/E28,"–") -> – | H29: =IFERROR(E29/$E$25,"–") -> –
B30: Handraisers are a subset of Leads; step conversion applies from Leads > MQL onwards. Leads include lead-level records plus channel summary counts (Email / Paid / LinkedIn / Web).
B32: TASKS BY STATUS (respects filters)
B33: Status | E33: Tasks | G33: % of Total
B34: Not Started | E34: =COUNTIFS('DAILY TASK TRACKER'!$AI$5:$AI$1504,1,'DAILY TASK TRACKER'!$M$5:$M$1504,"Not Started") -> 0 | G34: =IFERROR(E34/COUNTIFS('DAILY TASK TRACKER'!$AI$5:$AI$1504,1),"–") -> 0
B35: In Progress | E35: =COUNTIFS('DAILY TASK TRACKER'!$AI$5:$AI$1504,1,'DAILY TASK TRACKER'!$M$5:$M$1504,"In Progress") -> 0 | G35: =IFERROR(E35/COUNTIFS('DAILY TASK TRACKER'!$AI$5:$AI$1504,1),"–") -> 0
B36: Completed | E36: =COUNTIFS('DAILY TASK TRACKER'!$AI$5:$AI$1504,1,'DAILY TASK TRACKER'!$M$5:$M$1504,"Completed") -> 0 | G36: =IFERROR(E36/COUNTIFS('DAILY TASK TRACKER'!$AI$5:$AI$1504,1),"–") -> 0
B37: On Hold | E37: =COUNTIFS('DAILY TASK TRACKER'!$AI$5:$AI$1504,1,'DAILY TASK TRACKER'!$M$5:$M$1504,"On Hold") -> 0 | G37: =IFERROR(E37/COUNTIFS('DAILY TASK TRACKER'!$AI$5:$AI$1504,1),"–") -> 0
B38: Blocked | E38: =COUNTIFS('DAILY TASK TRACKER'!$AI$5:$AI$1504,1,'DAILY TASK TRACKER'!$M$5:$M$1504,"Blocked") -> 0 | G38: =IFERROR(E38/COUNTIFS('DAILY TASK TRACKER'!$AI$5:$AI$1504,1),"–") -> 0
B39: Cancelled | E39: =COUNTIFS('DAILY TASK TRACKER'!$AI$5:$AI$1504,1,'DAILY TASK TRACKER'!$M$5:$M$1504,"Cancelled") -> 0 | G39: =IFERROR(E39/COUNTIFS('DAILY TASK TRACKER'!$AI$5:$AI$1504,1),"–") -> 0
B40: Status Not Updated | E40: =COUNTIFS('DAILY TASK TRACKER'!$AI$5:$AI$1504,1)-SUM(E34:E39) -> 58 | G40: =IFERROR(E40/COUNTIFS('DAILY TASK TRACKER'!$AI$5:$AI$1504,1),"–") -> 1
B43: LEAD GENERATION SNAPSHOT (Q8 / Q9 - respects Client, Campaign, Team, Channel filters)
B44: Metric | E44: Yesterday | F44: Week to Date | G44: Month to Date | H44: Previous Month | I44: All Time
B45: Leads Generated | E45: =(COUNTIFS('LEAD MQL TRACKER'!$AI$5:$AI$1004,1,'LEAD MQL TRACKER'!$Z$5:$Z$1004,">="&(ReportDate-1),'LEAD MQL TRACKER'!$Z$5:$Z$1004,"<="&(ReportDate-1))+SUMIFS('EMAIL MARKETING'!$Q$5:$Q$804,'EMAIL MARKETING'!$Z$5:$Z$804,1,'EMAIL MARKETING'!$A$5:$A$804,">="&(ReportDate-1),'EMAIL MARKETING'!$A$5:$A$804,"<="&(ReportDate-1))+SUMIFS('PAID MEDIA ADS'!$M$5:$M$804,'PAID MEDIA ADS'!$W$5:$W$804,1,'PAID MEDIA ADS'!$A$5:$A$804,">="&(ReportDate-1),'PAID MEDIA ADS'!$A$5:$A$804,"<="&(ReportDate-1))+SUMIFS('LINKEDIN OUTREACH'!$N$5:$N$704,'LINKEDIN OUTREACH'!$U$5:$U$704,1,'LINKEDIN OUTREACH'!$A$5:$A$704,">="&(ReportDate-1),'LINKEDIN OUTREACH'!$A$5:$A$704,"<="&(ReportDate-1))+SUMIFS('WEBSITE CONTENT SEO'!$L$5:$L$804,'WEBSITE CONTENT SEO'!$X$5:$X$804,1,'WEBSITE CONTENT SEO'!$A$5:$A$804,">="&(ReportDate-1),'WEBSITE CONTENT SEO'!$A$5:$A$804,"<="&(ReportDate-1))) -> 0 | F45: =(COUNTIFS('LEAD MQL TRACKER'!$AI$5:$AI$1004,1,'LEAD MQL TRACKER'!$Z$5:$Z$1004,">="&(ReportDate-WEEKDAY(ReportDate,2)+1),'LEAD MQL TRACKER'!$Z$5:$Z$1004,"<="&(ReportDate))+SUMIFS('EMAIL MARKETING'!$Q$5:$Q$804,'EMAIL MARKETING'!$Z$5:$Z$804,1,'EMAIL MARKETING'!$A$5:$A$804,">="&(ReportDate-WEEKDAY(ReportDate,2)+1),'EMAIL MARKETING'!$A$5:$A$804,"<="&(ReportDate))+SUMIFS('PAID MEDIA ADS'!$M$5:$M$804,'PAID MEDIA ADS'!$W$5:$W$804,1,'PAID MEDIA ADS'!$A$5:$A$804,">="&(ReportDate-WEEKDAY(ReportDate,2)+1),'PAID MEDIA ADS'!$A$5:$A$804,"<="&(ReportDate))+SUMIFS('LINKEDIN OUTREACH'!$N$5:$N$704,'LINKEDIN OUTREACH'!$U$5:$U$704,1,'LINKEDIN OUTREACH'!$A$5:$A$704,">="&(ReportDate-WEEKDAY(ReportDate,2)+1),'LINKEDIN OUTREACH'!$A$5:$A$704,"<="&(ReportDate))+SUMIFS('WEBSITE CONTENT SEO'!$L$5:$L$804,'WEBSITE CONTENT SEO'!$X$5:$X$804,1,'WEBSITE CONTENT SEO'!$A$5:$A$804,">="&(ReportDate-WEEKDAY(ReportDate,2)+1),'WEBSITE CONTENT SEO'!$A$5:$A$804,"<="&(ReportDate))) -> 0 | G45: =(COUNTIFS('LEAD MQL TRACKER'!$AI$5:$AI$1004,1,'LEAD MQL TRACKER'!$Z$5:$Z$1004,">="&(DATE(YEAR(ReportDate),MONTH(ReportDate),1)),'LEAD MQL TRACKER'!$Z$5:$Z$1004,"<="&(ReportDate))+SUMIFS('EMAIL MARKETING'!$Q$5:$Q$804,'EMAIL MARKETING'!$Z$5:$Z$804,1,'EMAIL MARKETING'!$A$5:$A$804,">="&(DATE(YEAR(ReportDate),MONTH(ReportDate),1)),'EMAIL MARKETING'!$A$5:$A$804,"<="&(ReportDate))+SUMIFS('PAID MEDIA ADS'!$M$5:$M$804,'PAID MEDIA ADS'!$W$5:$W$804,1,'PAID MEDIA ADS'!$A$5:$A$804,">="&(DATE(YEAR(ReportDate),MONTH(ReportDate),1)),'PAID MEDIA ADS'!$A$5:$A$804,"<="&(ReportDate))+SUMIFS('LINKEDIN OUTREACH'!$N$5:$N$704,'LINKEDIN OUTREACH'!$U$5:$U$704,1,'LINKEDIN OUTREACH'!$A$5:$A$704,">="&(DATE(YEAR(ReportDate),MONTH(ReportDate),1)),'LINKEDIN OUTREACH'!$A$5:$A$704,"<="&(ReportDate))+SUMIFS('WEBSITE CONTENT SEO'!$L$5:$L$804,'WEBSITE CONTENT SEO'!$X$5:$X$804,1,'WEBSITE CONTENT SEO'!$A$5:$A$804,">="&(DATE(YEAR(ReportDate),MONTH(ReportDate),1)),'WEBSITE CONTENT SEO'!$A$5:$A$804,"<="&(ReportDate))) -> 0 | H45: =(COUNTIFS('LEAD MQL TRACKER'!$AI$5:$AI$1004,1,'LEAD MQL TRACKER'!$Z$5:$Z$1004,">="&(EDATE(DATE(YEAR(ReportDate),MONTH(ReportDate),1),-1)),'LEAD MQL TRACKER'!$Z$5:$Z$1004,"<="&(DATE(YEAR(ReportDate),MONTH(ReportDate),1)-1))+SUMIFS('EMAIL MARKETING'!$Q$5:$Q$804,'EMAIL MARKETING'!$Z$5:$Z$804,1,'EMAIL MARKETING'!$A$5:$A$804,">="&(EDATE(DATE(YEAR(ReportDate),MONTH(ReportDate),1),-1)),'EMAIL MARKETING'!$A$5:$A$804,"<="&(DATE(YEAR(ReportDate),MONTH(ReportDate),1)-1))+SUMIFS('PAID MEDIA ADS'!$M$5:$M$804,'PAID MEDIA ADS'!$W$5:$W$804,1,'PAID MEDIA ADS'!$A$5:$A$804,">="&(EDATE(DATE(YEAR(ReportDate),MONTH(ReportDate),1),-1)),'PAID MEDIA ADS'!$A$5:$A$804,"<="&(DATE(YEAR(ReportDate),MONTH(ReportDate),1)-1))+SUMIFS('LINKEDIN OUTREACH'!$N$5:$N$704,'LINKEDIN OUTREACH'!$U$5:$U$704,1,'LINKEDIN OUTREACH'!$A$5:$A$704,">="&(EDATE(DATE(YEAR(ReportDate),MONTH(ReportDate),1),-1)),'LINKEDIN OUTREACH'!$A$5:$A$704,"<="&(DATE(YEAR(ReportDate),MONTH(ReportDate),1)-1))+SUMIFS('WEBSITE CONTENT SEO'!$L$5:$L$804,'WEBSITE CONTENT SEO'!$X$5:$X$804,1,'WEBSITE CONTENT SEO'!$A$5:$A$804,">="&(EDATE(DATE(YEAR(ReportDate),MONTH(ReportDate),1),-1)),'WEBSITE CONTENT SEO'!$A$5:$A$804,"<="&(DATE(YEAR(ReportDate),MONTH(ReportDate),1)-1))) -> 0 | I45: =(COUNTIFS('LEAD MQL TRACKER'!$AI$5:$AI$1004,1)+SUMIFS('EMAIL MARKETING'!$Q$5:$Q$804,'EMAIL MARKETING'!$Z$5:$Z$804,1)+SUMIFS('PAID MEDIA ADS'!$M$5:$M$804,'PAID MEDIA ADS'!$W$5:$W$804,1)+SUMIFS('LINKEDIN OUTREACH'!$N$5:$N$704,'LINKEDIN OUTREACH'!$U$5:$U$704,1)+SUMIFS('WEBSITE CONTENT SEO'!$L$5:$L$804,'WEBSITE CONTENT SEO'!$X$5:$X$804,1)) -> 0
B46: Digital Handraisers | E46: =(COUNTIFS('LEAD MQL TRACKER'!$AI$5:$AI$1004,1,'LEAD MQL TRACKER'!$Z$5:$Z$1004,">="&(ReportDate-1),'LEAD MQL TRACKER'!$Z$5:$Z$1004,"<="&(ReportDate-1),'LEAD MQL TRACKER'!$AC$5:$AC$1004,1)+SUMIFS('LINKEDIN OUTREACH'!$M$5:$M$704,'LINKEDIN OUTREACH'!$U$5:$U$704,1,'LINKEDIN OUTREACH'!$A$5:$A$704,">="&(ReportDate-1),'LINKEDIN OUTREACH'!$A$5:$A$704,"<="&(ReportDate-1))) -> 0 | F46: =(COUNTIFS('LEAD MQL TRACKER'!$AI$5:$AI$1004,1,'LEAD MQL TRACKER'!$Z$5:$Z$1004,">="&(ReportDate-WEEKDAY(ReportDate,2)+1),'LEAD MQL TRACKER'!$Z$5:$Z$1004,"<="&(ReportDate),'LEAD MQL TRACKER'!$AC$5:$AC$1004,1)+SUMIFS('LINKEDIN OUTREACH'!$M$5:$M$704,'LINKEDIN OUTREACH'!$U$5:$U$704,1,'LINKEDIN OUTREACH'!$A$5:$A$704,">="&(ReportDate-WEEKDAY(ReportDate,2)+1),'LINKEDIN OUTREACH'!$A$5:$A$704,"<="&(ReportDate))) -> 0 | G46: =(COUNTIFS('LEAD MQL TRACKER'!$AI$5:$AI$1004,1,'LEAD MQL TRACKER'!$Z$5:$Z$1004,">="&(DATE(YEAR(ReportDate),MONTH(ReportDate),1)),'LEAD MQL TRACKER'!$Z$5:$Z$1004,"<="&(ReportDate),'LEAD MQL TRACKER'!$AC$5:$AC$1004,1)+SUMIFS('LINKEDIN OUTREACH'!$M$5:$M$704,'LINKEDIN OUTREACH'!$U$5:$U$704,1,'LINKEDIN OUTREACH'!$A$5:$A$704,">="&(DATE(YEAR(ReportDate),MONTH(ReportDate),1)),'LINKEDIN OUTREACH'!$A$5:$A$704,"<="&(ReportDate))) -> 0 | H46: =(COUNTIFS('LEAD MQL TRACKER'!$AI$5:$AI$1004,1,'LEAD MQL TRACKER'!$Z$5:$Z$1004,">="&(EDATE(DATE(YEAR(ReportDate),MONTH(ReportDate),1),-1)),'LEAD MQL TRACKER'!$Z$5:$Z$1004,"<="&(DATE(YEAR(ReportDate),MONTH(ReportDate),1)-1),'LEAD MQL TRACKER'!$AC$5:$AC$1004,1)+SUMIFS('LINKEDIN OUTREACH'!$M$5:$M$704,'LINKEDIN OUTREACH'!$U$5:$U$704,1,'LINKEDIN OUTREACH'!$A$5:$A$704,">="&(EDATE(DATE(YEAR(ReportDate),MONTH(ReportDate),1),-1)),'LINKEDIN OUTREACH'!$A$5:$A$704,"<="&(DATE(YEAR(ReportDate),MONTH(ReportDate),1)-1))) -> 0 | I46: =(COUNTIFS('LEAD MQL TRACKER'!$AI$5:$AI$1004,1,'LEAD MQL TRACKER'!$AC$5:$AC$1004,1)+SUMIFS('LINKEDIN OUTREACH'!$M$5:$M$704,'LINKEDIN OUTREACH'!$U$5:$U$704,1)) -> 0
B47: MQLs Generated | E47: =(COUNTIFS('LEAD MQL TRACKER'!$AI$5:$AI$1004,1,'LEAD MQL TRACKER'!$Z$5:$Z$1004,">="&(ReportDate-1),'LEAD MQL TRACKER'!$Z$5:$Z$1004,"<="&(ReportDate-1),'LEAD MQL TRACKER'!$AD$5:$AD$1004,1)+SUMIFS('EMAIL MARKETING'!$R$5:$R$804,'EMAIL MARKETING'!$Z$5:$Z$804,1,'EMAIL MARKETING'!$A$5:$A$804,">="&(ReportDate-1),'EMAIL MARKETING'!$A$5:$A$804,"<="&(ReportDate-1))+SUMIFS('PAID MEDIA ADS'!$N$5:$N$804,'PAID MEDIA ADS'!$W$5:$W$804,1,'PAID MEDIA ADS'!$A$5:$A$804,">="&(ReportDate-1),'PAID MEDIA ADS'!$A$5:$A$804,"<="&(ReportDate-1))+SUMIFS('LINKEDIN OUTREACH'!$O$5:$O$704,'LINKEDIN OUTREACH'!$U$5:$U$704,1,'LINKEDIN OUTREACH'!$A$5:$A$704,">="&(ReportDate-1),'LINKEDIN OUTREACH'!$A$5:$A$704,"<="&(ReportDate-1))) -> 0 | F47: =(COUNTIFS('LEAD MQL TRACKER'!$AI$5:$AI$1004,1,'LEAD MQL TRACKER'!$Z$5:$Z$1004,">="&(ReportDate-WEEKDAY(ReportDate,2)+1),'LEAD MQL TRACKER'!$Z$5:$Z$1004,"<="&(ReportDate),'LEAD MQL TRACKER'!$AD$5:$AD$1004,1)+SUMIFS('EMAIL MARKETING'!$R$5:$R$804,'EMAIL MARKETING'!$Z$5:$Z$804,1,'EMAIL MARKETING'!$A$5:$A$804,">="&(ReportDate-WEEKDAY(ReportDate,2)+1),'EMAIL MARKETING'!$A$5:$A$804,"<="&(ReportDate))+SUMIFS('PAID MEDIA ADS'!$N$5:$N$804,'PAID MEDIA ADS'!$W$5:$W$804,1,'PAID MEDIA ADS'!$A$5:$A$804,">="&(ReportDate-WEEKDAY(ReportDate,2)+1),'PAID MEDIA ADS'!$A$5:$A$804,"<="&(ReportDate))+SUMIFS('LINKEDIN OUTREACH'!$O$5:$O$704,'LINKEDIN OUTREACH'!$U$5:$U$704,1,'LINKEDIN OUTREACH'!$A$5:$A$704,">="&(ReportDate-WEEKDAY(ReportDate,2)+1),'LINKEDIN OUTREACH'!$A$5:$A$704,"<="&(ReportDate))) -> 0 | G47: =(COUNTIFS('LEAD MQL TRACKER'!$AI$5:$AI$1004,1,'LEAD MQL TRACKER'!$Z$5:$Z$1004,">="&(DATE(YEAR(ReportDate),MONTH(ReportDate),1)),'LEAD MQL TRACKER'!$Z$5:$Z$1004,"<="&(ReportDate),'LEAD MQL TRACKER'!$AD$5:$AD$1004,1)+SUMIFS('EMAIL MARKETING'!$R$5:$R$804,'EMAIL MARKETING'!$Z$5:$Z$804,1,'EMAIL MARKETING'!$A$5:$A$804,">="&(DATE(YEAR(ReportDate),MONTH(ReportDate),1)),'EMAIL MARKETING'!$A$5:$A$804,"<="&(ReportDate))+SUMIFS('PAID MEDIA ADS'!$N$5:$N$804,'PAID MEDIA ADS'!$W$5:$W$804,1,'PAID MEDIA ADS'!$A$5:$A$804,">="&(DATE(YEAR(ReportDate),MONTH(ReportDate),1)),'PAID MEDIA ADS'!$A$5:$A$804,"<="&(ReportDate))+SUMIFS('LINKEDIN OUTREACH'!$O$5:$O$704,'LINKEDIN OUTREACH'!$U$5:$U$704,1,'LINKEDIN OUTREACH'!$A$5:$A$704,">="&(DATE(YEAR(ReportDate),MONTH(ReportDate),1)),'LINKEDIN OUTREACH'!$A$5:$A$704,"<="&(ReportDate))) -> 0 | H47: =(COUNTIFS('LEAD MQL TRACKER'!$AI$5:$AI$1004,1,'LEAD MQL TRACKER'!$Z$5:$Z$1004,">="&(EDATE(DATE(YEAR(ReportDate),MONTH(ReportDate),1),-1)),'LEAD MQL TRACKER'!$Z$5:$Z$1004,"<="&(DATE(YEAR(ReportDate),MONTH(ReportDate),1)-1),'LEAD MQL TRACKER'!$AD$5:$AD$1004,1)+SUMIFS('EMAIL MARKETING'!$R$5:$R$804,'EMAIL MARKETING'!$Z$5:$Z$804,1,'EMAIL MARKETING'!$A$5:$A$804,">="&(EDATE(DATE(YEAR(ReportDate),MONTH(ReportDate),1),-1)),'EMAIL MARKETING'!$A$5:$A$804,"<="&(DATE(YEAR(ReportDate),MONTH(ReportDate),1)-1))+SUMIFS('PAID MEDIA ADS'!$N$5:$N$804,'PAID MEDIA ADS'!$W$5:$W$804,1,'PAID MEDIA ADS'!$A$5:$A$804,">="&(EDATE(DATE(YEAR(ReportDate),MONTH(ReportDate),1),-1)),'PAID MEDIA ADS'!$A$5:$A$804,"<="&(DATE(YEAR(ReportDate),MONTH(ReportDate),1)-1))+SUMIFS('LINKEDIN OUTREACH'!$O$5:$O$704,'LINKEDIN OUTREACH'!$U$5:$U$704,1,'LINKEDIN OUTREACH'!$A$5:$A$704,">="&(EDATE(DATE(YEAR(ReportDate),MONTH(ReportDate),1),-1)),'LINKEDIN OUTREACH'!$A$5:$A$704,"<="&(DATE(YEAR(ReportDate),MONTH(ReportDate),1)-1))) -> 0 | I47: =(COUNTIFS('LEAD MQL TRACKER'!$AI$5:$AI$1004,1,'LEAD MQL TRACKER'!$AD$5:$AD$1004,1)+SUMIFS('EMAIL MARKETING'!$R$5:$R$804,'EMAIL MARKETING'!$Z$5:$Z$804,1)+SUMIFS('PAID MEDIA ADS'!$N$5:$N$804,'PAID MEDIA ADS'!$W$5:$W$804,1)+SUMIFS('LINKEDIN OUTREACH'!$O$5:$O$704,'LINKEDIN OUTREACH'!$U$5:$U$704,1)) -> 0
B48: SQLs Generated | E48: =COUNTIFS('LEAD MQL TRACKER'!$AI$5:$AI$1004,1,'LEAD MQL TRACKER'!$Z$5:$Z$1004,">="&(ReportDate-1),'LEAD MQL TRACKER'!$Z$5:$Z$1004,"<="&(ReportDate-1),'LEAD MQL TRACKER'!$AE$5:$AE$1004,1) -> 0 | F48: =COUNTIFS('LEAD MQL TRACKER'!$AI$5:$AI$1004,1,'LEAD MQL TRACKER'!$Z$5:$Z$1004,">="&(ReportDate-WEEKDAY(ReportDate,2)+1),'LEAD MQL TRACKER'!$Z$5:$Z$1004,"<="&(ReportDate),'LEAD MQL TRACKER'!$AE$5:$AE$1004,1) -> 0 | G48: =COUNTIFS('LEAD MQL TRACKER'!$AI$5:$AI$1004,1,'LEAD MQL TRACKER'!$Z$5:$Z$1004,">="&(DATE(YEAR(ReportDate),MONTH(ReportDate),1)),'LEAD MQL TRACKER'!$Z$5:$Z$1004,"<="&(ReportDate),'LEAD MQL TRACKER'!$AE$5:$AE$1004,1) -> 0 | H48: =COUNTIFS('LEAD MQL TRACKER'!$AI$5:$AI$1004,1,'LEAD MQL TRACKER'!$Z$5:$Z$1004,">="&(EDATE(DATE(YEAR(ReportDate),MONTH(ReportDate),1),-1)),'LEAD MQL TRACKER'!$Z$5:$Z$1004,"<="&(DATE(YEAR(ReportDate),MONTH(ReportDate),1)-1),'LEAD MQL TRACKER'!$AE$5:$AE$1004,1) -> 0 | I48: =COUNTIFS('LEAD MQL TRACKER'!$AI$5:$AI$1004,1,'LEAD MQL TRACKER'!$AE$5:$AE$1004,1) -> 0
B49: Opportunities | E49: =COUNTIFS('LEAD MQL TRACKER'!$AI$5:$AI$1004,1,'LEAD MQL TRACKER'!$Z$5:$Z$1004,">="&(ReportDate-1),'LEAD MQL TRACKER'!$Z$5:$Z$1004,"<="&(ReportDate-1),'LEAD MQL TRACKER'!$AF$5:$AF$1004,1) -> 0 | F49: =COUNTIFS('LEAD MQL TRACKER'!$AI$5:$AI$1004,1,'LEAD MQL TRACKER'!$Z$5:$Z$1004,">="&(ReportDate-WEEKDAY(ReportDate,2)+1),'LEAD MQL TRACKER'!$Z$5:$Z$1004,"<="&(ReportDate),'LEAD MQL TRACKER'!$AF$5:$AF$1004,1) -> 0 | G49: =COUNTIFS('LEAD MQL TRACKER'!$AI$5:$AI$1004,1,'LEAD MQL TRACKER'!$Z$5:$Z$1004,">="&(DATE(YEAR(ReportDate),MONTH(ReportDate),1)),'LEAD MQL TRACKER'!$Z$5:$Z$1004,"<="&(ReportDate),'LEAD MQL TRACKER'!$AF$5:$AF$1004,1) -> 0 | H49: =COUNTIFS('LEAD MQL TRACKER'!$AI$5:$AI$1004,1,'LEAD MQL TRACKER'!$Z$5:$Z$1004,">="&(EDATE(DATE(YEAR(ReportDate),MONTH(ReportDate),1),-1)),'LEAD MQL TRACKER'!$Z$5:$Z$1004,"<="&(DATE(YEAR(ReportDate),MONTH(ReportDate),1)-1),'LEAD MQL TRACKER'!$AF$5:$AF$1004,1) -> 0 | I49: =COUNTIFS('LEAD MQL TRACKER'!$AI$5:$AI$1004,1,'LEAD MQL TRACKER'!$AF$5:$AF$1004,1) -> 0
B52: MANAGEMENT ATTENTION - DAILY REVIEW
B53: Q1. What did the team complete yesterday? | K53: Q2. What is planned for today?
B54: Team Member | C54: Client | D54: Task | H54: Output / Result | K54: Team Member | L54: Client | M54: Task | P54: Priority | Q54: Status | R54: Due
B55: =IFERROR(IF(INDEX('DAILY TASK TRACKER'!$B$5:$B$1504,MATCH(SMALL('DAILY TASK TRACKER'!$BG$5:$BG$1504,1),'DAILY TASK TRACKER'!$BG$5:$BG$1504,0))="","",INDEX('DAILY TASK TRACKER'!$B$5:$B$1504,MATCH(SMALL('DAILY TASK TRACKER'!$BG$5:$BG$1504,1),'DAILY TASK TRACKER'!$BG$5:$BG$1504,0))),"- none -") -> - none - | C55: =IFERROR(IF(INDEX('DAILY TASK TRACKER'!$C$5:$C$1504,MATCH(SMALL('DAILY TASK TRACKER'!$BG$5:$BG$1504,1),'DAILY TASK TRACKER'!$BG$5:$BG$1504,0))="","",INDEX('DAILY TASK TRACKER'!$C$5:$C$1504,MATCH(SMALL('DAILY TASK TRACKER'!$BG$5:$BG$1504,1),'DAILY TASK TRACKER'!$BG$5:$BG$1504,0))),"") | D55: =IFERROR(IF(INDEX('DAILY TASK TRACKER'!$G$5:$G$1504,MATCH(SMALL('DAILY TASK TRACKER'!$BG$5:$BG$1504,1),'DAILY TASK TRACKER'!$BG$5:$BG$1504,0))="","",INDEX('DAILY TASK TRACKER'!$G$5:$G$1504,MATCH(SMALL('DAILY TASK TRACKER'!$BG$5:$BG$1504,1),'DAILY TASK TRACKER'!$BG$5:$BG$1504,0))),"") | H55: =IFERROR(IF(INDEX('DAILY TASK TRACKER'!$O$5:$O$1504,MATCH(SMALL('DAILY TASK TRACKER'!$BG$5:$BG$1504,1),'DAILY TASK TRACKER'!$BG$5:$BG$1504,0))="","",INDEX('DAILY TASK TRACKER'!$O$5:$O$1504,MATCH(SMALL('DAILY TASK TRACKER'!$BG$5:$BG$1504,1),'DAILY TASK TRACKER'!$BG$5:$BG$1504,0))),"") | K55: =IFERROR(IF(INDEX('DAILY TASK TRACKER'!$B$5:$B$1504,MATCH(SMALL('DAILY TASK TRACKER'!$BE$5:$BE$1504,1),'DAILY TASK TRACKER'!$BE$5:$BE$1504,0))="","",INDEX('DAILY TASK TRACKER'!$B$5:$B$1504,MATCH(SMALL('DAILY TASK TRACKER'!$BE$5:$BE$1504,1),'DAILY TASK TRACKER'!$BE$5:$BE$1504,0))),"- none -") -> - none - | L55: =IFERROR(IF(INDEX('DAILY TASK TRACKER'!$C$5:$C$1504,MATCH(SMALL('DAILY TASK TRACKER'!$BE$5:$BE$1504,1),'DAILY TASK TRACKER'!$BE$5:$BE$1504,0))="","",INDEX('DAILY TASK TRACKER'!$C$5:$C$1504,MATCH(SMALL('DAILY TASK TRACKER'!$BE$5:$BE$1504,1),'DAILY TASK TRACKER'!$BE$5:$BE$1504,0))),"") | M55: =IFERROR(IF(INDEX('DAILY TASK TRACKER'!$G$5:$G$1504,MATCH(SMALL('DAILY TASK TRACKER'!$BE$5:$BE$1504,1),'DAILY TASK TRACKER'!$BE$5:$BE$1504,0))="","",INDEX('DAILY TASK TRACKER'!$G$5:$G$1504,MATCH(SMALL('DAILY TASK TRACKER'!$BE$5:$BE$1504,1),'DAILY TASK TRACKER'!$BE$5:$BE$1504,0))),"") | P55: =IFERROR(IF(INDEX('DAILY TASK TRACKER'!$I$5:$I$1504,MATCH(SMALL('DAILY TASK TRACKER'!$BE$5:$BE$1504,1),'DAILY TASK TRACKER'!$BE$5:$BE$1504,0))="","",INDEX('DAILY TASK TRACKER'!$I$5:$I$1504,MATCH(SMALL('DAILY TASK TRACKER'!$BE$5:$BE$1504,1),'DAILY TASK TRACKER'!$BE$5:$BE$1504,0))),"") | Q55: =IFERROR(IF(INDEX('DAILY TASK TRACKER'!$M$5:$M$1504,MATCH(SMALL('DAILY TASK TRACKER'!$BE$5:$BE$1504,1),'DAILY TASK TRACKER'!$BE$5:$BE$1504,0))="","",INDEX('DAILY TASK TRACKER'!$M$5:$M$1504,MATCH(SMALL('DAILY TASK TRACKER'!$BE$5:$BE$1504,1),'DAILY TASK TRACKER'!$BE$5:$BE$1504,0))),"") | R55: =IFERROR(IF(INDEX('DAILY TASK TRACKER'!$L$5:$L$1504,MATCH(SMALL('DAILY TASK TRACKER'!$BE$5:$BE$1504,1),'DAILY TASK TRACKER'!$BE$5:$BE$1504,0))="","",INDEX('DAILY TASK TRACKER'!$L$5:$L$1504,MATCH(SMALL('DAILY TASK TRACKER'!$BE$5:$BE$1504,1),'DAILY TASK TRACKER'!$BE$5:$BE$1504,0))),"")
B56: =IFERROR(IF(INDEX('DAILY TASK TRACKER'!$B$5:$B$1504,MATCH(SMALL('DAILY TASK TRACKER'!$BG$5:$BG$1504,2),'DAILY TASK TRACKER'!$BG$5:$BG$1504,0))="","",INDEX('DAILY TASK TRACKER'!$B$5:$B$1504,MATCH(SMALL('DAILY TASK TRACKER'!$BG$5:$BG$1504,2),'DAILY TASK TRACKER'!$BG$5:$BG$1504,0))),"") | C56: =IFERROR(IF(INDEX('DAILY TASK TRACKER'!$C$5:$C$1504,MATCH(SMALL('DAILY TASK TRACKER'!$BG$5:$BG$1504,2),'DAILY TASK TRACKER'!$BG$5:$BG$1504,0))="","",INDEX('DAILY TASK TRACKER'!$C$5:$C$1504,MATCH(SMALL('DAILY TASK TRACKER'!$BG$5:$BG$1504,2),'DAILY TASK TRACKER'!$BG$5:$BG$1504,0))),"") | D56: =IFERROR(IF(INDEX('DAILY TASK TRACKER'!$G$5:$G$1504,MATCH(SMALL('DAILY TASK TRACKER'!$BG$5:$BG$1504,2),'DAILY TASK TRACKER'!$BG$5:$BG$1504,0))="","",INDEX('DAILY TASK TRACKER'!$G$5:$G$1504,MATCH(SMALL('DAILY TASK TRACKER'!$BG$5:$BG$1504,2),'DAILY TASK TRACKER'!$BG$5:$BG$1504,0))),"") | H56: =IFERROR(IF(INDEX('DAILY TASK TRACKER'!$O$5:$O$1504,MATCH(SMALL('DAILY TASK TRACKER'!$BG$5:$BG$1504,2),'DAILY TASK TRACKER'!$BG$5:$BG$1504,0))="","",INDEX('DAILY TASK TRACKER'!$O$5:$O$1504,MATCH(SMALL('DAILY TASK TRACKER'!$BG$5:$BG$1504,2),'DAILY TASK TRACKER'!$BG$5:$BG$1504,0))),"") | K56: =IFERROR(IF(INDEX('DAILY TASK TRACKER'!$B$5:$B$1504,MATCH(SMALL('DAILY TASK TRACKER'!$BE$5:$BE$1504,2),'DAILY TASK TRACKER'!$BE$5:$BE$1504,0))="","",INDEX('DAILY TASK TRACKER'!$B$5:$B$1504,MATCH(SMALL('DAILY TASK TRACKER'!$BE$5:$BE$1504,2),'DAILY TASK TRACKER'!$BE$5:$BE$1504,0))),"") | L56: =IFERROR(IF(INDEX('DAILY TASK TRACKER'!$C$5:$C$1504,MATCH(SMALL('DAILY TASK TRACKER'!$BE$5:$BE$1504,2),'DAILY TASK TRACKER'!$BE$5:$BE$1504,0))="","",INDEX('DAILY TASK TRACKER'!$C$5:$C$1504,MATCH(SMALL('DAILY TASK TRACKER'!$BE$5:$BE$1504,2),'DAILY TASK TRACKER'!$BE$5:$BE$1504,0))),"") | M56: =IFERROR(IF(INDEX('DAILY TASK TRACKER'!$G$5:$G$1504,MATCH(SMALL('DAILY TASK TRACKER'!$BE$5:$BE$1504,2),'DAILY TASK TRACKER'!$BE$5:$BE$1504,0))="","",INDEX('DAILY TASK TRACKER'!$G$5:$G$1504,MATCH(SMALL('DAILY TASK TRACKER'!$BE$5:$BE$1504,2),'DAILY TASK TRACKER'!$BE$5:$BE$1504,0))),"") | P56: =IFERROR(IF(INDEX('DAILY TASK TRACKER'!$I$5:$I$1504,MATCH(SMALL('DAILY TASK TRACKER'!$BE$5:$BE$1504,2),'DAILY TASK TRACKER'!$BE$5:$BE$1504,0))="","",INDEX('DAILY TASK TRACKER'!$I$5:$I$1504,MATCH(SMALL('DAILY TASK TRACKER'!$BE$5:$BE$1504,2),'DAILY TASK TRACKER'!$BE$5:$BE$1504,0))),"") | Q56: =IFERROR(IF(INDEX('DAILY TASK TRACKER'!$M$5:$M$1504,MATCH(SMALL('DAILY TASK TRACKER'!$BE$5:$BE$1504,2),'DAILY TASK TRACKER'!$BE$5:$BE$1504,0))="","",INDEX('DAILY TASK TRACKER'!$M$5:$M$1504,MATCH(SMALL('DAILY TASK TRACKER'!$BE$5:$BE$1504,2),'DAILY TASK TRACKER'!$BE$5:$BE$1504,0))),"") | R56: =IFERROR(IF(INDEX('DAILY TASK TRACKER'!$L$5:$L$1504,MATCH(SMALL('DAILY TASK TRACKER'!$BE$5:$BE$1504,2),'DAILY TASK TRACKER'!$BE$5:$BE$1504,0))="","",INDEX('DAILY TASK TRACKER'!$L$5:$L$1504,MATCH(SMALL('DAILY TASK TRACKER'!$BE$5:$BE$1504,2),'DAILY TASK TRACKER'!$BE$5:$BE$1504,0))),"")
B57: =IFERROR(IF(INDEX('DAILY TASK TRACKER'!$B$5:$B$1504,MATCH(SMALL('DAILY TASK TRACKER'!$BG$5:$BG$1504,3),'DAILY TASK TRACKER'!$BG$5:$BG$1504,0))="","",INDEX('DAILY TASK TRACKER'!$B$5:$B$1504,MATCH(SMALL('DAILY TASK TRACKER'!$BG$5:$BG$1504,3),'DAILY TASK TRACKER'!$BG$5:$BG$1504,0))),"") | C57: =IFERROR(IF(INDEX('DAILY TASK TRACKER'!$C$5:$C$1504,MATCH(SMALL('DAILY TASK TRACKER'!$BG$5:$BG$1504,3),'DAILY TASK TRACKER'!$BG$5:$BG$1504,0))="","",INDEX('DAILY TASK TRACKER'!$C$5:$C$1504,MATCH(SMALL('DAILY TASK TRACKER'!$BG$5:$BG$1504,3),'DAILY TASK TRACKER'!$BG$5:$BG$1504,0))),"") | D57: =IFERROR(IF(INDEX('DAILY TASK TRACKER'!$G$5:$G$1504,MATCH(SMALL('DAILY TASK TRACKER'!$BG$5:$BG$1504,3),'DAILY TASK TRACKER'!$BG$5:$BG$1504,0))="","",INDEX('DAILY TASK TRACKER'!$G$5:$G$1504,MATCH(SMALL('DAILY TASK TRACKER'!$BG$5:$BG$1504,3),'DAILY TASK TRACKER'!$BG$5:$BG$1504,0))),"") | H57: =IFERROR(IF(INDEX('DAILY TASK TRACKER'!$O$5:$O$1504,MATCH(SMALL('DAILY TASK TRACKER'!$BG$5:$BG$1504,3),'DAILY TASK TRACKER'!$BG$5:$BG$1504,0))="","",INDEX('DAILY TASK TRACKER'!$O$5:$O$1504,MATCH(SMALL('DAILY TASK TRACKER'!$BG$5:$BG$1504,3),'DAILY TASK TRACKER'!$BG$5:$BG$1504,0))),"") | K57: =IFERROR(IF(INDEX('DAILY TASK TRACKER'!$B$5:$B$1504,MATCH(SMALL('DAILY TASK TRACKER'!$BE$5:$BE$1504,3),'DAILY TASK TRACKER'!$BE$5:$BE$1504,0))="","",INDEX('DAILY TASK TRACKER'!$B$5:$B$1504,MATCH(SMALL('DAILY TASK TRACKER'!$BE$5:$BE$1504,3),'DAILY TASK TRACKER'!$BE$5:$BE$1504,0))),"") | L57: =IFERROR(IF(INDEX('DAILY TASK TRACKER'!$C$5:$C$1504,MATCH(SMALL('DAILY TASK TRACKER'!$BE$5:$BE$1504,3),'DAILY TASK TRACKER'!$BE$5:$BE$1504,0))="","",INDEX('DAILY TASK TRACKER'!$C$5:$C$1504,MATCH(SMALL('DAILY TASK TRACKER'!$BE$5:$BE$1504,3),'DAILY TASK TRACKER'!$BE$5:$BE$1504,0))),"") | M57: =IFERROR(IF(INDEX('DAILY TASK TRACKER'!$G$5:$G$1504,MATCH(SMALL('DAILY TASK TRACKER'!$BE$5:$BE$1504,3),'DAILY TASK TRACKER'!$BE$5:$BE$1504,0))="","",INDEX('DAILY TASK TRACKER'!$G$5:$G$1504,MATCH(SMALL('DAILY TASK TRACKER'!$BE$5:$BE$1504,3),'DAILY TASK TRACKER'!$BE$5:$BE$1504,0))),"") | P57: =IFERROR(IF(INDEX('DAILY TASK TRACKER'!$I$5:$I$1504,MATCH(SMALL('DAILY TASK TRACKER'!$BE$5:$BE$1504,3),'DAILY TASK TRACKER'!$BE$5:$BE$1504,0))="","",INDEX('DAILY TASK TRACKER'!$I$5:$I$1504,MATCH(SMALL('DAILY TASK TRACKER'!$BE$5:$BE$1504,3),'DAILY TASK TRACKER'!$BE$5:$BE$1504,0))),"") | Q57: =IFERROR(IF(INDEX('DAILY TASK TRACKER'!$M$5:$M$1504,MATCH(SMALL('DAILY TASK TRACKER'!$BE$5:$BE$1504,3),'DAILY TASK TRACKER'!$BE$5:$BE$1504,0))="","",INDEX('DAILY TASK TRACKER'!$M$5:$M$1504,MATCH(SMALL('DAILY TASK TRACKER'!$BE$5:$BE$1504,3),'DAILY TASK TRACKER'!$BE$5:$BE$1504,0))),"") | R57: =IFERROR(IF(INDEX('DAILY TASK TRACKER'!$L$5:$L$1504,MATCH(SMALL('DAILY TASK TRACKER'!$BE$5:$BE$1504,3),'DAILY TASK TRACKER'!$BE$5:$BE$1504,0))="","",INDEX('DAILY TASK TRACKER'!$L$5:$L$1504,MATCH(SMALL('DAILY TASK TRACKER'!$BE$5:$BE$1504,3),'DAILY TASK TRACKER'!$BE$5:$BE$1504,0))),"")
B58: =IFERROR(IF(INDEX('DAILY TASK TRACKER'!$B$5:$B$1504,MATCH(SMALL('DAILY TASK TRACKER'!$BG$5:$BG$1504,4),'DAILY TASK TRACKER'!$BG$5:$BG$1504,0))="","",INDEX('DAILY TASK TRACKER'!$B$5:$B$1504,MATCH(SMALL('DAILY TASK TRACKER'!$BG$5:$BG$1504,4),'DAILY TASK TRACKER'!$BG$5:$BG$1504,0))),"") | C58: =IFERROR(IF(INDEX('DAILY TASK TRACKER'!$C$5:$C$1504,MATCH(SMALL('DAILY TASK TRACKER'!$BG$5:$BG$1504,4),'DAILY TASK TRACKER'!$BG$5:$BG$1504,0))="","",INDEX('DAILY TASK TRACKER'!$C$5:$C$1504,MATCH(SMALL('DAILY TASK TRACKER'!$BG$5:$BG$1504,4),'DAILY TASK TRACKER'!$BG$5:$BG$1504,0))),"") | D58: =IFERROR(IF(INDEX('DAILY TASK TRACKER'!$G$5:$G$1504,MATCH(SMALL('DAILY TASK TRACKER'!$BG$5:$BG$1504,4),'DAILY TASK TRACKER'!$BG$5:$BG$1504,0))="","",INDEX('DAILY TASK TRACKER'!$G$5:$G$1504,MATCH(SMALL('DAILY TASK TRACKER'!$BG$5:$BG$1504,4),'DAILY TASK TRACKER'!$BG$5:$BG$1504,0))),"") | H58: =IFERROR(IF(INDEX('DAILY TASK TRACKER'!$O$5:$O$1504,MATCH(SMALL('DAILY TASK TRACKER'!$BG$5:$BG$1504,4),'DAILY TASK TRACKER'!$BG$5:$BG$1504,0))="","",INDEX('DAILY TASK TRACKER'!$O$5:$O$1504,MATCH(SMALL('DAILY TASK TRACKER'!$BG$5:$BG$1504,4),'DAILY TASK TRACKER'!$BG$5:$BG$1504,0))),"") | K58: =IFERROR(IF(INDEX('DAILY TASK TRACKER'!$B$5:$B$1504,MATCH(SMALL('DAILY TASK TRACKER'!$BE$5:$BE$1504,4),'DAILY TASK TRACKER'!$BE$5:$BE$1504,0))="","",INDEX('DAILY TASK TRACKER'!$B$5:$B$1504,MATCH(SMALL('DAILY TASK TRACKER'!$BE$5:$BE$1504,4),'DAILY TASK TRACKER'!$BE$5:$BE$1504,0))),"") | L58: =IFERROR(IF(INDEX('DAILY TASK TRACKER'!$C$5:$C$1504,MATCH(SMALL('DAILY TASK TRACKER'!$BE$5:$BE$1504,4),'DAILY TASK TRACKER'!$BE$5:$BE$1504,0))="","",INDEX('DAILY TASK TRACKER'!$C$5:$C$1504,MATCH(SMALL('DAILY TASK TRACKER'!$BE$5:$BE$1504,4),'DAILY TASK TRACKER'!$BE$5:$BE$1504,0))),"") | M58: =IFERROR(IF(INDEX('DAILY TASK TRACKER'!$G$5:$G$1504,MATCH(SMALL('DAILY TASK TRACKER'!$BE$5:$BE$1504,4),'DAILY TASK TRACKER'!$BE$5:$BE$1504,0))="","",INDEX('DAILY TASK TRACKER'!$G$5:$G$1504,MATCH(SMALL('DAILY TASK TRACKER'!$BE$5:$BE$1504,4),'DAILY TASK TRACKER'!$BE$5:$BE$1504,0))),"") | P58: =IFERROR(IF(INDEX('DAILY TASK TRACKER'!$I$5:$I$1504,MATCH(SMALL('DAILY TASK TRACKER'!$BE$5:$BE$1504,4),'DAILY TASK TRACKER'!$BE$5:$BE$1504,0))="","",INDEX('DAILY TASK TRACKER'!$I$5:$I$1504,MATCH(SMALL('DAILY TASK TRACKER'!$BE$5:$BE$1504,4),'DAILY TASK TRACKER'!$BE$5:$BE$1504,0))),"") | Q58: =IFERROR(IF(INDEX('DAILY TASK TRACKER'!$M$5:$M$1504,MATCH(SMALL('DAILY TASK TRACKER'!$BE$5:$BE$1504,4),'DAILY TASK TRACKER'!$BE$5:$BE$1504,0))="","",INDEX('DAILY TASK TRACKER'!$M$5:$M$1504,MATCH(SMALL('DAILY TASK TRACKER'!$BE$5:$BE$1504,4),'DAILY TASK TRACKER'!$BE$5:$BE$1504,0))),"") | R58: =IFERROR(IF(INDEX('DAILY TASK TRACKER'!$L$5:$L$1504,MATCH(SMALL('DAILY TASK TRACKER'!$BE$5:$BE$1504,4),'DAILY TASK TRACKER'!$BE$5:$BE$1504,0))="","",INDEX('DAILY TASK TRACKER'!$L$5:$L$1504,MATCH(SMALL('DAILY TASK TRACKER'!$BE$5:$BE$1504,4),'DAILY TASK TRACKER'!$BE$5:$BE$1504,0))),"")
B59: =IFERROR(IF(INDEX('DAILY TASK TRACKER'!$B$5:$B$1504,MATCH(SMALL('DAILY TASK TRACKER'!$BG$5:$BG$1504,5),'DAILY TASK TRACKER'!$BG$5:$BG$1504,0))="","",INDEX('DAILY TASK TRACKER'!$B$5:$B$1504,MATCH(SMALL('DAILY TASK TRACKER'!$BG$5:$BG$1504,5),'DAILY TASK TRACKER'!$BG$5:$BG$1504,0))),"") | C59: =IFERROR(IF(INDEX('DAILY TASK TRACKER'!$C$5:$C$1504,MATCH(SMALL('DAILY TASK TRACKER'!$BG$5:$BG$1504,5),'DAILY TASK TRACKER'!$BG$5:$BG$1504,0))="","",INDEX('DAILY TASK TRACKER'!$C$5:$C$1504,MATCH(SMALL('DAILY TASK TRACKER'!$BG$5:$BG$1504,5),'DAILY TASK TRACKER'!$BG$5:$BG$1504,0))),"") | D59: =IFERROR(IF(INDEX('DAILY TASK TRACKER'!$G$5:$G$1504,MATCH(SMALL('DAILY TASK TRACKER'!$BG$5:$BG$1504,5),'DAILY TASK TRACKER'!$BG$5:$BG$1504,0))="","",INDEX('DAILY TASK TRACKER'!$G$5:$G$1504,MATCH(SMALL('DAILY TASK TRACKER'!$BG$5:$BG$1504,5),'DAILY TASK TRACKER'!$BG$5:$BG$1504,0))),"") | H59: =IFERROR(IF(INDEX('DAILY TASK TRACKER'!$O$5:$O$1504,MATCH(SMALL('DAILY TASK TRACKER'!$BG$5:$BG$1504,5),'DAILY TASK TRACKER'!$BG$5:$BG$1504,0))="","",INDEX('DAILY TASK TRACKER'!$O$5:$O$1504,MATCH(SMALL('DAILY TASK TRACKER'!$BG$5:$BG$1504,5),'DAILY TASK TRACKER'!$BG$5:$BG$1504,0))),"") | K59: =IFERROR(IF(INDEX('DAILY TASK TRACKER'!$B$5:$B$1504,MATCH(SMALL('DAILY TASK TRACKER'!$BE$5:$BE$1504,5),'DAILY TASK TRACKER'!$BE$5:$BE$1504,0))="","",INDEX('DAILY TASK TRACKER'!$B$5:$B$1504,MATCH(SMALL('DAILY TASK TRACKER'!$BE$5:$BE$1504,5),'DAILY TASK TRACKER'!$BE$5:$BE$1504,0))),"") | L59: =IFERROR(IF(INDEX('DAILY TASK TRACKER'!$C$5:$C$1504,MATCH(SMALL('DAILY TASK TRACKER'!$BE$5:$BE$1504,5),'DAILY TASK TRACKER'!$BE$5:$BE$1504,0))="","",INDEX('DAILY TASK TRACKER'!$C$5:$C$1504,MATCH(SMALL('DAILY TASK TRACKER'!$BE$5:$BE$1504,5),'DAILY TASK TRACKER'!$BE$5:$BE$1504,0))),"") | M59: =IFERROR(IF(INDEX('DAILY TASK TRACKER'!$G$5:$G$1504,MATCH(SMALL('DAILY TASK TRACKER'!$BE$5:$BE$1504,5),'DAILY TASK TRACKER'!$BE$5:$BE$1504,0))="","",INDEX('DAILY TASK TRACKER'!$G$5:$G$1504,MATCH(SMALL('DAILY TASK TRACKER'!$BE$5:$BE$1504,5),'DAILY TASK TRACKER'!$BE$5:$BE$1504,0))),"") | P59: =IFERROR(IF(INDEX('DAILY TASK TRACKER'!$I$5:$I$1504,MATCH(SMALL('DAILY TASK TRACKER'!$BE$5:$BE$1504,5),'DAILY TASK TRACKER'!$BE$5:$BE$1504,0))="","",INDEX('DAILY TASK TRACKER'!$I$5:$I$1504,MATCH(SMALL('DAILY TASK TRACKER'!$BE$5:$BE$1504,5),'DAILY TASK TRACKER'!$BE$5:$BE$1504,0))),"") | Q59: =IFERROR(IF(INDEX('DAILY TASK TRACKER'!$M$5:$M$1504,MATCH(SMALL('DAILY TASK TRACKER'!$BE$5:$BE$1504,5),'DAILY TASK TRACKER'!$BE$5:$BE$1504,0))="","",INDEX('DAILY TASK TRACKER'!$M$5:$M$1504,MATCH(SMALL('DAILY TASK TRACKER'!$BE$5:$BE$1504,5),'DAILY TASK TRACKER'!$BE$5:$BE$1504,0))),"") | R59: =IFERROR(IF(INDEX('DAILY TASK TRACKER'!$L$5:$L$1504,MATCH(SMALL('DAILY TASK TRACKER'!$BE$5:$BE$1504,5),'DAILY TASK TRACKER'!$BE$5:$BE$1504,0))="","",INDEX('DAILY TASK TRACKER'!$L$5:$L$1504,MATCH(SMALL('DAILY TASK TRACKER'!$BE$5:$BE$1504,5),'DAILY TASK TRACKER'!$BE$5:$BE$1504,0))),"")
B60: =IFERROR(IF(INDEX('DAILY TASK TRACKER'!$B$5:$B$1504,MATCH(SMALL('DAILY TASK TRACKER'!$BG$5:$BG$1504,6),'DAILY TASK TRACKER'!$BG$5:$BG$1504,0))="","",INDEX('DAILY TASK TRACKER'!$B$5:$B$1504,MATCH(SMALL('DAILY TASK TRACKER'!$BG$5:$BG$1504,6),'DAILY TASK TRACKER'!$BG$5:$BG$1504,0))),"") | C60: =IFERROR(IF(INDEX('DAILY TASK TRACKER'!$C$5:$C$1504,MATCH(SMALL('DAILY TASK TRACKER'!$BG$5:$BG$1504,6),'DAILY TASK TRACKER'!$BG$5:$BG$1504,0))="","",INDEX('DAILY TASK TRACKER'!$C$5:$C$1504,MATCH(SMALL('DAILY TASK TRACKER'!$BG$5:$BG$1504,6),'DAILY TASK TRACKER'!$BG$5:$BG$1504,0))),"") | D60: =IFERROR(IF(INDEX('DAILY TASK TRACKER'!$G$5:$G$1504,MATCH(SMALL('DAILY TASK TRACKER'!$BG$5:$BG$1504,6),'DAILY TASK TRACKER'!$BG$5:$BG$1504,0))="","",INDEX('DAILY TASK TRACKER'!$G$5:$G$1504,MATCH(SMALL('DAILY TASK TRACKER'!$BG$5:$BG$1504,6),'DAILY TASK TRACKER'!$BG$5:$BG$1504,0))),"") | H60: =IFERROR(IF(INDEX('DAILY TASK TRACKER'!$O$5:$O$1504,MATCH(SMALL('DAILY TASK TRACKER'!$BG$5:$BG$1504,6),'DAILY TASK TRACKER'!$BG$5:$BG$1504,0))="","",INDEX('DAILY TASK TRACKER'!$O$5:$O$1504,MATCH(SMALL('DAILY TASK TRACKER'!$BG$5:$BG$1504,6),'DAILY TASK TRACKER'!$BG$5:$BG$1504,0))),"") | K60: =IFERROR(IF(INDEX('DAILY TASK TRACKER'!$B$5:$B$1504,MATCH(SMALL('DAILY TASK TRACKER'!$BE$5:$BE$1504,6),'DAILY TASK TRACKER'!$BE$5:$BE$1504,0))="","",INDEX('DAILY TASK TRACKER'!$B$5:$B$1504,MATCH(SMALL('DAILY TASK TRACKER'!$BE$5:$BE$1504,6),'DAILY TASK TRACKER'!$BE$5:$BE$1504,0))),"") | L60: =IFERROR(IF(INDEX('DAILY TASK TRACKER'!$C$5:$C$1504,MATCH(SMALL('DAILY TASK TRACKER'!$BE$5:$BE$1504,6),'DAILY TASK TRACKER'!$BE$5:$BE$1504,0))="","",INDEX('DAILY TASK TRACKER'!$C$5:$C$1504,MATCH(SMALL('DAILY TASK TRACKER'!$BE$5:$BE$1504,6),'DAILY TASK TRACKER'!$BE$5:$BE$1504,0))),"") | M60: =IFERROR(IF(INDEX('DAILY TASK TRACKER'!$G$5:$G$1504,MATCH(SMALL('DAILY TASK TRACKER'!$BE$5:$BE$1504,6),'DAILY TASK TRACKER'!$BE$5:$BE$1504,0))="","",INDEX('DAILY TASK TRACKER'!$G$5:$G$1504,MATCH(SMALL('DAILY TASK TRACKER'!$BE$5:$BE$1504,6),'DAILY TASK TRACKER'!$BE$5:$BE$1504,0))),"") | P60: =IFERROR(IF(INDEX('DAILY TASK TRACKER'!$I$5:$I$1504,MATCH(SMALL('DAILY TASK TRACKER'!$BE$5:$BE$1504,6),'DAILY TASK TRACKER'!$BE$5:$BE$1504,0))="","",INDEX('DAILY TASK TRACKER'!$I$5:$I$1504,MATCH(SMALL('DAILY TASK TRACKER'!$BE$5:$BE$1504,6),'DAILY TASK TRACKER'!$BE$5:$BE$1504,0))),"") | Q60: =IFERROR(IF(INDEX('DAILY TASK TRACKER'!$M$5:$M$1504,MATCH(SMALL('DAILY TASK TRACKER'!$BE$5:$BE$1504,6),'DAILY TASK TRACKER'!$BE$5:$BE$1504,0))="","",INDEX('DAILY TASK TRACKER'!$M$5:$M$1504,MATCH(SMALL('DAILY TASK TRACKER'!$BE$5:$BE$1504,6),'DAILY TASK TRACKER'!$BE$5:$BE$1504,0))),"") | R60: =IFERROR(IF(INDEX('DAILY TASK TRACKER'!$L$5:$L$1504,MATCH(SMALL('DAILY TASK TRACKER'!$BE$5:$BE$1504,6),'DAILY TASK TRACKER'!$BE$5:$BE$1504,0))="","",INDEX('DAILY TASK TRACKER'!$L$5:$L$1504,MATCH(SMALL('DAILY TASK TRACKER'!$BE$5:$BE$1504,6),'DAILY TASK TRACKER'!$BE$5:$BE$1504,0))),"")
B61: =IFERROR(IF(INDEX('DAILY TASK TRACKER'!$B$5:$B$1504,MATCH(SMALL('DAILY TASK TRACKER'!$BG$5:$BG$1504,7),'DAILY TASK TRACKER'!$BG$5:$BG$1504,0))="","",INDEX('DAILY TASK TRACKER'!$B$5:$B$1504,MATCH(SMALL('DAILY TASK TRACKER'!$BG$5:$BG$1504,7),'DAILY TASK TRACKER'!$BG$5:$BG$1504,0))),"") | C61: =IFERROR(IF(INDEX('DAILY TASK TRACKER'!$C$5:$C$1504,MATCH(SMALL('DAILY TASK TRACKER'!$BG$5:$BG$1504,7),'DAILY TASK TRACKER'!$BG$5:$BG$1504,0))="","",INDEX('DAILY TASK TRACKER'!$C$5:$C$1504,MATCH(SMALL('DAILY TASK TRACKER'!$BG$5:$BG$1504,7),'DAILY TASK TRACKER'!$BG$5:$BG$1504,0))),"") | D61: =IFERROR(IF(INDEX('DAILY TASK TRACKER'!$G$5:$G$1504,MATCH(SMALL('DAILY TASK TRACKER'!$BG$5:$BG$1504,7),'DAILY TASK TRACKER'!$BG$5:$BG$1504,0))="","",INDEX('DAILY TASK TRACKER'!$G$5:$G$1504,MATCH(SMALL('DAILY TASK TRACKER'!$BG$5:$BG$1504,7),'DAILY TASK TRACKER'!$BG$5:$BG$1504,0))),"") | H61: =IFERROR(IF(INDEX('DAILY TASK TRACKER'!$O$5:$O$1504,MATCH(SMALL('DAILY TASK TRACKER'!$BG$5:$BG$1504,7),'DAILY TASK TRACKER'!$BG$5:$BG$1504,0))="","",INDEX('DAILY TASK TRACKER'!$O$5:$O$1504,MATCH(SMALL('DAILY TASK TRACKER'!$BG$5:$BG$1504,7),'DAILY TASK TRACKER'!$BG$5:$BG$1504,0))),"") | K61: =IFERROR(IF(INDEX('DAILY TASK TRACKER'!$B$5:$B$1504,MATCH(SMALL('DAILY TASK TRACKER'!$BE$5:$BE$1504,7),'DAILY TASK TRACKER'!$BE$5:$BE$1504,0))="","",INDEX('DAILY TASK TRACKER'!$B$5:$B$1504,MATCH(SMALL('DAILY TASK TRACKER'!$BE$5:$BE$1504,7),'DAILY TASK TRACKER'!$BE$5:$BE$1504,0))),"") | L61: =IFERROR(IF(INDEX('DAILY TASK TRACKER'!$C$5:$C$1504,MATCH(SMALL('DAILY TASK TRACKER'!$BE$5:$BE$1504,7),'DAILY TASK TRACKER'!$BE$5:$BE$1504,0))="","",INDEX('DAILY TASK TRACKER'!$C$5:$C$1504,MATCH(SMALL('DAILY TASK TRACKER'!$BE$5:$BE$1504,7),'DAILY TASK TRACKER'!$BE$5:$BE$1504,0))),"") | M61: =IFERROR(IF(INDEX('DAILY TASK TRACKER'!$G$5:$G$1504,MATCH(SMALL('DAILY TASK TRACKER'!$BE$5:$BE$1504,7),'DAILY TASK TRACKER'!$BE$5:$BE$1504,0))="","",INDEX('DAILY TASK TRACKER'!$G$5:$G$1504,MATCH(SMALL('DAILY TASK TRACKER'!$BE$5:$BE$1504,7),'DAILY TASK TRACKER'!$BE$5:$BE$1504,0))),"") | P61: =IFERROR(IF(INDEX('DAILY TASK TRACKER'!$I$5:$I$1504,MATCH(SMALL('DAILY TASK TRACKER'!$BE$5:$BE$1504,7),'DAILY TASK TRACKER'!$BE$5:$BE$1504,0))="","",INDEX('DAILY TASK TRACKER'!$I$5:$I$1504,MATCH(SMALL('DAILY TASK TRACKER'!$BE$5:$BE$1504,7),'DAILY TASK TRACKER'!$BE$5:$BE$1504,0))),"") | Q61: =IFERROR(IF(INDEX('DAILY TASK TRACKER'!$M$5:$M$1504,MATCH(SMALL('DAILY TASK TRACKER'!$BE$5:$BE$1504,7),'DAILY TASK TRACKER'!$BE$5:$BE$1504,0))="","",INDEX('DAILY TASK TRACKER'!$M$5:$M$1504,MATCH(SMALL('DAILY TASK TRACKER'!$BE$5:$BE$1504,7),'DAILY TASK TRACKER'!$BE$5:$BE$1504,0))),"") | R61: =IFERROR(IF(INDEX('DAILY TASK TRACKER'!$L$5:$L$1504,MATCH(SMALL('DAILY TASK TRACKER'!$BE$5:$BE$1504,7),'DAILY TASK TRACKER'!$BE$5:$BE$1504,0))="","",INDEX('DAILY TASK TRACKER'!$L$5:$L$1504,MATCH(SMALL('DAILY TASK TRACKER'!$BE$5:$BE$1504,7),'DAILY TASK TRACKER'!$BE$5:$BE$1504,0))),"")
B62: =IFERROR(IF(INDEX('DAILY TASK TRACKER'!$B$5:$B$1504,MATCH(SMALL('DAILY TASK TRACKER'!$BG$5:$BG$1504,8),'DAILY TASK TRACKER'!$BG$5:$BG$1504,0))="","",INDEX('DAILY TASK TRACKER'!$B$5:$B$1504,MATCH(SMALL('DAILY TASK TRACKER'!$BG$5:$BG$1504,8),'DAILY TASK TRACKER'!$BG$5:$BG$1504,0))),"") | C62: =IFERROR(IF(INDEX('DAILY TASK TRACKER'!$C$5:$C$1504,MATCH(SMALL('DAILY TASK TRACKER'!$BG$5:$BG$1504,8),'DAILY TASK TRACKER'!$BG$5:$BG$1504,0))="","",INDEX('DAILY TASK TRACKER'!$C$5:$C$1504,MATCH(SMALL('DAILY TASK TRACKER'!$BG$5:$BG$1504,8),'DAILY TASK TRACKER'!$BG$5:$BG$1504,0))),"") | D62: =IFERROR(IF(INDEX('DAILY TASK TRACKER'!$G$5:$G$1504,MATCH(SMALL('DAILY TASK TRACKER'!$BG$5:$BG$1504,8),'DAILY TASK TRACKER'!$BG$5:$BG$1504,0))="","",INDEX('DAILY TASK TRACKER'!$G$5:$G$1504,MATCH(SMALL('DAILY TASK TRACKER'!$BG$5:$BG$1504,8),'DAILY TASK TRACKER'!$BG$5:$BG$1504,0))),"") | H62: =IFERROR(IF(INDEX('DAILY TASK TRACKER'!$O$5:$O$1504,MATCH(SMALL('DAILY TASK TRACKER'!$BG$5:$BG$1504,8),'DAILY TASK TRACKER'!$BG$5:$BG$1504,0))="","",INDEX('DAILY TASK TRACKER'!$O$5:$O$1504,MATCH(SMALL('DAILY TASK TRACKER'!$BG$5:$BG$1504,8),'DAILY TASK TRACKER'!$BG$5:$BG$1504,0))),"") | K62: =IFERROR(IF(INDEX('DAILY TASK TRACKER'!$B$5:$B$1504,MATCH(SMALL('DAILY TASK TRACKER'!$BE$5:$BE$1504,8),'DAILY TASK TRACKER'!$BE$5:$BE$1504,0))="","",INDEX('DAILY TASK TRACKER'!$B$5:$B$1504,MATCH(SMALL('DAILY TASK TRACKER'!$BE$5:$BE$1504,8),'DAILY TASK TRACKER'!$BE$5:$BE$1504,0))),"") | L62: =IFERROR(IF(INDEX('DAILY TASK TRACKER'!$C$5:$C$1504,MATCH(SMALL('DAILY TASK TRACKER'!$BE$5:$BE$1504,8),'DAILY TASK TRACKER'!$BE$5:$BE$1504,0))="","",INDEX('DAILY TASK TRACKER'!$C$5:$C$1504,MATCH(SMALL('DAILY TASK TRACKER'!$BE$5:$BE$1504,8),'DAILY TASK TRACKER'!$BE$5:$BE$1504,0))),"") | M62: =IFERROR(IF(INDEX('DAILY TASK TRACKER'!$G$5:$G$1504,MATCH(SMALL('DAILY TASK TRACKER'!$BE$5:$BE$1504,8),'DAILY TASK TRACKER'!$BE$5:$BE$1504,0))="","",INDEX('DAILY TASK TRACKER'!$G$5:$G$1504,MATCH(SMALL('DAILY TASK TRACKER'!$BE$5:$BE$1504,8),'DAILY TASK TRACKER'!$BE$5:$BE$1504,0))),"") | P62: =IFERROR(IF(INDEX('DAILY TASK TRACKER'!$I$5:$I$1504,MATCH(SMALL('DAILY TASK TRACKER'!$BE$5:$BE$1504,8),'DAILY TASK TRACKER'!$BE$5:$BE$1504,0))="","",INDEX('DAILY TASK TRACKER'!$I$5:$I$1504,MATCH(SMALL('DAILY TASK TRACKER'!$BE$5:$BE$1504,8),'DAILY TASK TRACKER'!$BE$5:$BE$1504,0))),"") | Q62: =IFERROR(IF(INDEX('DAILY TASK TRACKER'!$M$5:$M$1504,MATCH(SMALL('DAILY TASK TRACKER'!$BE$5:$BE$1504,8),'DAILY TASK TRACKER'!$BE$5:$BE$1504,0))="","",INDEX('DAILY TASK TRACKER'!$M$5:$M$1504,MATCH(SMALL('DAILY TASK TRACKER'!$BE$5:$BE$1504,8),'DAILY TASK TRACKER'!$BE$5:$BE$1504,0))),"") | R62: =IFERROR(IF(INDEX('DAILY TASK TRACKER'!$L$5:$L$1504,MATCH(SMALL('DAILY TASK TRACKER'!$BE$5:$BE$1504,8),'DAILY TASK TRACKER'!$BE$5:$BE$1504,0))="","",INDEX('DAILY TASK TRACKER'!$L$5:$L$1504,MATCH(SMALL('DAILY TASK TRACKER'!$BE$5:$BE$1504,8),'DAILY TASK TRACKER'!$BE$5:$BE$1504,0))),"")
B64: Q3. What is overdue? | K64: Q4. What is blocked?
B65: Team Member | C65: Client | D65: Task | G65: Priority | H65: Due | I65: Days Over | K65: Team Member | L65: Client | M65: Task | O65: Blocker | R65: Priority
B66: =IFERROR(IF(INDEX('DAILY TASK TRACKER'!$B$5:$B$1504,MATCH(SMALL('DAILY TASK TRACKER'!$BB$5:$BB$1504,1),'DAILY TASK TRACKER'!$BB$5:$BB$1504,0))="","",INDEX('DAILY TASK TRACKER'!$B$5:$B$1504,MATCH(SMALL('DAILY TASK TRACKER'!$BB$5:$BB$1504,1),'DAILY TASK TRACKER'!$BB$5:$BB$1504,0))),"- none -") -> Surbhi Pandey | C66: =IFERROR(IF(INDEX('DAILY TASK TRACKER'!$C$5:$C$1504,MATCH(SMALL('DAILY TASK TRACKER'!$BB$5:$BB$1504,1),'DAILY TASK TRACKER'!$BB$5:$BB$1504,0))="","",INDEX('DAILY TASK TRACKER'!$C$5:$C$1504,MATCH(SMALL('DAILY TASK TRACKER'!$BB$5:$BB$1504,1),'DAILY TASK TRACKER'!$BB$5:$BB$1504,0))),"") -> SAP | D66: =IFERROR(IF(INDEX('DAILY TASK TRACKER'!$G$5:$G$1504,MATCH(SMALL('DAILY TASK TRACKER'!$BB$5:$BB$1504,1),'DAILY TASK TRACKER'!$BB$5:$BB$1504,0))="","",INDEX('DAILY TASK TRACKER'!$G$5:$G$1504,MATCH(SMALL('DAILY TASK TRACKER'!$BB$5:$BB$1504,1),'DAILY TASK TRACKER'!$BB$5:$BB$1504,0))),"") -> Content Syndication - Email + WhatsApp deployment | G66: =IFERROR(IF(INDEX('DAILY TASK TRACKER'!$I$5:$I$1504,MATCH(SMALL('DAILY TASK TRACKER'!$BB$5:$BB$1504,1),'DAILY TASK TRACKER'!$BB$5:$BB$1504,0))="","",INDEX('DAILY TASK TRACKER'!$I$5:$I$1504,MATCH(SMALL('DAILY TASK TRACKER'!$BB$5:$BB$1504,1),'DAILY TASK TRACKER'!$BB$5:$BB$1504,0))),"") | H66: =IFERROR(IF(INDEX('DAILY TASK TRACKER'!$L$5:$L$1504,MATCH(SMALL('DAILY TASK TRACKER'!$BB$5:$BB$1504,1),'DAILY TASK TRACKER'!$BB$5:$BB$1504,0))="","",INDEX('DAILY TASK TRACKER'!$L$5:$L$1504,MATCH(SMALL('DAILY TASK TRACKER'!$BB$5:$BB$1504,1),'DAILY TASK TRACKER'!$BB$5:$BB$1504,0))),"") -> 46290 | I66: =IFERROR(IF(INDEX('DAILY TASK TRACKER'!$AD$5:$AD$1504,MATCH(SMALL('DAILY TASK TRACKER'!$BB$5:$BB$1504,1),'DAILY TASK TRACKER'!$BB$5:$BB$1504,0))="","",INDEX('DAILY TASK TRACKER'!$AD$5:$AD$1504,MATCH(SMALL('DAILY TASK TRACKER'!$BB$5:$BB$1504,1),'DAILY TASK TRACKER'!$BB$5:$BB$1504,0))),"") -> 10 | K66: =IFERROR(IF(INDEX('DAILY TASK TRACKER'!$B$5:$B$1504,MATCH(SMALL('DAILY TASK TRACKER'!$BC$5:$BC$1504,1),'DAILY TASK TRACKER'!$BC$5:$BC$1504,0))="","",INDEX('DAILY TASK TRACKER'!$B$5:$B$1504,MATCH(SMALL('DAILY TASK TRACKER'!$BC$5:$BC$1504,1),'DAILY TASK TRACKER'!$BC$5:$BC$1504,0))),"- none -") -> - none - | L66: =IFERROR(IF(INDEX('DAILY TASK TRACKER'!$C$5:$C$1504,MATCH(SMALL('DAILY TASK TRACKER'!$BC$5:$BC$1504,1),'DAILY TASK TRACKER'!$BC$5:$BC$1504,0))="","",INDEX('DAILY TASK TRACKER'!$C$5:$C$1504,MATCH(SMALL('DAILY TASK TRACKER'!$BC$5:$BC$1504,1),'DAILY TASK TRACKER'!$BC$5:$BC$1504,0))),"") | M66: =IFERROR(IF(INDEX('DAILY TASK TRACKER'!$G$5:$G$1504,MATCH(SMALL('DAILY TASK TRACKER'!$BC$5:$BC$1504,1),'DAILY TASK TRACKER'!$BC$5:$BC$1504,0))="","",INDEX('DAILY TASK TRACKER'!$G$5:$G$1504,MATCH(SMALL('DAILY TASK TRACKER'!$BC$5:$BC$1504,1),'DAILY TASK TRACKER'!$BC$5:$BC$1504,0))),"") | O66: =IFERROR(IF(INDEX('DAILY TASK TRACKER'!$T$5:$T$1504,MATCH(SMALL('DAILY TASK TRACKER'!$BC$5:$BC$1504,1),'DAILY TASK TRACKER'!$BC$5:$BC$1504,0))="","",INDEX('DAILY TASK TRACKER'!$T$5:$T$1504,MATCH(SMALL('DAILY TASK TRACKER'!$BC$5:$BC$1504,1),'DAILY TASK TRACKER'!$BC$5:$BC$1504,0))),"") | R66: =IFERROR(IF(INDEX('DAILY TASK TRACKER'!$I$5:$I$1504,MATCH(SMALL('DAILY TASK TRACKER'!$BC$5:$BC$1504,1),'DAILY TASK TRACKER'!$BC$5:$BC$1504,0))="","",INDEX('DAILY TASK TRACKER'!$I$5:$I$1504,MATCH(SMALL('DAILY TASK TRACKER'!$BC$5:$BC$1504,1),'DAILY TASK TRACKER'!$BC$5:$BC$1504,0))),"")
B67: =IFERROR(IF(INDEX('DAILY TASK TRACKER'!$B$5:$B$1504,MATCH(SMALL('DAILY TASK TRACKER'!$BB$5:$BB$1504,2),'DAILY TASK TRACKER'!$BB$5:$BB$1504,0))="","",INDEX('DAILY TASK TRACKER'!$B$5:$B$1504,MATCH(SMALL('DAILY TASK TRACKER'!$BB$5:$BB$1504,2),'DAILY TASK TRACKER'!$BB$5:$BB$1504,0))),"") -> Surbhi Pandey | C67: =IFERROR(IF(INDEX('DAILY TASK TRACKER'!$C$5:$C$1504,MATCH(SMALL('DAILY TASK TRACKER'!$BB$5:$BB$1504,2),'DAILY TASK TRACKER'!$BB$5:$BB$1504,0))="","",INDEX('DAILY TASK TRACKER'!$C$5:$C$1504,MATCH(SMALL('DAILY TASK TRACKER'!$BB$5:$BB$1504,2),'DAILY TASK TRACKER'!$BB$5:$BB$1504,0))),"") -> SAP | D67: =IFERROR(IF(INDEX('DAILY TASK TRACKER'!$G$5:$G$1504,MATCH(SMALL('DAILY TASK TRACKER'!$BB$5:$BB$1504,2),'DAILY TASK TRACKER'!$BB$5:$BB$1504,0))="","",INDEX('DAILY TASK TRACKER'!$G$5:$G$1504,MATCH(SMALL('DAILY TASK TRACKER'!$BB$5:$BB$1504,2),'DAILY TASK TRACKER'!$BB$5:$BB$1504,0))),"") -> Content Syndication - Email + WhatsApp deployment | G67: =IFERROR(IF(INDEX('DAILY TASK TRACKER'!$I$5:$I$1504,MATCH(SMALL('DAILY TASK TRACKER'!$BB$5:$BB$1504,2),'DAILY TASK TRACKER'!$BB$5:$BB$1504,0))="","",INDEX('DAILY TASK TRACKER'!$I$5:$I$1504,MATCH(SMALL('DAILY TASK TRACKER'!$BB$5:$BB$1504,2),'DAILY TASK TRACKER'!$BB$5:$BB$1504,0))),"") | H67: =IFERROR(IF(INDEX('DAILY TASK TRACKER'!$L$5:$L$1504,MATCH(SMALL('DAILY TASK TRACKER'!$BB$5:$BB$1504,2),'DAILY TASK TRACKER'!$BB$5:$BB$1504,0))="","",INDEX('DAILY TASK TRACKER'!$L$5:$L$1504,MATCH(SMALL('DAILY TASK TRACKER'!$BB$5:$BB$1504,2),'DAILY TASK TRACKER'!$BB$5:$BB$1504,0))),"") -> 46290 | I67: =IFERROR(IF(INDEX('DAILY TASK TRACKER'!$AD$5:$AD$1504,MATCH(SMALL('DAILY TASK TRACKER'!$BB$5:$BB$1504,2),'DAILY TASK TRACKER'!$BB$5:$BB$1504,0))="","",INDEX('DAILY TASK TRACKER'!$AD$5:$AD$1504,MATCH(SMALL('DAILY TASK TRACKER'!$BB$5:$BB$1504,2),'DAILY TASK TRACKER'!$BB$5:$BB$1504,0))),"") -> 10 | K67: =IFERROR(IF(INDEX('DAILY TASK TRACKER'!$B$5:$B$1504,MATCH(SMALL('DAILY TASK TRACKER'!$BC$5:$BC$1504,2),'DAILY TASK TRACKER'!$BC$5:$BC$1504,0))="","",INDEX('DAILY TASK TRACKER'!$B$5:$B$1504,MATCH(SMALL('DAILY TASK TRACKER'!$BC$5:$BC$1504,2),'DAILY TASK TRACKER'!$BC$5:$BC$1504,0))),"") | L67: =IFERROR(IF(INDEX('DAILY TASK TRACKER'!$C$5:$C$1504,MATCH(SMALL('DAILY TASK TRACKER'!$BC$5:$BC$1504,2),'DAILY TASK TRACKER'!$BC$5:$BC$1504,0))="","",INDEX('DAILY TASK TRACKER'!$C$5:$C$1504,MATCH(SMALL('DAILY TASK TRACKER'!$BC$5:$BC$1504,2),'DAILY TASK TRACKER'!$BC$5:$BC$1504,0))),"") | M67: =IFERROR(IF(INDEX('DAILY TASK TRACKER'!$G$5:$G$1504,MATCH(SMALL('DAILY TASK TRACKER'!$BC$5:$BC$1504,2),'DAILY TASK TRACKER'!$BC$5:$BC$1504,0))="","",INDEX('DAILY TASK TRACKER'!$G$5:$G$1504,MATCH(SMALL('DAILY TASK TRACKER'!$BC$5:$BC$1504,2),'DAILY TASK TRACKER'!$BC$5:$BC$1504,0))),"") | O67: =IFERROR(IF(INDEX('DAILY TASK TRACKER'!$T$5:$T$1504,MATCH(SMALL('DAILY TASK TRACKER'!$BC$5:$BC$1504,2),'DAILY TASK TRACKER'!$BC$5:$BC$1504,0))="","",INDEX('DAILY TASK TRACKER'!$T$5:$T$1504,MATCH(SMALL('DAILY TASK TRACKER'!$BC$5:$BC$1504,2),'DAILY TASK TRACKER'!$BC$5:$BC$1504,0))),"") | R67: =IFERROR(IF(INDEX('DAILY TASK TRACKER'!$I$5:$I$1504,MATCH(SMALL('DAILY TASK TRACKER'!$BC$5:$BC$1504,2),'DAILY TASK TRACKER'!$BC$5:$BC$1504,0))="","",INDEX('DAILY TASK TRACKER'!$I$5:$I$1504,MATCH(SMALL('DAILY TASK TRACKER'!$BC$5:$BC$1504,2),'DAILY TASK TRACKER'!$BC$5:$BC$1504,0))),"")
B68: =IFERROR(IF(INDEX('DAILY TASK TRACKER'!$B$5:$B$1504,MATCH(SMALL('DAILY TASK TRACKER'!$BB$5:$BB$1504,3),'DAILY TASK TRACKER'!$BB$5:$BB$1504,0))="","",INDEX('DAILY TASK TRACKER'!$B$5:$B$1504,MATCH(SMALL('DAILY TASK TRACKER'!$BB$5:$BB$1504,3),'DAILY TASK TRACKER'!$BB$5:$BB$1504,0))),"") -> Surbhi Pandey | C68: =IFERROR(IF(INDEX('DAILY TASK TRACKER'!$C$5:$C$1504,MATCH(SMALL('DAILY TASK TRACKER'!$BB$5:$BB$1504,3),'DAILY TASK TRACKER'!$BB$5:$BB$1504,0))="","",INDEX('DAILY TASK TRACKER'!$C$5:$C$1504,MATCH(SMALL('DAILY TASK TRACKER'!$BB$5:$BB$1504,3),'DAILY TASK TRACKER'!$BB$5:$BB$1504,0))),"") -> SAP | D68: =IFERROR(IF(INDEX('DAILY TASK TRACKER'!$G$5:$G$1504,MATCH(SMALL('DAILY TASK TRACKER'!$BB$5:$BB$1504,3),'DAILY TASK TRACKER'!$BB$5:$BB$1504,0))="","",INDEX('DAILY TASK TRACKER'!$G$5:$G$1504,MATCH(SMALL('DAILY TASK TRACKER'!$BB$5:$BB$1504,3),'DAILY TASK TRACKER'!$BB$5:$BB$1504,0))),"") -> Content Syndication - Email + WhatsApp deployment | G68: =IFERROR(IF(INDEX('DAILY TASK TRACKER'!$I$5:$I$1504,MATCH(SMALL('DAILY TASK TRACKER'!$BB$5:$BB$1504,3),'DAILY TASK TRACKER'!$BB$5:$BB$1504,0))="","",INDEX('DAILY TASK TRACKER'!$I$5:$I$1504,MATCH(SMALL('DAILY TASK TRACKER'!$BB$5:$BB$1504,3),'DAILY TASK TRACKER'!$BB$5:$BB$1504,0))),"") | H68: =IFERROR(IF(INDEX('DAILY TASK TRACKER'!$L$5:$L$1504,MATCH(SMALL('DAILY TASK TRACKER'!$BB$5:$BB$1504,3),'DAILY TASK TRACKER'!$BB$5:$BB$1504,0))="","",INDEX('DAILY TASK TRACKER'!$L$5:$L$1504,MATCH(SMALL('DAILY TASK TRACKER'!$BB$5:$BB$1504,3),'DAILY TASK TRACKER'!$BB$5:$BB$1504,0))),"") -> 46295 | I68: =IFERROR(IF(INDEX('DAILY TASK TRACKER'!$AD$5:$AD$1504,MATCH(SMALL('DAILY TASK TRACKER'!$BB$5:$BB$1504,3),'DAILY TASK TRACKER'!$BB$5:$BB$1504,0))="","",INDEX('DAILY TASK TRACKER'!$AD$5:$AD$1504,MATCH(SMALL('DAILY TASK TRACKER'!$BB$5:$BB$1504,3),'DAILY TASK TRACKER'!$BB$5:$BB$1504,0))),"") -> 5 | K68: =IFERROR(IF(INDEX('DAILY TASK TRACKER'!$B$5:$B$1504,MATCH(SMALL('DAILY TASK TRACKER'!$BC$5:$BC$1504,3),'DAILY TASK TRACKER'!$BC$5:$BC$1504,0))="","",INDEX('DAILY TASK TRACKER'!$B$5:$B$1504,MATCH(SMALL('DAILY TASK TRACKER'!$BC$5:$BC$1504,3),'DAILY TASK TRACKER'!$BC$5:$BC$1504,0))),"") | L68: =IFERROR(IF(INDEX('DAILY TASK TRACKER'!$C$5:$C$1504,MATCH(SMALL('DAILY TASK TRACKER'!$BC$5:$BC$1504,3),'DAILY TASK TRACKER'!$BC$5:$BC$1504,0))="","",INDEX('DAILY TASK TRACKER'!$C$5:$C$1504,MATCH(SMALL('DAILY TASK TRACKER'!$BC$5:$BC$1504,3),'DAILY TASK TRACKER'!$BC$5:$BC$1504,0))),"") | M68: =IFERROR(IF(INDEX('DAILY TASK TRACKER'!$G$5:$G$1504,MATCH(SMALL('DAILY TASK TRACKER'!$BC$5:$BC$1504,3),'DAILY TASK TRACKER'!$BC$5:$BC$1504,0))="","",INDEX('DAILY TASK TRACKER'!$G$5:$G$1504,MATCH(SMALL('DAILY TASK TRACKER'!$BC$5:$BC$1504,3),'DAILY TASK TRACKER'!$BC$5:$BC$1504,0))),"") | O68: =IFERROR(IF(INDEX('DAILY TASK TRACKER'!$T$5:$T$1504,MATCH(SMALL('DAILY TASK TRACKER'!$BC$5:$BC$1504,3),'DAILY TASK TRACKER'!$BC$5:$BC$1504,0))="","",INDEX('DAILY TASK TRACKER'!$T$5:$T$1504,MATCH(SMALL('DAILY TASK TRACKER'!$BC$5:$BC$1504,3),'DAILY TASK TRACKER'!$BC$5:$BC$1504,0))),"") | R68: =IFERROR(IF(INDEX('DAILY TASK TRACKER'!$I$5:$I$1504,MATCH(SMALL('DAILY TASK TRACKER'!$BC$5:$BC$1504,3),'DAILY TASK TRACKER'!$BC$5:$BC$1504,0))="","",INDEX('DAILY TASK TRACKER'!$I$5:$I$1504,MATCH(SMALL('DAILY TASK TRACKER'!$BC$5:$BC$1504,3),'DAILY TASK TRACKER'!$BC$5:$BC$1504,0))),"")
B69: =IFERROR(IF(INDEX('DAILY TASK TRACKER'!$B$5:$B$1504,MATCH(SMALL('DAILY TASK TRACKER'!$BB$5:$BB$1504,4),'DAILY TASK TRACKER'!$BB$5:$BB$1504,0))="","",INDEX('DAILY TASK TRACKER'!$B$5:$B$1504,MATCH(SMALL('DAILY TASK TRACKER'!$BB$5:$BB$1504,4),'DAILY TASK TRACKER'!$BB$5:$BB$1504,0))),"") | C69: =IFERROR(IF(INDEX('DAILY TASK TRACKER'!$C$5:$C$1504,MATCH(SMALL('DAILY TASK TRACKER'!$BB$5:$BB$1504,4),'DAILY TASK TRACKER'!$BB$5:$BB$1504,0))="","",INDEX('DAILY TASK TRACKER'!$C$5:$C$1504,MATCH(SMALL('DAILY TASK TRACKER'!$BB$5:$BB$1504,4),'DAILY TASK TRACKER'!$BB$5:$BB$1504,0))),"") | D69: =IFERROR(IF(INDEX('DAILY TASK TRACKER'!$G$5:$G$1504,MATCH(SMALL('DAILY TASK TRACKER'!$BB$5:$BB$1504,4),'DAILY TASK TRACKER'!$BB$5:$BB$1504,0))="","",INDEX('DAILY TASK TRACKER'!$G$5:$G$1504,MATCH(SMALL('DAILY TASK TRACKER'!$BB$5:$BB$1504,4),'DAILY TASK TRACKER'!$BB$5:$BB$1504,0))),"") | G69: =IFERROR(IF(INDEX('DAILY TASK TRACKER'!$I$5:$I$1504,MATCH(SMALL('DAILY TASK TRACKER'!$BB$5:$BB$1504,4),'DAILY TASK TRACKER'!$BB$5:$BB$1504,0))="","",INDEX('DAILY TASK TRACKER'!$I$5:$I$1504,MATCH(SMALL('DAILY TASK TRACKER'!$BB$5:$BB$1504,4),'DAILY TASK TRACKER'!$BB$5:$BB$1504,0))),"") | H69: =IFERROR(IF(INDEX('DAILY TASK TRACKER'!$L$5:$L$1504,MATCH(SMALL('DAILY TASK TRACKER'!$BB$5:$BB$1504,4),'DAILY TASK TRACKER'!$BB$5:$BB$1504,0))="","",INDEX('DAILY TASK TRACKER'!$L$5:$L$1504,MATCH(SMALL('DAILY TASK TRACKER'!$BB$5:$BB$1504,4),'DAILY TASK TRACKER'!$BB$5:$BB$1504,0))),"") | I69: =IFERROR(IF(INDEX('DAILY TASK TRACKER'!$AD$5:$AD$1504,MATCH(SMALL('DAILY TASK TRACKER'!$BB$5:$BB$1504,4),'DAILY TASK TRACKER'!$BB$5:$BB$1504,0))="","",INDEX('DAILY TASK TRACKER'!$AD$5:$AD$1504,MATCH(SMALL('DAILY TASK TRACKER'!$BB$5:$BB$1504,4),'DAILY TASK TRACKER'!$BB$5:$BB$1504,0))),"") | K69: =IFERROR(IF(INDEX('DAILY TASK TRACKER'!$B$5:$B$1504,MATCH(SMALL('DAILY TASK TRACKER'!$BC$5:$BC$1504,4),'DAILY TASK TRACKER'!$BC$5:$BC$1504,0))="","",INDEX('DAILY TASK TRACKER'!$B$5:$B$1504,MATCH(SMALL('DAILY TASK TRACKER'!$BC$5:$BC$1504,4),'DAILY TASK TRACKER'!$BC$5:$BC$1504,0))),"") | L69: =IFERROR(IF(INDEX('DAILY TASK TRACKER'!$C$5:$C$1504,MATCH(SMALL('DAILY TASK TRACKER'!$BC$5:$BC$1504,4),'DAILY TASK TRACKER'!$BC$5:$BC$1504,0))="","",INDEX('DAILY TASK TRACKER'!$C$5:$C$1504,MATCH(SMALL('DAILY TASK TRACKER'!$BC$5:$BC$1504,4),'DAILY TASK TRACKER'!$BC$5:$BC$1504,0))),"") | M69: =IFERROR(IF(INDEX('DAILY TASK TRACKER'!$G$5:$G$1504,MATCH(SMALL('DAILY TASK TRACKER'!$BC$5:$BC$1504,4),'DAILY TASK TRACKER'!$BC$5:$BC$1504,0))="","",INDEX('DAILY TASK TRACKER'!$G$5:$G$1504,MATCH(SMALL('DAILY TASK TRACKER'!$BC$5:$BC$1504,4),'DAILY TASK TRACKER'!$BC$5:$BC$1504,0))),"") | O69: =IFERROR(IF(INDEX('DAILY TASK TRACKER'!$T$5:$T$1504,MATCH(SMALL('DAILY TASK TRACKER'!$BC$5:$BC$1504,4),'DAILY TASK TRACKER'!$BC$5:$BC$1504,0))="","",INDEX('DAILY TASK TRACKER'!$T$5:$T$1504,MATCH(SMALL('DAILY TASK TRACKER'!$BC$5:$BC$1504,4),'DAILY TASK TRACKER'!$BC$5:$BC$1504,0))),"") | R69: =IFERROR(IF(INDEX('DAILY TASK TRACKER'!$I$5:$I$1504,MATCH(SMALL('DAILY TASK TRACKER'!$BC$5:$BC$1504,4),'DAILY TASK TRACKER'!$BC$5:$BC$1504,0))="","",INDEX('DAILY TASK TRACKER'!$I$5:$I$1504,MATCH(SMALL('DAILY TASK TRACKER'!$BC$5:$BC$1504,4),'DAILY TASK TRACKER'!$BC$5:$BC$1504,0))),"")
B70: =IFERROR(IF(INDEX('DAILY TASK TRACKER'!$B$5:$B$1504,MATCH(SMALL('DAILY TASK TRACKER'!$BB$5:$BB$1504,5),'DAILY TASK TRACKER'!$BB$5:$BB$1504,0))="","",INDEX('DAILY TASK TRACKER'!$B$5:$B$1504,MATCH(SMALL('DAILY TASK TRACKER'!$BB$5:$BB$1504,5),'DAILY TASK TRACKER'!$BB$5:$BB$1504,0))),"") | C70: =IFERROR(IF(INDEX('DAILY TASK TRACKER'!$C$5:$C$1504,MATCH(SMALL('DAILY TASK TRACKER'!$BB$5:$BB$1504,5),'DAILY TASK TRACKER'!$BB$5:$BB$1504,0))="","",INDEX('DAILY TASK TRACKER'!$C$5:$C$1504,MATCH(SMALL('DAILY TASK TRACKER'!$BB$5:$BB$1504,5),'DAILY TASK TRACKER'!$BB$5:$BB$1504,0))),"") | D70: =IFERROR(IF(INDEX('DAILY TASK TRACKER'!$G$5:$G$1504,MATCH(SMALL('DAILY TASK TRACKER'!$BB$5:$BB$1504,5),'DAILY TASK TRACKER'!$BB$5:$BB$1504,0))="","",INDEX('DAILY TASK TRACKER'!$G$5:$G$1504,MATCH(SMALL('DAILY TASK TRACKER'!$BB$5:$BB$1504,5),'DAILY TASK TRACKER'!$BB$5:$BB$1504,0))),"") | G70: =IFERROR(IF(INDEX('DAILY TASK TRACKER'!$I$5:$I$1504,MATCH(SMALL('DAILY TASK TRACKER'!$BB$5:$BB$1504,5),'DAILY TASK TRACKER'!$BB$5:$BB$1504,0))="","",INDEX('DAILY TASK TRACKER'!$I$5:$I$1504,MATCH(SMALL('DAILY TASK TRACKER'!$BB$5:$BB$1504,5),'DAILY TASK TRACKER'!$BB$5:$BB$1504,0))),"") | H70: =IFERROR(IF(INDEX('DAILY TASK TRACKER'!$L$5:$L$1504,MATCH(SMALL('DAILY TASK TRACKER'!$BB$5:$BB$1504,5),'DAILY TASK TRACKER'!$BB$5:$BB$1504,0))="","",INDEX('DAILY TASK TRACKER'!$L$5:$L$1504,MATCH(SMALL('DAILY TASK TRACKER'!$BB$5:$BB$1504,5),'DAILY TASK TRACKER'!$BB$5:$BB$1504,0))),"") | I70: =IFERROR(IF(INDEX('DAILY TASK TRACKER'!$AD$5:$AD$1504,MATCH(SMALL('DAILY TASK TRACKER'!$BB$5:$BB$1504,5),'DAILY TASK TRACKER'!$BB$5:$BB$1504,0))="","",INDEX('DAILY TASK TRACKER'!$AD$5:$AD$1504,MATCH(SMALL('DAILY TASK TRACKER'!$BB$5:$BB$1504,5),'DAILY TASK TRACKER'!$BB$5:$BB$1504,0))),"") | K70: =IFERROR(IF(INDEX('DAILY TASK TRACKER'!$B$5:$B$1504,MATCH(SMALL('DAILY TASK TRACKER'!$BC$5:$BC$1504,5),'DAILY TASK TRACKER'!$BC$5:$BC$1504,0))="","",INDEX('DAILY TASK TRACKER'!$B$5:$B$1504,MATCH(SMALL('DAILY TASK TRACKER'!$BC$5:$BC$1504,5),'DAILY TASK TRACKER'!$BC$5:$BC$1504,0))),"") | L70: =IFERROR(IF(INDEX('DAILY TASK TRACKER'!$C$5:$C$1504,MATCH(SMALL('DAILY TASK TRACKER'!$BC$5:$BC$1504,5),'DAILY TASK TRACKER'!$BC$5:$BC$1504,0))="","",INDEX('DAILY TASK TRACKER'!$C$5:$C$1504,MATCH(SMALL('DAILY TASK TRACKER'!$BC$5:$BC$1504,5),'DAILY TASK TRACKER'!$BC$5:$BC$1504,0))),"") | M70: =IFERROR(IF(INDEX('DAILY TASK TRACKER'!$G$5:$G$1504,MATCH(SMALL('DAILY TASK TRACKER'!$BC$5:$BC$1504,5),'DAILY TASK TRACKER'!$BC$5:$BC$1504,0))="","",INDEX('DAILY TASK TRACKER'!$G$5:$G$1504,MATCH(SMALL('DAILY TASK TRACKER'!$BC$5:$BC$1504,5),'DAILY TASK TRACKER'!$BC$5:$BC$1504,0))),"") | O70: =IFERROR(IF(INDEX('DAILY TASK TRACKER'!$T$5:$T$1504,MATCH(SMALL('DAILY TASK TRACKER'!$BC$5:$BC$1504,5),'DAILY TASK TRACKER'!$BC$5:$BC$1504,0))="","",INDEX('DAILY TASK TRACKER'!$T$5:$T$1504,MATCH(SMALL('DAILY TASK TRACKER'!$BC$5:$BC$1504,5),'DAILY TASK TRACKER'!$BC$5:$BC$1504,0))),"") | R70: =IFERROR(IF(INDEX('DAILY TASK TRACKER'!$I$5:$I$1504,MATCH(SMALL('DAILY TASK TRACKER'!$BC$5:$BC$1504,5),'DAILY TASK TRACKER'!$BC$5:$BC$1504,0))="","",INDEX('DAILY TASK TRACKER'!$I$5:$I$1504,MATCH(SMALL('DAILY TASK TRACKER'!$BC$5:$BC$1504,5),'DAILY TASK TRACKER'!$BC$5:$BC$1504,0))),"")
B71: =IFERROR(IF(INDEX('DAILY TASK TRACKER'!$B$5:$B$1504,MATCH(SMALL('DAILY TASK TRACKER'!$BB$5:$BB$1504,6),'DAILY TASK TRACKER'!$BB$5:$BB$1504,0))="","",INDEX('DAILY TASK TRACKER'!$B$5:$B$1504,MATCH(SMALL('DAILY TASK TRACKER'!$BB$5:$BB$1504,6),'DAILY TASK TRACKER'!$BB$5:$BB$1504,0))),"") | C71: =IFERROR(IF(INDEX('DAILY TASK TRACKER'!$C$5:$C$1504,MATCH(SMALL('DAILY TASK TRACKER'!$BB$5:$BB$1504,6),'DAILY TASK TRACKER'!$BB$5:$BB$1504,0))="","",INDEX('DAILY TASK TRACKER'!$C$5:$C$1504,MATCH(SMALL('DAILY TASK TRACKER'!$BB$5:$BB$1504,6),'DAILY TASK TRACKER'!$BB$5:$BB$1504,0))),"") | D71: =IFERROR(IF(INDEX('DAILY TASK TRACKER'!$G$5:$G$1504,MATCH(SMALL('DAILY TASK TRACKER'!$BB$5:$BB$1504,6),'DAILY TASK TRACKER'!$BB$5:$BB$1504,0))="","",INDEX('DAILY TASK TRACKER'!$G$5:$G$1504,MATCH(SMALL('DAILY TASK TRACKER'!$BB$5:$BB$1504,6),'DAILY TASK TRACKER'!$BB$5:$BB$1504,0))),"") | G71: =IFERROR(IF(INDEX('DAILY TASK TRACKER'!$I$5:$I$1504,MATCH(SMALL('DAILY TASK TRACKER'!$BB$5:$BB$1504,6),'DAILY TASK TRACKER'!$BB$5:$BB$1504,0))="","",INDEX('DAILY TASK TRACKER'!$I$5:$I$1504,MATCH(SMALL('DAILY TASK TRACKER'!$BB$5:$BB$1504,6),'DAILY TASK TRACKER'!$BB$5:$BB$1504,0))),"") | H71: =IFERROR(IF(INDEX('DAILY TASK TRACKER'!$L$5:$L$1504,MATCH(SMALL('DAILY TASK TRACKER'!$BB$5:$BB$1504,6),'DAILY TASK TRACKER'!$BB$5:$BB$1504,0))="","",INDEX('DAILY TASK TRACKER'!$L$5:$L$1504,MATCH(SMALL('DAILY TASK TRACKER'!$BB$5:$BB$1504,6),'DAILY TASK TRACKER'!$BB$5:$BB$1504,0))),"") | I71: =IFERROR(IF(INDEX('DAILY TASK TRACKER'!$AD$5:$AD$1504,MATCH(SMALL('DAILY TASK TRACKER'!$BB$5:$BB$1504,6),'DAILY TASK TRACKER'!$BB$5:$BB$1504,0))="","",INDEX('DAILY TASK TRACKER'!$AD$5:$AD$1504,MATCH(SMALL('DAILY TASK TRACKER'!$BB$5:$BB$1504,6),'DAILY TASK TRACKER'!$BB$5:$BB$1504,0))),"") | K71: =IFERROR(IF(INDEX('DAILY TASK TRACKER'!$B$5:$B$1504,MATCH(SMALL('DAILY TASK TRACKER'!$BC$5:$BC$1504,6),'DAILY TASK TRACKER'!$BC$5:$BC$1504,0))="","",INDEX('DAILY TASK TRACKER'!$B$5:$B$1504,MATCH(SMALL('DAILY TASK TRACKER'!$BC$5:$BC$1504,6),'DAILY TASK TRACKER'!$BC$5:$BC$1504,0))),"") | L71: =IFERROR(IF(INDEX('DAILY TASK TRACKER'!$C$5:$C$1504,MATCH(SMALL('DAILY TASK TRACKER'!$BC$5:$BC$1504,6),'DAILY TASK TRACKER'!$BC$5:$BC$1504,0))="","",INDEX('DAILY TASK TRACKER'!$C$5:$C$1504,MATCH(SMALL('DAILY TASK TRACKER'!$BC$5:$BC$1504,6),'DAILY TASK TRACKER'!$BC$5:$BC$1504,0))),"") | M71: =IFERROR(IF(INDEX('DAILY TASK TRACKER'!$G$5:$G$1504,MATCH(SMALL('DAILY TASK TRACKER'!$BC$5:$BC$1504,6),'DAILY TASK TRACKER'!$BC$5:$BC$1504,0))="","",INDEX('DAILY TASK TRACKER'!$G$5:$G$1504,MATCH(SMALL('DAILY TASK TRACKER'!$BC$5:$BC$1504,6),'DAILY TASK TRACKER'!$BC$5:$BC$1504,0))),"") | O71: =IFERROR(IF(INDEX('DAILY TASK TRACKER'!$T$5:$T$1504,MATCH(SMALL('DAILY TASK TRACKER'!$BC$5:$BC$1504,6),'DAILY TASK TRACKER'!$BC$5:$BC$1504,0))="","",INDEX('DAILY TASK TRACKER'!$T$5:$T$1504,MATCH(SMALL('DAILY TASK TRACKER'!$BC$5:$BC$1504,6),'DAILY TASK TRACKER'!$BC$5:$BC$1504,0))),"") | R71: =IFERROR(IF(INDEX('DAILY TASK TRACKER'!$I$5:$I$1504,MATCH(SMALL('DAILY TASK TRACKER'!$BC$5:$BC$1504,6),'DAILY TASK TRACKER'!$BC$5:$BC$1504,0))="","",INDEX('DAILY TASK TRACKER'!$I$5:$I$1504,MATCH(SMALL('DAILY TASK TRACKER'!$BC$5:$BC$1504,6),'DAILY TASK TRACKER'!$BC$5:$BC$1504,0))),"")
B72: =IFERROR(IF(INDEX('DAILY TASK TRACKER'!$B$5:$B$1504,MATCH(SMALL('DAILY TASK TRACKER'!$BB$5:$BB$1504,7),'DAILY TASK TRACKER'!$BB$5:$BB$1504,0))="","",INDEX('DAILY TASK TRACKER'!$B$5:$B$1504,MATCH(SMALL('DAILY TASK TRACKER'!$BB$5:$BB$1504,7),'DAILY TASK TRACKER'!$BB$5:$BB$1504,0))),"") | C72: =IFERROR(IF(INDEX('DAILY TASK TRACKER'!$C$5:$C$1504,MATCH(SMALL('DAILY TASK TRACKER'!$BB$5:$BB$1504,7),'DAILY TASK TRACKER'!$BB$5:$BB$1504,0))="","",INDEX('DAILY TASK TRACKER'!$C$5:$C$1504,MATCH(SMALL('DAILY TASK TRACKER'!$BB$5:$BB$1504,7),'DAILY TASK TRACKER'!$BB$5:$BB$1504,0))),"") | D72: =IFERROR(IF(INDEX('DAILY TASK TRACKER'!$G$5:$G$1504,MATCH(SMALL('DAILY TASK TRACKER'!$BB$5:$BB$1504,7),'DAILY TASK TRACKER'!$BB$5:$BB$1504,0))="","",INDEX('DAILY TASK TRACKER'!$G$5:$G$1504,MATCH(SMALL('DAILY TASK TRACKER'!$BB$5:$BB$1504,7),'DAILY TASK TRACKER'!$BB$5:$BB$1504,0))),"") | G72: =IFERROR(IF(INDEX('DAILY TASK TRACKER'!$I$5:$I$1504,MATCH(SMALL('DAILY TASK TRACKER'!$BB$5:$BB$1504,7),'DAILY TASK TRACKER'!$BB$5:$BB$1504,0))="","",INDEX('DAILY TASK TRACKER'!$I$5:$I$1504,MATCH(SMALL('DAILY TASK TRACKER'!$BB$5:$BB$1504,7),'DAILY TASK TRACKER'!$BB$5:$BB$1504,0))),"") | H72: =IFERROR(IF(INDEX('DAILY TASK TRACKER'!$L$5:$L$1504,MATCH(SMALL('DAILY TASK TRACKER'!$BB$5:$BB$1504,7),'DAILY TASK TRACKER'!$BB$5:$BB$1504,0))="","",INDEX('DAILY TASK TRACKER'!$L$5:$L$1504,MATCH(SMALL('DAILY TASK TRACKER'!$BB$5:$BB$1504,7),'DAILY TASK TRACKER'!$BB$5:$BB$1504,0))),"") | I72: =IFERROR(IF(INDEX('DAILY TASK TRACKER'!$AD$5:$AD$1504,MATCH(SMALL('DAILY TASK TRACKER'!$BB$5:$BB$1504,7),'DAILY TASK TRACKER'!$BB$5:$BB$1504,0))="","",INDEX('DAILY TASK TRACKER'!$AD$5:$AD$1504,MATCH(SMALL('DAILY TASK TRACKER'!$BB$5:$BB$1504,7),'DAILY TASK TRACKER'!$BB$5:$BB$1504,0))),"") | K72: =IFERROR(IF(INDEX('DAILY TASK TRACKER'!$B$5:$B$1504,MATCH(SMALL('DAILY TASK TRACKER'!$BC$5:$BC$1504,7),'DAILY TASK TRACKER'!$BC$5:$BC$1504,0))="","",INDEX('DAILY TASK TRACKER'!$B$5:$B$1504,MATCH(SMALL('DAILY TASK TRACKER'!$BC$5:$BC$1504,7),'DAILY TASK TRACKER'!$BC$5:$BC$1504,0))),"") | L72: =IFERROR(IF(INDEX('DAILY TASK TRACKER'!$C$5:$C$1504,MATCH(SMALL('DAILY TASK TRACKER'!$BC$5:$BC$1504,7),'DAILY TASK TRACKER'!$BC$5:$BC$1504,0))="","",INDEX('DAILY TASK TRACKER'!$C$5:$C$1504,MATCH(SMALL('DAILY TASK TRACKER'!$BC$5:$BC$1504,7),'DAILY TASK TRACKER'!$BC$5:$BC$1504,0))),"") | M72: =IFERROR(IF(INDEX('DAILY TASK TRACKER'!$G$5:$G$1504,MATCH(SMALL('DAILY TASK TRACKER'!$BC$5:$BC$1504,7),'DAILY TASK TRACKER'!$BC$5:$BC$1504,0))="","",INDEX('DAILY TASK TRACKER'!$G$5:$G$1504,MATCH(SMALL('DAILY TASK TRACKER'!$BC$5:$BC$1504,7),'DAILY TASK TRACKER'!$BC$5:$BC$1504,0))),"") | O72: =IFERROR(IF(INDEX('DAILY TASK TRACKER'!$T$5:$T$1504,MATCH(SMALL('DAILY TASK TRACKER'!$BC$5:$BC$1504,7),'DAILY TASK TRACKER'!$BC$5:$BC$1504,0))="","",INDEX('DAILY TASK TRACKER'!$T$5:$T$1504,MATCH(SMALL('DAILY TASK TRACKER'!$BC$5:$BC$1504,7),'DAILY TASK TRACKER'!$BC$5:$BC$1504,0))),"") | R72: =IFERROR(IF(INDEX('DAILY TASK TRACKER'!$I$5:$I$1504,MATCH(SMALL('DAILY TASK TRACKER'!$BC$5:$BC$1504,7),'DAILY TASK TRACKER'!$BC$5:$BC$1504,0))="","",INDEX('DAILY TASK TRACKER'!$I$5:$I$1504,MATCH(SMALL('DAILY TASK TRACKER'!$BC$5:$BC$1504,7),'DAILY TASK TRACKER'!$BC$5:$BC$1504,0))),"")
B73: =IFERROR(IF(INDEX('DAILY TASK TRACKER'!$B$5:$B$1504,MATCH(SMALL('DAILY TASK TRACKER'!$BB$5:$BB$1504,8),'DAILY TASK TRACKER'!$BB$5:$BB$1504,0))="","",INDEX('DAILY TASK TRACKER'!$B$5:$B$1504,MATCH(SMALL('DAILY TASK TRACKER'!$BB$5:$BB$1504,8),'DAILY TASK TRACKER'!$BB$5:$BB$1504,0))),"") | C73: =IFERROR(IF(INDEX('DAILY TASK TRACKER'!$C$5:$C$1504,MATCH(SMALL('DAILY TASK TRACKER'!$BB$5:$BB$1504,8),'DAILY TASK TRACKER'!$BB$5:$BB$1504,0))="","",INDEX('DAILY TASK TRACKER'!$C$5:$C$1504,MATCH(SMALL('DAILY TASK TRACKER'!$BB$5:$BB$1504,8),'DAILY TASK TRACKER'!$BB$5:$BB$1504,0))),"") | D73: =IFERROR(IF(INDEX('DAILY TASK TRACKER'!$G$5:$G$1504,MATCH(SMALL('DAILY TASK TRACKER'!$BB$5:$BB$1504,8),'DAILY TASK TRACKER'!$BB$5:$BB$1504,0))="","",INDEX('DAILY TASK TRACKER'!$G$5:$G$1504,MATCH(SMALL('DAILY TASK TRACKER'!$BB$5:$BB$1504,8),'DAILY TASK TRACKER'!$BB$5:$BB$1504,0))),"") | G73: =IFERROR(IF(INDEX('DAILY TASK TRACKER'!$I$5:$I$1504,MATCH(SMALL('DAILY TASK TRACKER'!$BB$5:$BB$1504,8),'DAILY TASK TRACKER'!$BB$5:$BB$1504,0))="","",INDEX('DAILY TASK TRACKER'!$I$5:$I$1504,MATCH(SMALL('DAILY TASK TRACKER'!$BB$5:$BB$1504,8),'DAILY TASK TRACKER'!$BB$5:$BB$1504,0))),"") | H73: =IFERROR(IF(INDEX('DAILY TASK TRACKER'!$L$5:$L$1504,MATCH(SMALL('DAILY TASK TRACKER'!$BB$5:$BB$1504,8),'DAILY TASK TRACKER'!$BB$5:$BB$1504,0))="","",INDEX('DAILY TASK TRACKER'!$L$5:$L$1504,MATCH(SMALL('DAILY TASK TRACKER'!$BB$5:$BB$1504,8),'DAILY TASK TRACKER'!$BB$5:$BB$1504,0))),"") | I73: =IFERROR(IF(INDEX('DAILY TASK TRACKER'!$AD$5:$AD$1504,MATCH(SMALL('DAILY TASK TRACKER'!$BB$5:$BB$1504,8),'DAILY TASK TRACKER'!$BB$5:$BB$1504,0))="","",INDEX('DAILY TASK TRACKER'!$AD$5:$AD$1504,MATCH(SMALL('DAILY TASK TRACKER'!$BB$5:$BB$1504,8),'DAILY TASK TRACKER'!$BB$5:$BB$1504,0))),"") | K73: =IFERROR(IF(INDEX('DAILY TASK TRACKER'!$B$5:$B$1504,MATCH(SMALL('DAILY TASK TRACKER'!$BC$5:$BC$1504,8),'DAILY TASK TRACKER'!$BC$5:$BC$1504,0))="","",INDEX('DAILY TASK TRACKER'!$B$5:$B$1504,MATCH(SMALL('DAILY TASK TRACKER'!$BC$5:$BC$1504,8),'DAILY TASK TRACKER'!$BC$5:$BC$1504,0))),"") | L73: =IFERROR(IF(INDEX('DAILY TASK TRACKER'!$C$5:$C$1504,MATCH(SMALL('DAILY TASK TRACKER'!$BC$5:$BC$1504,8),'DAILY TASK TRACKER'!$BC$5:$BC$1504,0))="","",INDEX('DAILY TASK TRACKER'!$C$5:$C$1504,MATCH(SMALL('DAILY TASK TRACKER'!$BC$5:$BC$1504,8),'DAILY TASK TRACKER'!$BC$5:$BC$1504,0))),"") | M73: =IFERROR(IF(INDEX('DAILY TASK TRACKER'!$G$5:$G$1504,MATCH(SMALL('DAILY TASK TRACKER'!$BC$5:$BC$1504,8),'DAILY TASK TRACKER'!$BC$5:$BC$1504,0))="","",INDEX('DAILY TASK TRACKER'!$G$5:$G$1504,MATCH(SMALL('DAILY TASK TRACKER'!$BC$5:$BC$1504,8),'DAILY TASK TRACKER'!$BC$5:$BC$1504,0))),"") | O73: =IFERROR(IF(INDEX('DAILY TASK TRACKER'!$T$5:$T$1504,MATCH(SMALL('DAILY TASK TRACKER'!$BC$5:$BC$1504,8),'DAILY TASK TRACKER'!$BC$5:$BC$1504,0))="","",INDEX('DAILY TASK TRACKER'!$T$5:$T$1504,MATCH(SMALL('DAILY TASK TRACKER'!$BC$5:$BC$1504,8),'DAILY TASK TRACKER'!$BC$5:$BC$1504,0))),"") | R73: =IFERROR(IF(INDEX('DAILY TASK TRACKER'!$I$5:$I$1504,MATCH(SMALL('DAILY TASK TRACKER'!$BC$5:$BC$1504,8),'DAILY TASK TRACKER'!$BC$5:$BC$1504,0))="","",INDEX('DAILY TASK TRACKER'!$I$5:$I$1504,MATCH(SMALL('DAILY TASK TRACKER'!$BC$5:$BC$1504,8),'DAILY TASK TRACKER'!$BC$5:$BC$1504,0))),"")
B75: Q12. Decisions / approvals required from me | K75: Q13. Escalate to Rajesh
B76: Team Member | C76: Client | D76: Task | G76: Next Action | I76: Due | K76: Team Member | L76: Client | M76: Task | P76: Blocker | R76: Due
B77: =IFERROR(IF(INDEX('DAILY TASK TRACKER'!$B$5:$B$1504,MATCH(SMALL('DAILY TASK TRACKER'!$BH$5:$BH$1504,1),'DAILY TASK TRACKER'!$BH$5:$BH$1504,0))="","",INDEX('DAILY TASK TRACKER'!$B$5:$B$1504,MATCH(SMALL('DAILY TASK TRACKER'!$BH$5:$BH$1504,1),'DAILY TASK TRACKER'!$BH$5:$BH$1504,0))),"- none -") -> - none - | C77: =IFERROR(IF(INDEX('DAILY TASK TRACKER'!$C$5:$C$1504,MATCH(SMALL('DAILY TASK TRACKER'!$BH$5:$BH$1504,1),'DAILY TASK TRACKER'!$BH$5:$BH$1504,0))="","",INDEX('DAILY TASK TRACKER'!$C$5:$C$1504,MATCH(SMALL('DAILY TASK TRACKER'!$BH$5:$BH$1504,1),'DAILY TASK TRACKER'!$BH$5:$BH$1504,0))),"") | D77: =IFERROR(IF(INDEX('DAILY TASK TRACKER'!$G$5:$G$1504,MATCH(SMALL('DAILY TASK TRACKER'!$BH$5:$BH$1504,1),'DAILY TASK TRACKER'!$BH$5:$BH$1504,0))="","",INDEX('DAILY TASK TRACKER'!$G$5:$G$1504,MATCH(SMALL('DAILY TASK TRACKER'!$BH$5:$BH$1504,1),'DAILY TASK TRACKER'!$BH$5:$BH$1504,0))),"") | G77: =IFERROR(IF(INDEX('DAILY TASK TRACKER'!$V$5:$V$1504,MATCH(SMALL('DAILY TASK TRACKER'!$BH$5:$BH$1504,1),'DAILY TASK TRACKER'!$BH$5:$BH$1504,0))="","",INDEX('DAILY TASK TRACKER'!$V$5:$V$1504,MATCH(SMALL('DAILY TASK TRACKER'!$BH$5:$BH$1504,1),'DAILY TASK TRACKER'!$BH$5:$BH$1504,0))),"") | I77: =IFERROR(IF(INDEX('DAILY TASK TRACKER'!$L$5:$L$1504,MATCH(SMALL('DAILY TASK TRACKER'!$BH$5:$BH$1504,1),'DAILY TASK TRACKER'!$BH$5:$BH$1504,0))="","",INDEX('DAILY TASK TRACKER'!$L$5:$L$1504,MATCH(SMALL('DAILY TASK TRACKER'!$BH$5:$BH$1504,1),'DAILY TASK TRACKER'!$BH$5:$BH$1504,0))),"") | K77: =IFERROR(IF(INDEX('DAILY TASK TRACKER'!$B$5:$B$1504,MATCH(SMALL('DAILY TASK TRACKER'!$BI$5:$BI$1504,1),'DAILY TASK TRACKER'!$BI$5:$BI$1504,0))="","",INDEX('DAILY TASK TRACKER'!$B$5:$B$1504,MATCH(SMALL('DAILY TASK TRACKER'!$BI$5:$BI$1504,1),'DAILY TASK TRACKER'!$BI$5:$BI$1504,0))),"- none -") -> - none - | L77: =IFERROR(IF(INDEX('DAILY TASK TRACKER'!$C$5:$C$1504,MATCH(SMALL('DAILY TASK TRACKER'!$BI$5:$BI$1504,1),'DAILY TASK TRACKER'!$BI$5:$BI$1504,0))="","",INDEX('DAILY TASK TRACKER'!$C$5:$C$1504,MATCH(SMALL('DAILY TASK TRACKER'!$BI$5:$BI$1504,1),'DAILY TASK TRACKER'!$BI$5:$BI$1504,0))),"") | M77: =IFERROR(IF(INDEX('DAILY TASK TRACKER'!$G$5:$G$1504,MATCH(SMALL('DAILY TASK TRACKER'!$BI$5:$BI$1504,1),'DAILY TASK TRACKER'!$BI$5:$BI$1504,0))="","",INDEX('DAILY TASK TRACKER'!$G$5:$G$1504,MATCH(SMALL('DAILY TASK TRACKER'!$BI$5:$BI$1504,1),'DAILY TASK TRACKER'!$BI$5:$BI$1504,0))),"") | P77: =IFERROR(IF(INDEX('DAILY TASK TRACKER'!$T$5:$T$1504,MATCH(SMALL('DAILY TASK TRACKER'!$BI$5:$BI$1504,1),'DAILY TASK TRACKER'!$BI$5:$BI$1504,0))="","",INDEX('DAILY TASK TRACKER'!$T$5:$T$1504,MATCH(SMALL('DAILY TASK TRACKER'!$BI$5:$BI$1504,1),'DAILY TASK TRACKER'!$BI$5:$BI$1504,0))),"") | R77: =IFERROR(IF(INDEX('DAILY TASK TRACKER'!$L$5:$L$1504,MATCH(SMALL('DAILY TASK TRACKER'!$BI$5:$BI$1504,1),'DAILY TASK TRACKER'!$BI$5:$BI$1504,0))="","",INDEX('DAILY TASK TRACKER'!$L$5:$L$1504,MATCH(SMALL('DAILY TASK TRACKER'!$BI$5:$BI$1504,1),'DAILY TASK TRACKER'!$BI$5:$BI$1504,0))),"")
B78: =IFERROR(IF(INDEX('DAILY TASK TRACKER'!$B$5:$B$1504,MATCH(SMALL('DAILY TASK TRACKER'!$BH$5:$BH$1504,2),'DAILY TASK TRACKER'!$BH$5:$BH$1504,0))="","",INDEX('DAILY TASK TRACKER'!$B$5:$B$1504,MATCH(SMALL('DAILY TASK TRACKER'!$BH$5:$BH$1504,2),'DAILY TASK TRACKER'!$BH$5:$BH$1504,0))),"") | C78: =IFERROR(IF(INDEX('DAILY TASK TRACKER'!$C$5:$C$1504,MATCH(SMALL('DAILY TASK TRACKER'!$BH$5:$BH$1504,2),'DAILY TASK TRACKER'!$BH$5:$BH$1504,0))="","",INDEX('DAILY TASK TRACKER'!$C$5:$C$1504,MATCH(SMALL('DAILY TASK TRACKER'!$BH$5:$BH$1504,2),'DAILY TASK TRACKER'!$BH$5:$BH$1504,0))),"") | D78: =IFERROR(IF(INDEX('DAILY TASK TRACKER'!$G$5:$G$1504,MATCH(SMALL('DAILY TASK TRACKER'!$BH$5:$BH$1504,2),'DAILY TASK TRACKER'!$BH$5:$BH$1504,0))="","",INDEX('DAILY TASK TRACKER'!$G$5:$G$1504,MATCH(SMALL('DAILY TASK TRACKER'!$BH$5:$BH$1504,2),'DAILY TASK TRACKER'!$BH$5:$BH$1504,0))),"") | G78: =IFERROR(IF(INDEX('DAILY TASK TRACKER'!$V$5:$V$1504,MATCH(SMALL('DAILY TASK TRACKER'!$BH$5:$BH$1504,2),'DAILY TASK TRACKER'!$BH$5:$BH$1504,0))="","",INDEX('DAILY TASK TRACKER'!$V$5:$V$1504,MATCH(SMALL('DAILY TASK TRACKER'!$BH$5:$BH$1504,2),'DAILY TASK TRACKER'!$BH$5:$BH$1504,0))),"") | I78: =IFERROR(IF(INDEX('DAILY TASK TRACKER'!$L$5:$L$1504,MATCH(SMALL('DAILY TASK TRACKER'!$BH$5:$BH$1504,2),'DAILY TASK TRACKER'!$BH$5:$BH$1504,0))="","",INDEX('DAILY TASK TRACKER'!$L$5:$L$1504,MATCH(SMALL('DAILY TASK TRACKER'!$BH$5:$BH$1504,2),'DAILY TASK TRACKER'!$BH$5:$BH$1504,0))),"") | K78: =IFERROR(IF(INDEX('DAILY TASK TRACKER'!$B$5:$B$1504,MATCH(SMALL('DAILY TASK TRACKER'!$BI$5:$BI$1504,2),'DAILY TASK TRACKER'!$BI$5:$BI$1504,0))="","",INDEX('DAILY TASK TRACKER'!$B$5:$B$1504,MATCH(SMALL('DAILY TASK TRACKER'!$BI$5:$BI$1504,2),'DAILY TASK TRACKER'!$BI$5:$BI$1504,0))),"") | L78: =IFERROR(IF(INDEX('DAILY TASK TRACKER'!$C$5:$C$1504,MATCH(SMALL('DAILY TASK TRACKER'!$BI$5:$BI$1504,2),'DAILY TASK TRACKER'!$BI$5:$BI$1504,0))="","",INDEX('DAILY TASK TRACKER'!$C$5:$C$1504,MATCH(SMALL('DAILY TASK TRACKER'!$BI$5:$BI$1504,2),'DAILY TASK TRACKER'!$BI$5:$BI$1504,0))),"") | M78: =IFERROR(IF(INDEX('DAILY TASK TRACKER'!$G$5:$G$1504,MATCH(SMALL('DAILY TASK TRACKER'!$BI$5:$BI$1504,2),'DAILY TASK TRACKER'!$BI$5:$BI$1504,0))="","",INDEX('DAILY TASK TRACKER'!$G$5:$G$1504,MATCH(SMALL('DAILY TASK TRACKER'!$BI$5:$BI$1504,2),'DAILY TASK TRACKER'!$BI$5:$BI$1504,0))),"") | P78: =IFERROR(IF(INDEX('DAILY TASK TRACKER'!$T$5:$T$1504,MATCH(SMALL('DAILY TASK TRACKER'!$BI$5:$BI$1504,2),'DAILY TASK TRACKER'!$BI$5:$BI$1504,0))="","",INDEX('DAILY TASK TRACKER'!$T$5:$T$1504,MATCH(SMALL('DAILY TASK TRACKER'!$BI$5:$BI$1504,2),'DAILY TASK TRACKER'!$BI$5:$BI$1504,0))),"") | R78: =IFERROR(IF(INDEX('DAILY TASK TRACKER'!$L$5:$L$1504,MATCH(SMALL('DAILY TASK TRACKER'!$BI$5:$BI$1504,2),'DAILY TASK TRACKER'!$BI$5:$BI$1504,0))="","",INDEX('DAILY TASK TRACKER'!$L$5:$L$1504,MATCH(SMALL('DAILY TASK TRACKER'!$BI$5:$BI$1504,2),'DAILY TASK TRACKER'!$BI$5:$BI$1504,0))),"")
B79: =IFERROR(IF(INDEX('DAILY TASK TRACKER'!$B$5:$B$1504,MATCH(SMALL('DAILY TASK TRACKER'!$BH$5:$BH$1504,3),'DAILY TASK TRACKER'!$BH$5:$BH$1504,0))="","",INDEX('DAILY TASK TRACKER'!$B$5:$B$1504,MATCH(SMALL('DAILY TASK TRACKER'!$BH$5:$BH$1504,3),'DAILY TASK TRACKER'!$BH$5:$BH$1504,0))),"") | C79: =IFERROR(IF(INDEX('DAILY TASK TRACKER'!$C$5:$C$1504,MATCH(SMALL('DAILY TASK TRACKER'!$BH$5:$BH$1504,3),'DAILY TASK TRACKER'!$BH$5:$BH$1504,0))="","",INDEX('DAILY TASK TRACKER'!$C$5:$C$1504,MATCH(SMALL('DAILY TASK TRACKER'!$BH$5:$BH$1504,3),'DAILY TASK TRACKER'!$BH$5:$BH$1504,0))),"") | D79: =IFERROR(IF(INDEX('DAILY TASK TRACKER'!$G$5:$G$1504,MATCH(SMALL('DAILY TASK TRACKER'!$BH$5:$BH$1504,3),'DAILY TASK TRACKER'!$BH$5:$BH$1504,0))="","",INDEX('DAILY TASK TRACKER'!$G$5:$G$1504,MATCH(SMALL('DAILY TASK TRACKER'!$BH$5:$BH$1504,3),'DAILY TASK TRACKER'!$BH$5:$BH$1504,0))),"") | G79: =IFERROR(IF(INDEX('DAILY TASK TRACKER'!$V$5:$V$1504,MATCH(SMALL('DAILY TASK TRACKER'!$BH$5:$BH$1504,3),'DAILY TASK TRACKER'!$BH$5:$BH$1504,0))="","",INDEX('DAILY TASK TRACKER'!$V$5:$V$1504,MATCH(SMALL('DAILY TASK TRACKER'!$BH$5:$BH$1504,3),'DAILY TASK TRACKER'!$BH$5:$BH$1504,0))),"") | I79: =IFERROR(IF(INDEX('DAILY TASK TRACKER'!$L$5:$L$1504,MATCH(SMALL('DAILY TASK TRACKER'!$BH$5:$BH$1504,3),'DAILY TASK TRACKER'!$BH$5:$BH$1504,0))="","",INDEX('DAILY TASK TRACKER'!$L$5:$L$1504,MATCH(SMALL('DAILY TASK TRACKER'!$BH$5:$BH$1504,3),'DAILY TASK TRACKER'!$BH$5:$BH$1504,0))),"") | K79: =IFERROR(IF(INDEX('DAILY TASK TRACKER'!$B$5:$B$1504,MATCH(SMALL('DAILY TASK TRACKER'!$BI$5:$BI$1504,3),'DAILY TASK TRACKER'!$BI$5:$BI$1504,0))="","",INDEX('DAILY TASK TRACKER'!$B$5:$B$1504,MATCH(SMALL('DAILY TASK TRACKER'!$BI$5:$BI$1504,3),'DAILY TASK TRACKER'!$BI$5:$BI$1504,0))),"") | L79: =IFERROR(IF(INDEX('DAILY TASK TRACKER'!$C$5:$C$1504,MATCH(SMALL('DAILY TASK TRACKER'!$BI$5:$BI$1504,3),'DAILY TASK TRACKER'!$BI$5:$BI$1504,0))="","",INDEX('DAILY TASK TRACKER'!$C$5:$C$1504,MATCH(SMALL('DAILY TASK TRACKER'!$BI$5:$BI$1504,3),'DAILY TASK TRACKER'!$BI$5:$BI$1504,0))),"") | M79: =IFERROR(IF(INDEX('DAILY TASK TRACKER'!$G$5:$G$1504,MATCH(SMALL('DAILY TASK TRACKER'!$BI$5:$BI$1504,3),'DAILY TASK TRACKER'!$BI$5:$BI$1504,0))="","",INDEX('DAILY TASK TRACKER'!$G$5:$G$1504,MATCH(SMALL('DAILY TASK TRACKER'!$BI$5:$BI$1504,3),'DAILY TASK TRACKER'!$BI$5:$BI$1504,0))),"") | P79: =IFERROR(IF(INDEX('DAILY TASK TRACKER'!$T$5:$T$1504,MATCH(SMALL('DAILY TASK TRACKER'!$BI$5:$BI$1504,3),'DAILY TASK TRACKER'!$BI$5:$BI$1504,0))="","",INDEX('DAILY TASK TRACKER'!$T$5:$T$1504,MATCH(SMALL('DAILY TASK TRACKER'!$BI$5:$BI$1504,3),'DAILY TASK TRACKER'!$BI$5:$BI$1504,0))),"") | R79: =IFERROR(IF(INDEX('DAILY TASK TRACKER'!$L$5:$L$1504,MATCH(SMALL('DAILY TASK TRACKER'!$BI$5:$BI$1504,3),'DAILY TASK TRACKER'!$BI$5:$BI$1504,0))="","",INDEX('DAILY TASK TRACKER'!$L$5:$L$1504,MATCH(SMALL('DAILY TASK TRACKER'!$BI$5:$BI$1504,3),'DAILY TASK TRACKER'!$BI$5:$BI$1504,0))),"")
B80: =IFERROR(IF(INDEX('DAILY TASK TRACKER'!$B$5:$B$1504,MATCH(SMALL('DAILY TASK TRACKER'!$BH$5:$BH$1504,4),'DAILY TASK TRACKER'!$BH$5:$BH$1504,0))="","",INDEX('DAILY TASK TRACKER'!$B$5:$B$1504,MATCH(SMALL('DAILY TASK TRACKER'!$BH$5:$BH$1504,4),'DAILY TASK TRACKER'!$BH$5:$BH$1504,0))),"") | C80: =IFERROR(IF(INDEX('DAILY TASK TRACKER'!$C$5:$C$1504,MATCH(SMALL('DAILY TASK TRACKER'!$BH$5:$BH$1504,4),'DAILY TASK TRACKER'!$BH$5:$BH$1504,0))="","",INDEX('DAILY TASK TRACKER'!$C$5:$C$1504,MATCH(SMALL('DAILY TASK TRACKER'!$BH$5:$BH$1504,4),'DAILY TASK TRACKER'!$BH$5:$BH$1504,0))),"") | D80: =IFERROR(IF(INDEX('DAILY TASK TRACKER'!$G$5:$G$1504,MATCH(SMALL('DAILY TASK TRACKER'!$BH$5:$BH$1504,4),'DAILY TASK TRACKER'!$BH$5:$BH$1504,0))="","",INDEX('DAILY TASK TRACKER'!$G$5:$G$1504,MATCH(SMALL('DAILY TASK TRACKER'!$BH$5:$BH$1504,4),'DAILY TASK TRACKER'!$BH$5:$BH$1504,0))),"") | G80: =IFERROR(IF(INDEX('DAILY TASK TRACKER'!$V$5:$V$1504,MATCH(SMALL('DAILY TASK TRACKER'!$BH$5:$BH$1504,4),'DAILY TASK TRACKER'!$BH$5:$BH$1504,0))="","",INDEX('DAILY TASK TRACKER'!$V$5:$V$1504,MATCH(SMALL('DAILY TASK TRACKER'!$BH$5:$BH$1504,4),'DAILY TASK TRACKER'!$BH$5:$BH$1504,0))),"") | I80: =IFERROR(IF(INDEX('DAILY TASK TRACKER'!$L$5:$L$1504,MATCH(SMALL('DAILY TASK TRACKER'!$BH$5:$BH$1504,4),'DAILY TASK TRACKER'!$BH$5:$BH$1504,0))="","",INDEX('DAILY TASK TRACKER'!$L$5:$L$1504,MATCH(SMALL('DAILY TASK TRACKER'!$BH$5:$BH$1504,4),'DAILY TASK TRACKER'!$BH$5:$BH$1504,0))),"") | K80: =IFERROR(IF(INDEX('DAILY TASK TRACKER'!$B$5:$B$1504,MATCH(SMALL('DAILY TASK TRACKER'!$BI$5:$BI$1504,4),'DAILY TASK TRACKER'!$BI$5:$BI$1504,0))="","",INDEX('DAILY TASK TRACKER'!$B$5:$B$1504,MATCH(SMALL('DAILY TASK TRACKER'!$BI$5:$BI$1504,4),'DAILY TASK TRACKER'!$BI$5:$BI$1504,0))),"") | L80: =IFERROR(IF(INDEX('DAILY TASK TRACKER'!$C$5:$C$1504,MATCH(SMALL('DAILY TASK TRACKER'!$BI$5:$BI$1504,4),'DAILY TASK TRACKER'!$BI$5:$BI$1504,0))="","",INDEX('DAILY TASK TRACKER'!$C$5:$C$1504,MATCH(SMALL('DAILY TASK TRACKER'!$BI$5:$BI$1504,4),'DAILY TASK TRACKER'!$BI$5:$BI$1504,0))),"") | M80: =IFERROR(IF(INDEX('DAILY TASK TRACKER'!$G$5:$G$1504,MATCH(SMALL('DAILY TASK TRACKER'!$BI$5:$BI$1504,4),'DAILY TASK TRACKER'!$BI$5:$BI$1504,0))="","",INDEX('DAILY TASK TRACKER'!$G$5:$G$1504,MATCH(SMALL('DAILY TASK TRACKER'!$BI$5:$BI$1504,4),'DAILY TASK TRACKER'!$BI$5:$BI$1504,0))),"") | P80: =IFERROR(IF(INDEX('DAILY TASK TRACKER'!$T$5:$T$1504,MATCH(SMALL('DAILY TASK TRACKER'!$BI$5:$BI$1504,4),'DAILY TASK TRACKER'!$BI$5:$BI$1504,0))="","",INDEX('DAILY TASK TRACKER'!$T$5:$T$1504,MATCH(SMALL('DAILY TASK TRACKER'!$BI$5:$BI$1504,4),'DAILY TASK TRACKER'!$BI$5:$BI$1504,0))),"") | R80: =IFERROR(IF(INDEX('DAILY TASK TRACKER'!$L$5:$L$1504,MATCH(SMALL('DAILY TASK TRACKER'!$BI$5:$BI$1504,4),'DAILY TASK TRACKER'!$BI$5:$BI$1504,0))="","",INDEX('DAILY TASK TRACKER'!$L$5:$L$1504,MATCH(SMALL('DAILY TASK TRACKER'!$BI$5:$BI$1504,4),'DAILY TASK TRACKER'!$BI$5:$BI$1504,0))),"")
B81: =IFERROR(IF(INDEX('DAILY TASK TRACKER'!$B$5:$B$1504,MATCH(SMALL('DAILY TASK TRACKER'!$BH$5:$BH$1504,5),'DAILY TASK TRACKER'!$BH$5:$BH$1504,0))="","",INDEX('DAILY TASK TRACKER'!$B$5:$B$1504,MATCH(SMALL('DAILY TASK TRACKER'!$BH$5:$BH$1504,5),'DAILY TASK TRACKER'!$BH$5:$BH$1504,0))),"") | C81: =IFERROR(IF(INDEX('DAILY TASK TRACKER'!$C$5:$C$1504,MATCH(SMALL('DAILY TASK TRACKER'!$BH$5:$BH$1504,5),'DAILY TASK TRACKER'!$BH$5:$BH$1504,0))="","",INDEX('DAILY TASK TRACKER'!$C$5:$C$1504,MATCH(SMALL('DAILY TASK TRACKER'!$BH$5:$BH$1504,5),'DAILY TASK TRACKER'!$BH$5:$BH$1504,0))),"") | D81: =IFERROR(IF(INDEX('DAILY TASK TRACKER'!$G$5:$G$1504,MATCH(SMALL('DAILY TASK TRACKER'!$BH$5:$BH$1504,5),'DAILY TASK TRACKER'!$BH$5:$BH$1504,0))="","",INDEX('DAILY TASK TRACKER'!$G$5:$G$1504,MATCH(SMALL('DAILY TASK TRACKER'!$BH$5:$BH$1504,5),'DAILY TASK TRACKER'!$BH$5:$BH$1504,0))),"") | G81: =IFERROR(IF(INDEX('DAILY TASK TRACKER'!$V$5:$V$1504,MATCH(SMALL('DAILY TASK TRACKER'!$BH$5:$BH$1504,5),'DAILY TASK TRACKER'!$BH$5:$BH$1504,0))="","",INDEX('DAILY TASK TRACKER'!$V$5:$V$1504,MATCH(SMALL('DAILY TASK TRACKER'!$BH$5:$BH$1504,5),'DAILY TASK TRACKER'!$BH$5:$BH$1504,0))),"") | I81: =IFERROR(IF(INDEX('DAILY TASK TRACKER'!$L$5:$L$1504,MATCH(SMALL('DAILY TASK TRACKER'!$BH$5:$BH$1504,5),'DAILY TASK TRACKER'!$BH$5:$BH$1504,0))="","",INDEX('DAILY TASK TRACKER'!$L$5:$L$1504,MATCH(SMALL('DAILY TASK TRACKER'!$BH$5:$BH$1504,5),'DAILY TASK TRACKER'!$BH$5:$BH$1504,0))),"") | K81: =IFERROR(IF(INDEX('DAILY TASK TRACKER'!$B$5:$B$1504,MATCH(SMALL('DAILY TASK TRACKER'!$BI$5:$BI$1504,5),'DAILY TASK TRACKER'!$BI$5:$BI$1504,0))="","",INDEX('DAILY TASK TRACKER'!$B$5:$B$1504,MATCH(SMALL('DAILY TASK TRACKER'!$BI$5:$BI$1504,5),'DAILY TASK TRACKER'!$BI$5:$BI$1504,0))),"") | L81: =IFERROR(IF(INDEX('DAILY TASK TRACKER'!$C$5:$C$1504,MATCH(SMALL('DAILY TASK TRACKER'!$BI$5:$BI$1504,5),'DAILY TASK TRACKER'!$BI$5:$BI$1504,0))="","",INDEX('DAILY TASK TRACKER'!$C$5:$C$1504,MATCH(SMALL('DAILY TASK TRACKER'!$BI$5:$BI$1504,5),'DAILY TASK TRACKER'!$BI$5:$BI$1504,0))),"") | M81: =IFERROR(IF(INDEX('DAILY TASK TRACKER'!$G$5:$G$1504,MATCH(SMALL('DAILY TASK TRACKER'!$BI$5:$BI$1504,5),'DAILY TASK TRACKER'!$BI$5:$BI$1504,0))="","",INDEX('DAILY TASK TRACKER'!$G$5:$G$1504,MATCH(SMALL('DAILY TASK TRACKER'!$BI$5:$BI$1504,5),'DAILY TASK TRACKER'!$BI$5:$BI$1504,0))),"") | P81: =IFERROR(IF(INDEX('DAILY TASK TRACKER'!$T$5:$T$1504,MATCH(SMALL('DAILY TASK TRACKER'!$BI$5:$BI$1504,5),'DAILY TASK TRACKER'!$BI$5:$BI$1504,0))="","",INDEX('DAILY TASK TRACKER'!$T$5:$T$1504,MATCH(SMALL('DAILY TASK TRACKER'!$BI$5:$BI$1504,5),'DAILY TASK TRACKER'!$BI$5:$BI$1504,0))),"") | R81: =IFERROR(IF(INDEX('DAILY TASK TRACKER'!$L$5:$L$1504,MATCH(SMALL('DAILY TASK TRACKER'!$BI$5:$BI$1504,5),'DAILY TASK TRACKER'!$BI$5:$BI$1504,0))="","",INDEX('DAILY TASK TRACKER'!$L$5:$L$1504,MATCH(SMALL('DAILY TASK TRACKER'!$BI$5:$BI$1504,5),'DAILY TASK TRACKER'!$BI$5:$BI$1504,0))),"")
B82: =IFERROR(IF(INDEX('DAILY TASK TRACKER'!$B$5:$B$1504,MATCH(SMALL('DAILY TASK TRACKER'!$BH$5:$BH$1504,6),'DAILY TASK TRACKER'!$BH$5:$BH$1504,0))="","",INDEX('DAILY TASK TRACKER'!$B$5:$B$1504,MATCH(SMALL('DAILY TASK TRACKER'!$BH$5:$BH$1504,6),'DAILY TASK TRACKER'!$BH$5:$BH$1504,0))),"") | C82: =IFERROR(IF(INDEX('DAILY TASK TRACKER'!$C$5:$C$1504,MATCH(SMALL('DAILY TASK TRACKER'!$BH$5:$BH$1504,6),'DAILY TASK TRACKER'!$BH$5:$BH$1504,0))="","",INDEX('DAILY TASK TRACKER'!$C$5:$C$1504,MATCH(SMALL('DAILY TASK TRACKER'!$BH$5:$BH$1504,6),'DAILY TASK TRACKER'!$BH$5:$BH$1504,0))),"") | D82: =IFERROR(IF(INDEX('DAILY TASK TRACKER'!$G$5:$G$1504,MATCH(SMALL('DAILY TASK TRACKER'!$BH$5:$BH$1504,6),'DAILY TASK TRACKER'!$BH$5:$BH$1504,0))="","",INDEX('DAILY TASK TRACKER'!$G$5:$G$1504,MATCH(SMALL('DAILY TASK TRACKER'!$BH$5:$BH$1504,6),'DAILY TASK TRACKER'!$BH$5:$BH$1504,0))),"") | G82: =IFERROR(IF(INDEX('DAILY TASK TRACKER'!$V$5:$V$1504,MATCH(SMALL('DAILY TASK TRACKER'!$BH$5:$BH$1504,6),'DAILY TASK TRACKER'!$BH$5:$BH$1504,0))="","",INDEX('DAILY TASK TRACKER'!$V$5:$V$1504,MATCH(SMALL('DAILY TASK TRACKER'!$BH$5:$BH$1504,6),'DAILY TASK TRACKER'!$BH$5:$BH$1504,0))),"") | I82: =IFERROR(IF(INDEX('DAILY TASK TRACKER'!$L$5:$L$1504,MATCH(SMALL('DAILY TASK TRACKER'!$BH$5:$BH$1504,6),'DAILY TASK TRACKER'!$BH$5:$BH$1504,0))="","",INDEX('DAILY TASK TRACKER'!$L$5:$L$1504,MATCH(SMALL('DAILY TASK TRACKER'!$BH$5:$BH$1504,6),'DAILY TASK TRACKER'!$BH$5:$BH$1504,0))),"") | K82: =IFERROR(IF(INDEX('DAILY TASK TRACKER'!$B$5:$B$1504,MATCH(SMALL('DAILY TASK TRACKER'!$BI$5:$BI$1504,6),'DAILY TASK TRACKER'!$BI$5:$BI$1504,0))="","",INDEX('DAILY TASK TRACKER'!$B$5:$B$1504,MATCH(SMALL('DAILY TASK TRACKER'!$BI$5:$BI$1504,6),'DAILY TASK TRACKER'!$BI$5:$BI$1504,0))),"") | L82: =IFERROR(IF(INDEX('DAILY TASK TRACKER'!$C$5:$C$1504,MATCH(SMALL('DAILY TASK TRACKER'!$BI$5:$BI$1504,6),'DAILY TASK TRACKER'!$BI$5:$BI$1504,0))="","",INDEX('DAILY TASK TRACKER'!$C$5:$C$1504,MATCH(SMALL('DAILY TASK TRACKER'!$BI$5:$BI$1504,6),'DAILY TASK TRACKER'!$BI$5:$BI$1504,0))),"") | M82: =IFERROR(IF(INDEX('DAILY TASK TRACKER'!$G$5:$G$1504,MATCH(SMALL('DAILY TASK TRACKER'!$BI$5:$BI$1504,6),'DAILY TASK TRACKER'!$BI$5:$BI$1504,0))="","",INDEX('DAILY TASK TRACKER'!$G$5:$G$1504,MATCH(SMALL('DAILY TASK TRACKER'!$BI$5:$BI$1504,6),'DAILY TASK TRACKER'!$BI$5:$BI$1504,0))),"") | P82: =IFERROR(IF(INDEX('DAILY TASK TRACKER'!$T$5:$T$1504,MATCH(SMALL('DAILY TASK TRACKER'!$BI$5:$BI$1504,6),'DAILY TASK TRACKER'!$BI$5:$BI$1504,0))="","",INDEX('DAILY TASK TRACKER'!$T$5:$T$1504,MATCH(SMALL('DAILY TASK TRACKER'!$BI$5:$BI$1504,6),'DAILY TASK TRACKER'!$BI$5:$BI$1504,0))),"") | R82: =IFERROR(IF(INDEX('DAILY TASK TRACKER'!$L$5:$L$1504,MATCH(SMALL('DAILY TASK TRACKER'!$BI$5:$BI$1504,6),'DAILY TASK TRACKER'!$BI$5:$BI$1504,0))="","",INDEX('DAILY TASK TRACKER'!$L$5:$L$1504,MATCH(SMALL('DAILY TASK TRACKER'!$BI$5:$BI$1504,6),'DAILY TASK TRACKER'!$BI$5:$BI$1504,0))),"")
B83: =IFERROR(IF(INDEX('DAILY TASK TRACKER'!$B$5:$B$1504,MATCH(SMALL('DAILY TASK TRACKER'!$BH$5:$BH$1504,7),'DAILY TASK TRACKER'!$BH$5:$BH$1504,0))="","",INDEX('DAILY TASK TRACKER'!$B$5:$B$1504,MATCH(SMALL('DAILY TASK TRACKER'!$BH$5:$BH$1504,7),'DAILY TASK TRACKER'!$BH$5:$BH$1504,0))),"") | C83: =IFERROR(IF(INDEX('DAILY TASK TRACKER'!$C$5:$C$1504,MATCH(SMALL('DAILY TASK TRACKER'!$BH$5:$BH$1504,7),'DAILY TASK TRACKER'!$BH$5:$BH$1504,0))="","",INDEX('DAILY TASK TRACKER'!$C$5:$C$1504,MATCH(SMALL('DAILY TASK TRACKER'!$BH$5:$BH$1504,7),'DAILY TASK TRACKER'!$BH$5:$BH$1504,0))),"") | D83: =IFERROR(IF(INDEX('DAILY TASK TRACKER'!$G$5:$G$1504,MATCH(SMALL('DAILY TASK TRACKER'!$BH$5:$BH$1504,7),'DAILY TASK TRACKER'!$BH$5:$BH$1504,0))="","",INDEX('DAILY TASK TRACKER'!$G$5:$G$1504,MATCH(SMALL('DAILY TASK TRACKER'!$BH$5:$BH$1504,7),'DAILY TASK TRACKER'!$BH$5:$BH$1504,0))),"") | G83: =IFERROR(IF(INDEX('DAILY TASK TRACKER'!$V$5:$V$1504,MATCH(SMALL('DAILY TASK TRACKER'!$BH$5:$BH$1504,7),'DAILY TASK TRACKER'!$BH$5:$BH$1504,0))="","",INDEX('DAILY TASK TRACKER'!$V$5:$V$1504,MATCH(SMALL('DAILY TASK TRACKER'!$BH$5:$BH$1504,7),'DAILY TASK TRACKER'!$BH$5:$BH$1504,0))),"") | I83: =IFERROR(IF(INDEX('DAILY TASK TRACKER'!$L$5:$L$1504,MATCH(SMALL('DAILY TASK TRACKER'!$BH$5:$BH$1504,7),'DAILY TASK TRACKER'!$BH$5:$BH$1504,0))="","",INDEX('DAILY TASK TRACKER'!$L$5:$L$1504,MATCH(SMALL('DAILY TASK TRACKER'!$BH$5:$BH$1504,7),'DAILY TASK TRACKER'!$BH$5:$BH$1504,0))),"") | K83: =IFERROR(IF(INDEX('DAILY TASK TRACKER'!$B$5:$B$1504,MATCH(SMALL('DAILY TASK TRACKER'!$BI$5:$BI$1504,7),'DAILY TASK TRACKER'!$BI$5:$BI$1504,0))="","",INDEX('DAILY TASK TRACKER'!$B$5:$B$1504,MATCH(SMALL('DAILY TASK TRACKER'!$BI$5:$BI$1504,7),'DAILY TASK TRACKER'!$BI$5:$BI$1504,0))),"") | L83: =IFERROR(IF(INDEX('DAILY TASK TRACKER'!$C$5:$C$1504,MATCH(SMALL('DAILY TASK TRACKER'!$BI$5:$BI$1504,7),'DAILY TASK TRACKER'!$BI$5:$BI$1504,0))="","",INDEX('DAILY TASK TRACKER'!$C$5:$C$1504,MATCH(SMALL('DAILY TASK TRACKER'!$BI$5:$BI$1504,7),'DAILY TASK TRACKER'!$BI$5:$BI$1504,0))),"") | M83: =IFERROR(IF(INDEX('DAILY TASK TRACKER'!$G$5:$G$1504,MATCH(SMALL('DAILY TASK TRACKER'!$BI$5:$BI$1504,7),'DAILY TASK TRACKER'!$BI$5:$BI$1504,0))="","",INDEX('DAILY TASK TRACKER'!$G$5:$G$1504,MATCH(SMALL('DAILY TASK TRACKER'!$BI$5:$BI$1504,7),'DAILY TASK TRACKER'!$BI$5:$BI$1504,0))),"") | P83: =IFERROR(IF(INDEX('DAILY TASK TRACKER'!$T$5:$T$1504,MATCH(SMALL('DAILY TASK TRACKER'!$BI$5:$BI$1504,7),'DAILY TASK TRACKER'!$BI$5:$BI$1504,0))="","",INDEX('DAILY TASK TRACKER'!$T$5:$T$1504,MATCH(SMALL('DAILY TASK TRACKER'!$BI$5:$BI$1504,7),'DAILY TASK TRACKER'!$BI$5:$BI$1504,0))),"") | R83: =IFERROR(IF(INDEX('DAILY TASK TRACKER'!$L$5:$L$1504,MATCH(SMALL('DAILY TASK TRACKER'!$BI$5:$BI$1504,7),'DAILY TASK TRACKER'!$BI$5:$BI$1504,0))="","",INDEX('DAILY TASK TRACKER'!$L$5:$L$1504,MATCH(SMALL('DAILY TASK TRACKER'!$BI$5:$BI$1504,7),'DAILY TASK TRACKER'!$BI$5:$BI$1504,0))),"")
B84: =IFERROR(IF(INDEX('DAILY TASK TRACKER'!$B$5:$B$1504,MATCH(SMALL('DAILY TASK TRACKER'!$BH$5:$BH$1504,8),'DAILY TASK TRACKER'!$BH$5:$BH$1504,0))="","",INDEX('DAILY TASK TRACKER'!$B$5:$B$1504,MATCH(SMALL('DAILY TASK TRACKER'!$BH$5:$BH$1504,8),'DAILY TASK TRACKER'!$BH$5:$BH$1504,0))),"") | C84: =IFERROR(IF(INDEX('DAILY TASK TRACKER'!$C$5:$C$1504,MATCH(SMALL('DAILY TASK TRACKER'!$BH$5:$BH$1504,8),'DAILY TASK TRACKER'!$BH$5:$BH$1504,0))="","",INDEX('DAILY TASK TRACKER'!$C$5:$C$1504,MATCH(SMALL('DAILY TASK TRACKER'!$BH$5:$BH$1504,8),'DAILY TASK TRACKER'!$BH$5:$BH$1504,0))),"") | D84: =IFERROR(IF(INDEX('DAILY TASK TRACKER'!$G$5:$G$1504,MATCH(SMALL('DAILY TASK TRACKER'!$BH$5:$BH$1504,8),'DAILY TASK TRACKER'!$BH$5:$BH$1504,0))="","",INDEX('DAILY TASK TRACKER'!$G$5:$G$1504,MATCH(SMALL('DAILY TASK TRACKER'!$BH$5:$BH$1504,8),'DAILY TASK TRACKER'!$BH$5:$BH$1504,0))),"") | G84: =IFERROR(IF(INDEX('DAILY TASK TRACKER'!$V$5:$V$1504,MATCH(SMALL('DAILY TASK TRACKER'!$BH$5:$BH$1504,8),'DAILY TASK TRACKER'!$BH$5:$BH$1504,0))="","",INDEX('DAILY TASK TRACKER'!$V$5:$V$1504,MATCH(SMALL('DAILY TASK TRACKER'!$BH$5:$BH$1504,8),'DAILY TASK TRACKER'!$BH$5:$BH$1504,0))),"") | I84: =IFERROR(IF(INDEX('DAILY TASK TRACKER'!$L$5:$L$1504,MATCH(SMALL('DAILY TASK TRACKER'!$BH$5:$BH$1504,8),'DAILY TASK TRACKER'!$BH$5:$BH$1504,0))="","",INDEX('DAILY TASK TRACKER'!$L$5:$L$1504,MATCH(SMALL('DAILY TASK TRACKER'!$BH$5:$BH$1504,8),'DAILY TASK TRACKER'!$BH$5:$BH$1504,0))),"") | K84: =IFERROR(IF(INDEX('DAILY TASK TRACKER'!$B$5:$B$1504,MATCH(SMALL('DAILY TASK TRACKER'!$BI$5:$BI$1504,8),'DAILY TASK TRACKER'!$BI$5:$BI$1504,0))="","",INDEX('DAILY TASK TRACKER'!$B$5:$B$1504,MATCH(SMALL('DAILY TASK TRACKER'!$BI$5:$BI$1504,8),'DAILY TASK TRACKER'!$BI$5:$BI$1504,0))),"") | L84: =IFERROR(IF(INDEX('DAILY TASK TRACKER'!$C$5:$C$1504,MATCH(SMALL('DAILY TASK TRACKER'!$BI$5:$BI$1504,8),'DAILY TASK TRACKER'!$BI$5:$BI$1504,0))="","",INDEX('DAILY TASK TRACKER'!$C$5:$C$1504,MATCH(SMALL('DAILY TASK TRACKER'!$BI$5:$BI$1504,8),'DAILY TASK TRACKER'!$BI$5:$BI$1504,0))),"") | M84: =IFERROR(IF(INDEX('DAILY TASK TRACKER'!$G$5:$G$1504,MATCH(SMALL('DAILY TASK TRACKER'!$BI$5:$BI$1504,8),'DAILY TASK TRACKER'!$BI$5:$BI$1504,0))="","",INDEX('DAILY TASK TRACKER'!$G$5:$G$1504,MATCH(SMALL('DAILY TASK TRACKER'!$BI$5:$BI$1504,8),'DAILY TASK TRACKER'!$BI$5:$BI$1504,0))),"") | P84: =IFERROR(IF(INDEX('DAILY TASK TRACKER'!$T$5:$T$1504,MATCH(SMALL('DAILY TASK TRACKER'!$BI$5:$BI$1504,8),'DAILY TASK TRACKER'!$BI$5:$BI$1504,0))="","",INDEX('DAILY TASK TRACKER'!$T$5:$T$1504,MATCH(SMALL('DAILY TASK TRACKER'!$BI$5:$BI$1504,8),'DAILY TASK TRACKER'!$BI$5:$BI$1504,0))),"") | R84: =IFERROR(IF(INDEX('DAILY TASK TRACKER'!$L$5:$L$1504,MATCH(SMALL('DAILY TASK TRACKER'!$BI$5:$BI$1504,8),'DAILY TASK TRACKER'!$BI$5:$BI$1504,0))="","",INDEX('DAILY TASK TRACKER'!$L$5:$L$1504,MATCH(SMALL('DAILY TASK TRACKER'!$BI$5:$BI$1504,8),'DAILY TASK TRACKER'!$BI$5:$BI$1504,0))),"")
B86: Q14. Top priorities for tomorrow | K86: Due within the next 2 days (incl. today)
B87: Team Member | C87: Client | D87: Task | G87: Priority | H87: Status | I87: Due | K87: Team Member | L87: Client | M87: Task | P87: Priority | Q87: Status | R87: Due
B88: =IFERROR(IF(INDEX('DAILY TASK TRACKER'!$B$5:$B$1504,MATCH(SMALL('DAILY TASK TRACKER'!$BF$5:$BF$1504,1),'DAILY TASK TRACKER'!$BF$5:$BF$1504,0))="","",INDEX('DAILY TASK TRACKER'!$B$5:$B$1504,MATCH(SMALL('DAILY TASK TRACKER'!$BF$5:$BF$1504,1),'DAILY TASK TRACKER'!$BF$5:$BF$1504,0))),"- none -") -> Surbhi Pandey | C88: =IFERROR(IF(INDEX('DAILY TASK TRACKER'!$C$5:$C$1504,MATCH(SMALL('DAILY TASK TRACKER'!$BF$5:$BF$1504,1),'DAILY TASK TRACKER'!$BF$5:$BF$1504,0))="","",INDEX('DAILY TASK TRACKER'!$C$5:$C$1504,MATCH(SMALL('DAILY TASK TRACKER'!$BF$5:$BF$1504,1),'DAILY TASK TRACKER'!$BF$5:$BF$1504,0))),"") -> SAP | D88: =IFERROR(IF(INDEX('DAILY TASK TRACKER'!$G$5:$G$1504,MATCH(SMALL('DAILY TASK TRACKER'!$BF$5:$BF$1504,1),'DAILY TASK TRACKER'!$BF$5:$BF$1504,0))="","",INDEX('DAILY TASK TRACKER'!$G$5:$G$1504,MATCH(SMALL('DAILY TASK TRACKER'!$BF$5:$BF$1504,1),'DAILY TASK TRACKER'!$BF$5:$BF$1504,0))),"") -> Content Syndication - Email + WhatsApp deployment | G88: =IFERROR(IF(INDEX('DAILY TASK TRACKER'!$I$5:$I$1504,MATCH(SMALL('DAILY TASK TRACKER'!$BF$5:$BF$1504,1),'DAILY TASK TRACKER'!$BF$5:$BF$1504,0))="","",INDEX('DAILY TASK TRACKER'!$I$5:$I$1504,MATCH(SMALL('DAILY TASK TRACKER'!$BF$5:$BF$1504,1),'DAILY TASK TRACKER'!$BF$5:$BF$1504,0))),"") | H88: =IFERROR(IF(INDEX('DAILY TASK TRACKER'!$M$5:$M$1504,MATCH(SMALL('DAILY TASK TRACKER'!$BF$5:$BF$1504,1),'DAILY TASK TRACKER'!$BF$5:$BF$1504,0))="","",INDEX('DAILY TASK TRACKER'!$M$5:$M$1504,MATCH(SMALL('DAILY TASK TRACKER'!$BF$5:$BF$1504,1),'DAILY TASK TRACKER'!$BF$5:$BF$1504,0))),"") | I88: =IFERROR(IF(INDEX('DAILY TASK TRACKER'!$L$5:$L$1504,MATCH(SMALL('DAILY TASK TRACKER'!$BF$5:$BF$1504,1),'DAILY TASK TRACKER'!$BF$5:$BF$1504,0))="","",INDEX('DAILY TASK TRACKER'!$L$5:$L$1504,MATCH(SMALL('DAILY TASK TRACKER'!$BF$5:$BF$1504,1),'DAILY TASK TRACKER'!$BF$5:$BF$1504,0))),"") -> 46301 | K88: =IFERROR(IF(INDEX('DAILY TASK TRACKER'!$B$5:$B$1504,MATCH(SMALL('DAILY TASK TRACKER'!$BD$5:$BD$1504,1),'DAILY TASK TRACKER'!$BD$5:$BD$1504,0))="","",INDEX('DAILY TASK TRACKER'!$B$5:$B$1504,MATCH(SMALL('DAILY TASK TRACKER'!$BD$5:$BD$1504,1),'DAILY TASK TRACKER'!$BD$5:$BD$1504,0))),"- none -") -> Surbhi Pandey | L88: =IFERROR(IF(INDEX('DAILY TASK TRACKER'!$C$5:$C$1504,MATCH(SMALL('DAILY TASK TRACKER'!$BD$5:$BD$1504,1),'DAILY TASK TRACKER'!$BD$5:$BD$1504,0))="","",INDEX('DAILY TASK TRACKER'!$C$5:$C$1504,MATCH(SMALL('DAILY TASK TRACKER'!$BD$5:$BD$1504,1),'DAILY TASK TRACKER'!$BD$5:$BD$1504,0))),"") -> SAP | M88: =IFERROR(IF(INDEX('DAILY TASK TRACKER'!$G$5:$G$1504,MATCH(SMALL('DAILY TASK TRACKER'!$BD$5:$BD$1504,1),'DAILY TASK TRACKER'!$BD$5:$BD$1504,0))="","",INDEX('DAILY TASK TRACKER'!$G$5:$G$1504,MATCH(SMALL('DAILY TASK TRACKER'!$BD$5:$BD$1504,1),'DAILY TASK TRACKER'!$BD$5:$BD$1504,0))),"") -> Content Syndication - Email + WhatsApp deployment | P88: =IFERROR(IF(INDEX('DAILY TASK TRACKER'!$I$5:$I$1504,MATCH(SMALL('DAILY TASK TRACKER'!$BD$5:$BD$1504,1),'DAILY TASK TRACKER'!$BD$5:$BD$1504,0))="","",INDEX('DAILY TASK TRACKER'!$I$5:$I$1504,MATCH(SMALL('DAILY TASK TRACKER'!$BD$5:$BD$1504,1),'DAILY TASK TRACKER'!$BD$5:$BD$1504,0))),"") | Q88: =IFERROR(IF(INDEX('DAILY TASK TRACKER'!$M$5:$M$1504,MATCH(SMALL('DAILY TASK TRACKER'!$BD$5:$BD$1504,1),'DAILY TASK TRACKER'!$BD$5:$BD$1504,0))="","",INDEX('DAILY TASK TRACKER'!$M$5:$M$1504,MATCH(SMALL('DAILY TASK TRACKER'!$BD$5:$BD$1504,1),'DAILY TASK TRACKER'!$BD$5:$BD$1504,0))),"") | R88: =IFERROR(IF(INDEX('DAILY TASK TRACKER'!$L$5:$L$1504,MATCH(SMALL('DAILY TASK TRACKER'!$BD$5:$BD$1504,1),'DAILY TASK TRACKER'!$BD$5:$BD$1504,0))="","",INDEX('DAILY TASK TRACKER'!$L$5:$L$1504,MATCH(SMALL('DAILY TASK TRACKER'!$BD$5:$BD$1504,1),'DAILY TASK TRACKER'!$BD$5:$BD$1504,0))),"") -> 46301
B89: =IFERROR(IF(INDEX('DAILY TASK TRACKER'!$B$5:$B$1504,MATCH(SMALL('DAILY TASK TRACKER'!$BF$5:$BF$1504,2),'DAILY TASK TRACKER'!$BF$5:$BF$1504,0))="","",INDEX('DAILY TASK TRACKER'!$B$5:$B$1504,MATCH(SMALL('DAILY TASK TRACKER'!$BF$5:$BF$1504,2),'DAILY TASK TRACKER'!$BF$5:$BF$1504,0))),"") | C89: =IFERROR(IF(INDEX('DAILY TASK TRACKER'!$C$5:$C$1504,MATCH(SMALL('DAILY TASK TRACKER'!$BF$5:$BF$1504,2),'DAILY TASK TRACKER'!$BF$5:$BF$1504,0))="","",INDEX('DAILY TASK TRACKER'!$C$5:$C$1504,MATCH(SMALL('DAILY TASK TRACKER'!$BF$5:$BF$1504,2),'DAILY TASK TRACKER'!$BF$5:$BF$1504,0))),"") | D89: =IFERROR(IF(INDEX('DAILY TASK TRACKER'!$G$5:$G$1504,MATCH(SMALL('DAILY TASK TRACKER'!$BF$5:$BF$1504,2),'DAILY TASK TRACKER'!$BF$5:$BF$1504,0))="","",INDEX('DAILY TASK TRACKER'!$G$5:$G$1504,MATCH(SMALL('DAILY TASK TRACKER'!$BF$5:$BF$1504,2),'DAILY TASK TRACKER'!$BF$5:$BF$1504,0))),"") | G89: =IFERROR(IF(INDEX('DAILY TASK TRACKER'!$I$5:$I$1504,MATCH(SMALL('DAILY TASK TRACKER'!$BF$5:$BF$1504,2),'DAILY TASK TRACKER'!$BF$5:$BF$1504,0))="","",INDEX('DAILY TASK TRACKER'!$I$5:$I$1504,MATCH(SMALL('DAILY TASK TRACKER'!$BF$5:$BF$1504,2),'DAILY TASK TRACKER'!$BF$5:$BF$1504,0))),"") | H89: =IFERROR(IF(INDEX('DAILY TASK TRACKER'!$M$5:$M$1504,MATCH(SMALL('DAILY TASK TRACKER'!$BF$5:$BF$1504,2),'DAILY TASK TRACKER'!$BF$5:$BF$1504,0))="","",INDEX('DAILY TASK TRACKER'!$M$5:$M$1504,MATCH(SMALL('DAILY TASK TRACKER'!$BF$5:$BF$1504,2),'DAILY TASK TRACKER'!$BF$5:$BF$1504,0))),"") | I89: =IFERROR(IF(INDEX('DAILY TASK TRACKER'!$L$5:$L$1504,MATCH(SMALL('DAILY TASK TRACKER'!$BF$5:$BF$1504,2),'DAILY TASK TRACKER'!$BF$5:$BF$1504,0))="","",INDEX('DAILY TASK TRACKER'!$L$5:$L$1504,MATCH(SMALL('DAILY TASK TRACKER'!$BF$5:$BF$1504,2),'DAILY TASK TRACKER'!$BF$5:$BF$1504,0))),"") | K89: =IFERROR(IF(INDEX('DAILY TASK TRACKER'!$B$5:$B$1504,MATCH(SMALL('DAILY TASK TRACKER'!$BD$5:$BD$1504,2),'DAILY TASK TRACKER'!$BD$5:$BD$1504,0))="","",INDEX('DAILY TASK TRACKER'!$B$5:$B$1504,MATCH(SMALL('DAILY TASK TRACKER'!$BD$5:$BD$1504,2),'DAILY TASK TRACKER'!$BD$5:$BD$1504,0))),"") | L89: =IFERROR(IF(INDEX('DAILY TASK TRACKER'!$C$5:$C$1504,MATCH(SMALL('DAILY TASK TRACKER'!$BD$5:$BD$1504,2),'DAILY TASK TRACKER'!$BD$5:$BD$1504,0))="","",INDEX('DAILY TASK TRACKER'!$C$5:$C$1504,MATCH(SMALL('DAILY TASK TRACKER'!$BD$5:$BD$1504,2),'DAILY TASK TRACKER'!$BD$5:$BD$1504,0))),"") | M89: =IFERROR(IF(INDEX('DAILY TASK TRACKER'!$G$5:$G$1504,MATCH(SMALL('DAILY TASK TRACKER'!$BD$5:$BD$1504,2),'DAILY TASK TRACKER'!$BD$5:$BD$1504,0))="","",INDEX('DAILY TASK TRACKER'!$G$5:$G$1504,MATCH(SMALL('DAILY TASK TRACKER'!$BD$5:$BD$1504,2),'DAILY TASK TRACKER'!$BD$5:$BD$1504,0))),"") | P89: =IFERROR(IF(INDEX('DAILY TASK TRACKER'!$I$5:$I$1504,MATCH(SMALL('DAILY TASK TRACKER'!$BD$5:$BD$1504,2),'DAILY TASK TRACKER'!$BD$5:$BD$1504,0))="","",INDEX('DAILY TASK TRACKER'!$I$5:$I$1504,MATCH(SMALL('DAILY TASK TRACKER'!$BD$5:$BD$1504,2),'DAILY TASK TRACKER'!$BD$5:$BD$1504,0))),"") | Q89: =IFERROR(IF(INDEX('DAILY TASK TRACKER'!$M$5:$M$1504,MATCH(SMALL('DAILY TASK TRACKER'!$BD$5:$BD$1504,2),'DAILY TASK TRACKER'!$BD$5:$BD$1504,0))="","",INDEX('DAILY TASK TRACKER'!$M$5:$M$1504,MATCH(SMALL('DAILY TASK TRACKER'!$BD$5:$BD$1504,2),'DAILY TASK TRACKER'!$BD$5:$BD$1504,0))),"") | R89: =IFERROR(IF(INDEX('DAILY TASK TRACKER'!$L$5:$L$1504,MATCH(SMALL('DAILY TASK TRACKER'!$BD$5:$BD$1504,2),'DAILY TASK TRACKER'!$BD$5:$BD$1504,0))="","",INDEX('DAILY TASK TRACKER'!$L$5:$L$1504,MATCH(SMALL('DAILY TASK TRACKER'!$BD$5:$BD$1504,2),'DAILY TASK TRACKER'!$BD$5:$BD$1504,0))),"")
B90: =IFERROR(IF(INDEX('DAILY TASK TRACKER'!$B$5:$B$1504,MATCH(SMALL('DAILY TASK TRACKER'!$BF$5:$BF$1504,3),'DAILY TASK TRACKER'!$BF$5:$BF$1504,0))="","",INDEX('DAILY TASK TRACKER'!$B$5:$B$1504,MATCH(SMALL('DAILY TASK TRACKER'!$BF$5:$BF$1504,3),'DAILY TASK TRACKER'!$BF$5:$BF$1504,0))),"") | C90: =IFERROR(IF(INDEX('DAILY TASK TRACKER'!$C$5:$C$1504,MATCH(SMALL('DAILY TASK TRACKER'!$BF$5:$BF$1504,3),'DAILY TASK TRACKER'!$BF$5:$BF$1504,0))="","",INDEX('DAILY TASK TRACKER'!$C$5:$C$1504,MATCH(SMALL('DAILY TASK TRACKER'!$BF$5:$BF$1504,3),'DAILY TASK TRACKER'!$BF$5:$BF$1504,0))),"") | D90: =IFERROR(IF(INDEX('DAILY TASK TRACKER'!$G$5:$G$1504,MATCH(SMALL('DAILY TASK TRACKER'!$BF$5:$BF$1504,3),'DAILY TASK TRACKER'!$BF$5:$BF$1504,0))="","",INDEX('DAILY TASK TRACKER'!$G$5:$G$1504,MATCH(SMALL('DAILY TASK TRACKER'!$BF$5:$BF$1504,3),'DAILY TASK TRACKER'!$BF$5:$BF$1504,0))),"") | G90: =IFERROR(IF(INDEX('DAILY TASK TRACKER'!$I$5:$I$1504,MATCH(SMALL('DAILY TASK TRACKER'!$BF$5:$BF$1504,3),'DAILY TASK TRACKER'!$BF$5:$BF$1504,0))="","",INDEX('DAILY TASK TRACKER'!$I$5:$I$1504,MATCH(SMALL('DAILY TASK TRACKER'!$BF$5:$BF$1504,3),'DAILY TASK TRACKER'!$BF$5:$BF$1504,0))),"") | H90: =IFERROR(IF(INDEX('DAILY TASK TRACKER'!$M$5:$M$1504,MATCH(SMALL('DAILY TASK TRACKER'!$BF$5:$BF$1504,3),'DAILY TASK TRACKER'!$BF$5:$BF$1504,0))="","",INDEX('DAILY TASK TRACKER'!$M$5:$M$1504,MATCH(SMALL('DAILY TASK TRACKER'!$BF$5:$BF$1504,3),'DAILY TASK TRACKER'!$BF$5:$BF$1504,0))),"") | I90: =IFERROR(IF(INDEX('DAILY TASK TRACKER'!$L$5:$L$1504,MATCH(SMALL('DAILY TASK TRACKER'!$BF$5:$BF$1504,3),'DAILY TASK TRACKER'!$BF$5:$BF$1504,0))="","",INDEX('DAILY TASK TRACKER'!$L$5:$L$1504,MATCH(SMALL('DAILY TASK TRACKER'!$BF$5:$BF$1504,3),'DAILY TASK TRACKER'!$BF$5:$BF$1504,0))),"") | K90: =IFERROR(IF(INDEX('DAILY TASK TRACKER'!$B$5:$B$1504,MATCH(SMALL('DAILY TASK TRACKER'!$BD$5:$BD$1504,3),'DAILY TASK TRACKER'!$BD$5:$BD$1504,0))="","",INDEX('DAILY TASK TRACKER'!$B$5:$B$1504,MATCH(SMALL('DAILY TASK TRACKER'!$BD$5:$BD$1504,3),'DAILY TASK TRACKER'!$BD$5:$BD$1504,0))),"") | L90: =IFERROR(IF(INDEX('DAILY TASK TRACKER'!$C$5:$C$1504,MATCH(SMALL('DAILY TASK TRACKER'!$BD$5:$BD$1504,3),'DAILY TASK TRACKER'!$BD$5:$BD$1504,0))="","",INDEX('DAILY TASK TRACKER'!$C$5:$C$1504,MATCH(SMALL('DAILY TASK TRACKER'!$BD$5:$BD$1504,3),'DAILY TASK TRACKER'!$BD$5:$BD$1504,0))),"") | M90: =IFERROR(IF(INDEX('DAILY TASK TRACKER'!$G$5:$G$1504,MATCH(SMALL('DAILY TASK TRACKER'!$BD$5:$BD$1504,3),'DAILY TASK TRACKER'!$BD$5:$BD$1504,0))="","",INDEX('DAILY TASK TRACKER'!$G$5:$G$1504,MATCH(SMALL('DAILY TASK TRACKER'!$BD$5:$BD$1504,3),'DAILY TASK TRACKER'!$BD$5:$BD$1504,0))),"") | P90: =IFERROR(IF(INDEX('DAILY TASK TRACKER'!$I$5:$I$1504,MATCH(SMALL('DAILY TASK TRACKER'!$BD$5:$BD$1504,3),'DAILY TASK TRACKER'!$BD$5:$BD$1504,0))="","",INDEX('DAILY TASK TRACKER'!$I$5:$I$1504,MATCH(SMALL('DAILY TASK TRACKER'!$BD$5:$BD$1504,3),'DAILY TASK TRACKER'!$BD$5:$BD$1504,0))),"") | Q90: =IFERROR(IF(INDEX('DAILY TASK TRACKER'!$M$5:$M$1504,MATCH(SMALL('DAILY TASK TRACKER'!$BD$5:$BD$1504,3),'DAILY TASK TRACKER'!$BD$5:$BD$1504,0))="","",INDEX('DAILY TASK TRACKER'!$M$5:$M$1504,MATCH(SMALL('DAILY TASK TRACKER'!$BD$5:$BD$1504,3),'DAILY TASK TRACKER'!$BD$5:$BD$1504,0))),"") | R90: =IFERROR(IF(INDEX('DAILY TASK TRACKER'!$L$5:$L$1504,MATCH(SMALL('DAILY TASK TRACKER'!$BD$5:$BD$1504,3),'DAILY TASK TRACKER'!$BD$5:$BD$1504,0))="","",INDEX('DAILY TASK TRACKER'!$L$5:$L$1504,MATCH(SMALL('DAILY TASK TRACKER'!$BD$5:$BD$1504,3),'DAILY TASK TRACKER'!$BD$5:$BD$1504,0))),"")
B91: =IFERROR(IF(INDEX('DAILY TASK TRACKER'!$B$5:$B$1504,MATCH(SMALL('DAILY TASK TRACKER'!$BF$5:$BF$1504,4),'DAILY TASK TRACKER'!$BF$5:$BF$1504,0))="","",INDEX('DAILY TASK TRACKER'!$B$5:$B$1504,MATCH(SMALL('DAILY TASK TRACKER'!$BF$5:$BF$1504,4),'DAILY TASK TRACKER'!$BF$5:$BF$1504,0))),"") | C91: =IFERROR(IF(INDEX('DAILY TASK TRACKER'!$C$5:$C$1504,MATCH(SMALL('DAILY TASK TRACKER'!$BF$5:$BF$1504,4),'DAILY TASK TRACKER'!$BF$5:$BF$1504,0))="","",INDEX('DAILY TASK TRACKER'!$C$5:$C$1504,MATCH(SMALL('DAILY TASK TRACKER'!$BF$5:$BF$1504,4),'DAILY TASK TRACKER'!$BF$5:$BF$1504,0))),"") | D91: =IFERROR(IF(INDEX('DAILY TASK TRACKER'!$G$5:$G$1504,MATCH(SMALL('DAILY TASK TRACKER'!$BF$5:$BF$1504,4),'DAILY TASK TRACKER'!$BF$5:$BF$1504,0))="","",INDEX('DAILY TASK TRACKER'!$G$5:$G$1504,MATCH(SMALL('DAILY TASK TRACKER'!$BF$5:$BF$1504,4),'DAILY TASK TRACKER'!$BF$5:$BF$1504,0))),"") | G91: =IFERROR(IF(INDEX('DAILY TASK TRACKER'!$I$5:$I$1504,MATCH(SMALL('DAILY TASK TRACKER'!$BF$5:$BF$1504,4),'DAILY TASK TRACKER'!$BF$5:$BF$1504,0))="","",INDEX('DAILY TASK TRACKER'!$I$5:$I$1504,MATCH(SMALL('DAILY TASK TRACKER'!$BF$5:$BF$1504,4),'DAILY TASK TRACKER'!$BF$5:$BF$1504,0))),"") | H91: =IFERROR(IF(INDEX('DAILY TASK TRACKER'!$M$5:$M$1504,MATCH(SMALL('DAILY TASK TRACKER'!$BF$5:$BF$1504,4),'DAILY TASK TRACKER'!$BF$5:$BF$1504,0))="","",INDEX('DAILY TASK TRACKER'!$M$5:$M$1504,MATCH(SMALL('DAILY TASK TRACKER'!$BF$5:$BF$1504,4),'DAILY TASK TRACKER'!$BF$5:$BF$1504,0))),"") | I91: =IFERROR(IF(INDEX('DAILY TASK TRACKER'!$L$5:$L$1504,MATCH(SMALL('DAILY TASK TRACKER'!$BF$5:$BF$1504,4),'DAILY TASK TRACKER'!$BF$5:$BF$1504,0))="","",INDEX('DAILY TASK TRACKER'!$L$5:$L$1504,MATCH(SMALL('DAILY TASK TRACKER'!$BF$5:$BF$1504,4),'DAILY TASK TRACKER'!$BF$5:$BF$1504,0))),"") | K91: =IFERROR(IF(INDEX('DAILY TASK TRACKER'!$B$5:$B$1504,MATCH(SMALL('DAILY TASK TRACKER'!$BD$5:$BD$1504,4),'DAILY TASK TRACKER'!$BD$5:$BD$1504,0))="","",INDEX('DAILY TASK TRACKER'!$B$5:$B$1504,MATCH(SMALL('DAILY TASK TRACKER'!$BD$5:$BD$1504,4),'DAILY TASK TRACKER'!$BD$5:$BD$1504,0))),"") | L91: =IFERROR(IF(INDEX('DAILY TASK TRACKER'!$C$5:$C$1504,MATCH(SMALL('DAILY TASK TRACKER'!$BD$5:$BD$1504,4),'DAILY TASK TRACKER'!$BD$5:$BD$1504,0))="","",INDEX('DAILY TASK TRACKER'!$C$5:$C$1504,MATCH(SMALL('DAILY TASK TRACKER'!$BD$5:$BD$1504,4),'DAILY TASK TRACKER'!$BD$5:$BD$1504,0))),"") | M91: =IFERROR(IF(INDEX('DAILY TASK TRACKER'!$G$5:$G$1504,MATCH(SMALL('DAILY TASK TRACKER'!$BD$5:$BD$1504,4),'DAILY TASK TRACKER'!$BD$5:$BD$1504,0))="","",INDEX('DAILY TASK TRACKER'!$G$5:$G$1504,MATCH(SMALL('DAILY TASK TRACKER'!$BD$5:$BD$1504,4),'DAILY TASK TRACKER'!$BD$5:$BD$1504,0))),"") | P91: =IFERROR(IF(INDEX('DAILY TASK TRACKER'!$I$5:$I$1504,MATCH(SMALL('DAILY TASK TRACKER'!$BD$5:$BD$1504,4),'DAILY TASK TRACKER'!$BD$5:$BD$1504,0))="","",INDEX('DAILY TASK TRACKER'!$I$5:$I$1504,MATCH(SMALL('DAILY TASK TRACKER'!$BD$5:$BD$1504,4),'DAILY TASK TRACKER'!$BD$5:$BD$1504,0))),"") | Q91: =IFERROR(IF(INDEX('DAILY TASK TRACKER'!$M$5:$M$1504,MATCH(SMALL('DAILY TASK TRACKER'!$BD$5:$BD$1504,4),'DAILY TASK TRACKER'!$BD$5:$BD$1504,0))="","",INDEX('DAILY TASK TRACKER'!$M$5:$M$1504,MATCH(SMALL('DAILY TASK TRACKER'!$BD$5:$BD$1504,4),'DAILY TASK TRACKER'!$BD$5:$BD$1504,0))),"") | R91: =IFERROR(IF(INDEX('DAILY TASK TRACKER'!$L$5:$L$1504,MATCH(SMALL('DAILY TASK TRACKER'!$BD$5:$BD$1504,4),'DAILY TASK TRACKER'!$BD$5:$BD$1504,0))="","",INDEX('DAILY TASK TRACKER'!$L$5:$L$1504,MATCH(SMALL('DAILY TASK TRACKER'!$BD$5:$BD$1504,4),'DAILY TASK TRACKER'!$BD$5:$BD$1504,0))),"")
B92: =IFERROR(IF(INDEX('DAILY TASK TRACKER'!$B$5:$B$1504,MATCH(SMALL('DAILY TASK TRACKER'!$BF$5:$BF$1504,5),'DAILY TASK TRACKER'!$BF$5:$BF$1504,0))="","",INDEX('DAILY TASK TRACKER'!$B$5:$B$1504,MATCH(SMALL('DAILY TASK TRACKER'!$BF$5:$BF$1504,5),'DAILY TASK TRACKER'!$BF$5:$BF$1504,0))),"") | C92: =IFERROR(IF(INDEX('DAILY TASK TRACKER'!$C$5:$C$1504,MATCH(SMALL('DAILY TASK TRACKER'!$BF$5:$BF$1504,5),'DAILY TASK TRACKER'!$BF$5:$BF$1504,0))="","",INDEX('DAILY TASK TRACKER'!$C$5:$C$1504,MATCH(SMALL('DAILY TASK TRACKER'!$BF$5:$BF$1504,5),'DAILY TASK TRACKER'!$BF$5:$BF$1504,0))),"") | D92: =IFERROR(IF(INDEX('DAILY TASK TRACKER'!$G$5:$G$1504,MATCH(SMALL('DAILY TASK TRACKER'!$BF$5:$BF$1504,5),'DAILY TASK TRACKER'!$BF$5:$BF$1504,0))="","",INDEX('DAILY TASK TRACKER'!$G$5:$G$1504,MATCH(SMALL('DAILY TASK TRACKER'!$BF$5:$BF$1504,5),'DAILY TASK TRACKER'!$BF$5:$BF$1504,0))),"") | G92: =IFERROR(IF(INDEX('DAILY TASK TRACKER'!$I$5:$I$1504,MATCH(SMALL('DAILY TASK TRACKER'!$BF$5:$BF$1504,5),'DAILY TASK TRACKER'!$BF$5:$BF$1504,0))="","",INDEX('DAILY TASK TRACKER'!$I$5:$I$1504,MATCH(SMALL('DAILY TASK TRACKER'!$BF$5:$BF$1504,5),'DAILY TASK TRACKER'!$BF$5:$BF$1504,0))),"") | H92: =IFERROR(IF(INDEX('DAILY TASK TRACKER'!$M$5:$M$1504,MATCH(SMALL('DAILY TASK TRACKER'!$BF$5:$BF$1504,5),'DAILY TASK TRACKER'!$BF$5:$BF$1504,0))="","",INDEX('DAILY TASK TRACKER'!$M$5:$M$1504,MATCH(SMALL('DAILY TASK TRACKER'!$BF$5:$BF$1504,5),'DAILY TASK TRACKER'!$BF$5:$BF$1504,0))),"") | I92: =IFERROR(IF(INDEX('DAILY TASK TRACKER'!$L$5:$L$1504,MATCH(SMALL('DAILY TASK TRACKER'!$BF$5:$BF$1504,5),'DAILY TASK TRACKER'!$BF$5:$BF$1504,0))="","",INDEX('DAILY TASK TRACKER'!$L$5:$L$1504,MATCH(SMALL('DAILY TASK TRACKER'!$BF$5:$BF$1504,5),'DAILY TASK TRACKER'!$BF$5:$BF$1504,0))),"") | K92: =IFERROR(IF(INDEX('DAILY TASK TRACKER'!$B$5:$B$1504,MATCH(SMALL('DAILY TASK TRACKER'!$BD$5:$BD$1504,5),'DAILY TASK TRACKER'!$BD$5:$BD$1504,0))="","",INDEX('DAILY TASK TRACKER'!$B$5:$B$1504,MATCH(SMALL('DAILY TASK TRACKER'!$BD$5:$BD$1504,5),'DAILY TASK TRACKER'!$BD$5:$BD$1504,0))),"") | L92: =IFERROR(IF(INDEX('DAILY TASK TRACKER'!$C$5:$C$1504,MATCH(SMALL('DAILY TASK TRACKER'!$BD$5:$BD$1504,5),'DAILY TASK TRACKER'!$BD$5:$BD$1504,0))="","",INDEX('DAILY TASK TRACKER'!$C$5:$C$1504,MATCH(SMALL('DAILY TASK TRACKER'!$BD$5:$BD$1504,5),'DAILY TASK TRACKER'!$BD$5:$BD$1504,0))),"") | M92: =IFERROR(IF(INDEX('DAILY TASK TRACKER'!$G$5:$G$1504,MATCH(SMALL('DAILY TASK TRACKER'!$BD$5:$BD$1504,5),'DAILY TASK TRACKER'!$BD$5:$BD$1504,0))="","",INDEX('DAILY TASK TRACKER'!$G$5:$G$1504,MATCH(SMALL('DAILY TASK TRACKER'!$BD$5:$BD$1504,5),'DAILY TASK TRACKER'!$BD$5:$BD$1504,0))),"") | P92: =IFERROR(IF(INDEX('DAILY TASK TRACKER'!$I$5:$I$1504,MATCH(SMALL('DAILY TASK TRACKER'!$BD$5:$BD$1504,5),'DAILY TASK TRACKER'!$BD$5:$BD$1504,0))="","",INDEX('DAILY TASK TRACKER'!$I$5:$I$1504,MATCH(SMALL('DAILY TASK TRACKER'!$BD$5:$BD$1504,5),'DAILY TASK TRACKER'!$BD$5:$BD$1504,0))),"") | Q92: =IFERROR(IF(INDEX('DAILY TASK TRACKER'!$M$5:$M$1504,MATCH(SMALL('DAILY TASK TRACKER'!$BD$5:$BD$1504,5),'DAILY TASK TRACKER'!$BD$5:$BD$1504,0))="","",INDEX('DAILY TASK TRACKER'!$M$5:$M$1504,MATCH(SMALL('DAILY TASK TRACKER'!$BD$5:$BD$1504,5),'DAILY TASK TRACKER'!$BD$5:$BD$1504,0))),"") | R92: =IFERROR(IF(INDEX('DAILY TASK TRACKER'!$L$5:$L$1504,MATCH(SMALL('DAILY TASK TRACKER'!$BD$5:$BD$1504,5),'DAILY TASK TRACKER'!$BD$5:$BD$1504,0))="","",INDEX('DAILY TASK TRACKER'!$L$5:$L$1504,MATCH(SMALL('DAILY TASK TRACKER'!$BD$5:$BD$1504,5),'DAILY TASK TRACKER'!$BD$5:$BD$1504,0))),"")
B93: =IFERROR(IF(INDEX('DAILY TASK TRACKER'!$B$5:$B$1504,MATCH(SMALL('DAILY TASK TRACKER'!$BF$5:$BF$1504,6),'DAILY TASK TRACKER'!$BF$5:$BF$1504,0))="","",INDEX('DAILY TASK TRACKER'!$B$5:$B$1504,MATCH(SMALL('DAILY TASK TRACKER'!$BF$5:$BF$1504,6),'DAILY TASK TRACKER'!$BF$5:$BF$1504,0))),"") | C93: =IFERROR(IF(INDEX('DAILY TASK TRACKER'!$C$5:$C$1504,MATCH(SMALL('DAILY TASK TRACKER'!$BF$5:$BF$1504,6),'DAILY TASK TRACKER'!$BF$5:$BF$1504,0))="","",INDEX('DAILY TASK TRACKER'!$C$5:$C$1504,MATCH(SMALL('DAILY TASK TRACKER'!$BF$5:$BF$1504,6),'DAILY TASK TRACKER'!$BF$5:$BF$1504,0))),"") | D93: =IFERROR(IF(INDEX('DAILY TASK TRACKER'!$G$5:$G$1504,MATCH(SMALL('DAILY TASK TRACKER'!$BF$5:$BF$1504,6),'DAILY TASK TRACKER'!$BF$5:$BF$1504,0))="","",INDEX('DAILY TASK TRACKER'!$G$5:$G$1504,MATCH(SMALL('DAILY TASK TRACKER'!$BF$5:$BF$1504,6),'DAILY TASK TRACKER'!$BF$5:$BF$1504,0))),"") | G93: =IFERROR(IF(INDEX('DAILY TASK TRACKER'!$I$5:$I$1504,MATCH(SMALL('DAILY TASK TRACKER'!$BF$5:$BF$1504,6),'DAILY TASK TRACKER'!$BF$5:$BF$1504,0))="","",INDEX('DAILY TASK TRACKER'!$I$5:$I$1504,MATCH(SMALL('DAILY TASK TRACKER'!$BF$5:$BF$1504,6),'DAILY TASK TRACKER'!$BF$5:$BF$1504,0))),"") | H93: =IFERROR(IF(INDEX('DAILY TASK TRACKER'!$M$5:$M$1504,MATCH(SMALL('DAILY TASK TRACKER'!$BF$5:$BF$1504,6),'DAILY TASK TRACKER'!$BF$5:$BF$1504,0))="","",INDEX('DAILY TASK TRACKER'!$M$5:$M$1504,MATCH(SMALL('DAILY TASK TRACKER'!$BF$5:$BF$1504,6),'DAILY TASK TRACKER'!$BF$5:$BF$1504,0))),"") | I93: =IFERROR(IF(INDEX('DAILY TASK TRACKER'!$L$5:$L$1504,MATCH(SMALL('DAILY TASK TRACKER'!$BF$5:$BF$1504,6),'DAILY TASK TRACKER'!$BF$5:$BF$1504,0))="","",INDEX('DAILY TASK TRACKER'!$L$5:$L$1504,MATCH(SMALL('DAILY TASK TRACKER'!$BF$5:$BF$1504,6),'DAILY TASK TRACKER'!$BF$5:$BF$1504,0))),"") | K93: =IFERROR(IF(INDEX('DAILY TASK TRACKER'!$B$5:$B$1504,MATCH(SMALL('DAILY TASK TRACKER'!$BD$5:$BD$1504,6),'DAILY TASK TRACKER'!$BD$5:$BD$1504,0))="","",INDEX('DAILY TASK TRACKER'!$B$5:$B$1504,MATCH(SMALL('DAILY TASK TRACKER'!$BD$5:$BD$1504,6),'DAILY TASK TRACKER'!$BD$5:$BD$1504,0))),"") | L93: =IFERROR(IF(INDEX('DAILY TASK TRACKER'!$C$5:$C$1504,MATCH(SMALL('DAILY TASK TRACKER'!$BD$5:$BD$1504,6),'DAILY TASK TRACKER'!$BD$5:$BD$1504,0))="","",INDEX('DAILY TASK TRACKER'!$C$5:$C$1504,MATCH(SMALL('DAILY TASK TRACKER'!$BD$5:$BD$1504,6),'DAILY TASK TRACKER'!$BD$5:$BD$1504,0))),"") | M93: =IFERROR(IF(INDEX('DAILY TASK TRACKER'!$G$5:$G$1504,MATCH(SMALL('DAILY TASK TRACKER'!$BD$5:$BD$1504,6),'DAILY TASK TRACKER'!$BD$5:$BD$1504,0))="","",INDEX('DAILY TASK TRACKER'!$G$5:$G$1504,MATCH(SMALL('DAILY TASK TRACKER'!$BD$5:$BD$1504,6),'DAILY TASK TRACKER'!$BD$5:$BD$1504,0))),"") | P93: =IFERROR(IF(INDEX('DAILY TASK TRACKER'!$I$5:$I$1504,MATCH(SMALL('DAILY TASK TRACKER'!$BD$5:$BD$1504,6),'DAILY TASK TRACKER'!$BD$5:$BD$1504,0))="","",INDEX('DAILY TASK TRACKER'!$I$5:$I$1504,MATCH(SMALL('DAILY TASK TRACKER'!$BD$5:$BD$1504,6),'DAILY TASK TRACKER'!$BD$5:$BD$1504,0))),"") | Q93: =IFERROR(IF(INDEX('DAILY TASK TRACKER'!$M$5:$M$1504,MATCH(SMALL('DAILY TASK TRACKER'!$BD$5:$BD$1504,6),'DAILY TASK TRACKER'!$BD$5:$BD$1504,0))="","",INDEX('DAILY TASK TRACKER'!$M$5:$M$1504,MATCH(SMALL('DAILY TASK TRACKER'!$BD$5:$BD$1504,6),'DAILY TASK TRACKER'!$BD$5:$BD$1504,0))),"") | R93: =IFERROR(IF(INDEX('DAILY TASK TRACKER'!$L$5:$L$1504,MATCH(SMALL('DAILY TASK TRACKER'!$BD$5:$BD$1504,6),'DAILY TASK TRACKER'!$BD$5:$BD$1504,0))="","",INDEX('DAILY TASK TRACKER'!$L$5:$L$1504,MATCH(SMALL('DAILY TASK TRACKER'!$BD$5:$BD$1504,6),'DAILY TASK TRACKER'!$BD$5:$BD$1504,0))),"")
B94: =IFERROR(IF(INDEX('DAILY TASK TRACKER'!$B$5:$B$1504,MATCH(SMALL('DAILY TASK TRACKER'!$BF$5:$BF$1504,7),'DAILY TASK TRACKER'!$BF$5:$BF$1504,0))="","",INDEX('DAILY TASK TRACKER'!$B$5:$B$1504,MATCH(SMALL('DAILY TASK TRACKER'!$BF$5:$BF$1504,7),'DAILY TASK TRACKER'!$BF$5:$BF$1504,0))),"") | C94: =IFERROR(IF(INDEX('DAILY TASK TRACKER'!$C$5:$C$1504,MATCH(SMALL('DAILY TASK TRACKER'!$BF$5:$BF$1504,7),'DAILY TASK TRACKER'!$BF$5:$BF$1504,0))="","",INDEX('DAILY TASK TRACKER'!$C$5:$C$1504,MATCH(SMALL('DAILY TASK TRACKER'!$BF$5:$BF$1504,7),'DAILY TASK TRACKER'!$BF$5:$BF$1504,0))),"") | D94: =IFERROR(IF(INDEX('DAILY TASK TRACKER'!$G$5:$G$1504,MATCH(SMALL('DAILY TASK TRACKER'!$BF$5:$BF$1504,7),'DAILY TASK TRACKER'!$BF$5:$BF$1504,0))="","",INDEX('DAILY TASK TRACKER'!$G$5:$G$1504,MATCH(SMALL('DAILY TASK TRACKER'!$BF$5:$BF$1504,7),'DAILY TASK TRACKER'!$BF$5:$BF$1504,0))),"") | G94: =IFERROR(IF(INDEX('DAILY TASK TRACKER'!$I$5:$I$1504,MATCH(SMALL('DAILY TASK TRACKER'!$BF$5:$BF$1504,7),'DAILY TASK TRACKER'!$BF$5:$BF$1504,0))="","",INDEX('DAILY TASK TRACKER'!$I$5:$I$1504,MATCH(SMALL('DAILY TASK TRACKER'!$BF$5:$BF$1504,7),'DAILY TASK TRACKER'!$BF$5:$BF$1504,0))),"") | H94: =IFERROR(IF(INDEX('DAILY TASK TRACKER'!$M$5:$M$1504,MATCH(SMALL('DAILY TASK TRACKER'!$BF$5:$BF$1504,7),'DAILY TASK TRACKER'!$BF$5:$BF$1504,0))="","",INDEX('DAILY TASK TRACKER'!$M$5:$M$1504,MATCH(SMALL('DAILY TASK TRACKER'!$BF$5:$BF$1504,7),'DAILY TASK TRACKER'!$BF$5:$BF$1504,0))),"") | I94: =IFERROR(IF(INDEX('DAILY TASK TRACKER'!$L$5:$L$1504,MATCH(SMALL('DAILY TASK TRACKER'!$BF$5:$BF$1504,7),'DAILY TASK TRACKER'!$BF$5:$BF$1504,0))="","",INDEX('DAILY TASK TRACKER'!$L$5:$L$1504,MATCH(SMALL('DAILY TASK TRACKER'!$BF$5:$BF$1504,7),'DAILY TASK TRACKER'!$BF$5:$BF$1504,0))),"") | K94: =IFERROR(IF(INDEX('DAILY TASK TRACKER'!$B$5:$B$1504,MATCH(SMALL('DAILY TASK TRACKER'!$BD$5:$BD$1504,7),'DAILY TASK TRACKER'!$BD$5:$BD$1504,0))="","",INDEX('DAILY TASK TRACKER'!$B$5:$B$1504,MATCH(SMALL('DAILY TASK TRACKER'!$BD$5:$BD$1504,7),'DAILY TASK TRACKER'!$BD$5:$BD$1504,0))),"") | L94: =IFERROR(IF(INDEX('DAILY TASK TRACKER'!$C$5:$C$1504,MATCH(SMALL('DAILY TASK TRACKER'!$BD$5:$BD$1504,7),'DAILY TASK TRACKER'!$BD$5:$BD$1504,0))="","",INDEX('DAILY TASK TRACKER'!$C$5:$C$1504,MATCH(SMALL('DAILY TASK TRACKER'!$BD$5:$BD$1504,7),'DAILY TASK TRACKER'!$BD$5:$BD$1504,0))),"") | M94: =IFERROR(IF(INDEX('DAILY TASK TRACKER'!$G$5:$G$1504,MATCH(SMALL('DAILY TASK TRACKER'!$BD$5:$BD$1504,7),'DAILY TASK TRACKER'!$BD$5:$BD$1504,0))="","",INDEX('DAILY TASK TRACKER'!$G$5:$G$1504,MATCH(SMALL('DAILY TASK TRACKER'!$BD$5:$BD$1504,7),'DAILY TASK TRACKER'!$BD$5:$BD$1504,0))),"") | P94: =IFERROR(IF(INDEX('DAILY TASK TRACKER'!$I$5:$I$1504,MATCH(SMALL('DAILY TASK TRACKER'!$BD$5:$BD$1504,7),'DAILY TASK TRACKER'!$BD$5:$BD$1504,0))="","",INDEX('DAILY TASK TRACKER'!$I$5:$I$1504,MATCH(SMALL('DAILY TASK TRACKER'!$BD$5:$BD$1504,7),'DAILY TASK TRACKER'!$BD$5:$BD$1504,0))),"") | Q94: =IFERROR(IF(INDEX('DAILY TASK TRACKER'!$M$5:$M$1504,MATCH(SMALL('DAILY TASK TRACKER'!$BD$5:$BD$1504,7),'DAILY TASK TRACKER'!$BD$5:$BD$1504,0))="","",INDEX('DAILY TASK TRACKER'!$M$5:$M$1504,MATCH(SMALL('DAILY TASK TRACKER'!$BD$5:$BD$1504,7),'DAILY TASK TRACKER'!$BD$5:$BD$1504,0))),"") | R94: =IFERROR(IF(INDEX('DAILY TASK TRACKER'!$L$5:$L$1504,MATCH(SMALL('DAILY TASK TRACKER'!$BD$5:$BD$1504,7),'DAILY TASK TRACKER'!$BD$5:$BD$1504,0))="","",INDEX('DAILY TASK TRACKER'!$L$5:$L$1504,MATCH(SMALL('DAILY TASK TRACKER'!$BD$5:$BD$1504,7),'DAILY TASK TRACKER'!$BD$5:$BD$1504,0))),"")
B95: =IFERROR(IF(INDEX('DAILY TASK TRACKER'!$B$5:$B$1504,MATCH(SMALL('DAILY TASK TRACKER'!$BF$5:$BF$1504,8),'DAILY TASK TRACKER'!$BF$5:$BF$1504,0))="","",INDEX('DAILY TASK TRACKER'!$B$5:$B$1504,MATCH(SMALL('DAILY TASK TRACKER'!$BF$5:$BF$1504,8),'DAILY TASK TRACKER'!$BF$5:$BF$1504,0))),"") | C95: =IFERROR(IF(INDEX('DAILY TASK TRACKER'!$C$5:$C$1504,MATCH(SMALL('DAILY TASK TRACKER'!$BF$5:$BF$1504,8),'DAILY TASK TRACKER'!$BF$5:$BF$1504,0))="","",INDEX('DAILY TASK TRACKER'!$C$5:$C$1504,MATCH(SMALL('DAILY TASK TRACKER'!$BF$5:$BF$1504,8),'DAILY TASK TRACKER'!$BF$5:$BF$1504,0))),"") | D95: =IFERROR(IF(INDEX('DAILY TASK TRACKER'!$G$5:$G$1504,MATCH(SMALL('DAILY TASK TRACKER'!$BF$5:$BF$1504,8),'DAILY TASK TRACKER'!$BF$5:$BF$1504,0))="","",INDEX('DAILY TASK TRACKER'!$G$5:$G$1504,MATCH(SMALL('DAILY TASK TRACKER'!$BF$5:$BF$1504,8),'DAILY TASK TRACKER'!$BF$5:$BF$1504,0))),"") | G95: =IFERROR(IF(INDEX('DAILY TASK TRACKER'!$I$5:$I$1504,MATCH(SMALL('DAILY TASK TRACKER'!$BF$5:$BF$1504,8),'DAILY TASK TRACKER'!$BF$5:$BF$1504,0))="","",INDEX('DAILY TASK TRACKER'!$I$5:$I$1504,MATCH(SMALL('DAILY TASK TRACKER'!$BF$5:$BF$1504,8),'DAILY TASK TRACKER'!$BF$5:$BF$1504,0))),"") | H95: =IFERROR(IF(INDEX('DAILY TASK TRACKER'!$M$5:$M$1504,MATCH(SMALL('DAILY TASK TRACKER'!$BF$5:$BF$1504,8),'DAILY TASK TRACKER'!$BF$5:$BF$1504,0))="","",INDEX('DAILY TASK TRACKER'!$M$5:$M$1504,MATCH(SMALL('DAILY TASK TRACKER'!$BF$5:$BF$1504,8),'DAILY TASK TRACKER'!$BF$5:$BF$1504,0))),"") | I95: =IFERROR(IF(INDEX('DAILY TASK TRACKER'!$L$5:$L$1504,MATCH(SMALL('DAILY TASK TRACKER'!$BF$5:$BF$1504,8),'DAILY TASK TRACKER'!$BF$5:$BF$1504,0))="","",INDEX('DAILY TASK TRACKER'!$L$5:$L$1504,MATCH(SMALL('DAILY TASK TRACKER'!$BF$5:$BF$1504,8),'DAILY TASK TRACKER'!$BF$5:$BF$1504,0))),"") | K95: =IFERROR(IF(INDEX('DAILY TASK TRACKER'!$B$5:$B$1504,MATCH(SMALL('DAILY TASK TRACKER'!$BD$5:$BD$1504,8),'DAILY TASK TRACKER'!$BD$5:$BD$1504,0))="","",INDEX('DAILY TASK TRACKER'!$B$5:$B$1504,MATCH(SMALL('DAILY TASK TRACKER'!$BD$5:$BD$1504,8),'DAILY TASK TRACKER'!$BD$5:$BD$1504,0))),"") | L95: =IFERROR(IF(INDEX('DAILY TASK TRACKER'!$C$5:$C$1504,MATCH(SMALL('DAILY TASK TRACKER'!$BD$5:$BD$1504,8),'DAILY TASK TRACKER'!$BD$5:$BD$1504,0))="","",INDEX('DAILY TASK TRACKER'!$C$5:$C$1504,MATCH(SMALL('DAILY TASK TRACKER'!$BD$5:$BD$1504,8),'DAILY TASK TRACKER'!$BD$5:$BD$1504,0))),"") | M95: =IFERROR(IF(INDEX('DAILY TASK TRACKER'!$G$5:$G$1504,MATCH(SMALL('DAILY TASK TRACKER'!$BD$5:$BD$1504,8),'DAILY TASK TRACKER'!$BD$5:$BD$1504,0))="","",INDEX('DAILY TASK TRACKER'!$G$5:$G$1504,MATCH(SMALL('DAILY TASK TRACKER'!$BD$5:$BD$1504,8),'DAILY TASK TRACKER'!$BD$5:$BD$1504,0))),"") | P95: =IFERROR(IF(INDEX('DAILY TASK TRACKER'!$I$5:$I$1504,MATCH(SMALL('DAILY TASK TRACKER'!$BD$5:$BD$1504,8),'DAILY TASK TRACKER'!$BD$5:$BD$1504,0))="","",INDEX('DAILY TASK TRACKER'!$I$5:$I$1504,MATCH(SMALL('DAILY TASK TRACKER'!$BD$5:$BD$1504,8),'DAILY TASK TRACKER'!$BD$5:$BD$1504,0))),"") | Q95: =IFERROR(IF(INDEX('DAILY TASK TRACKER'!$M$5:$M$1504,MATCH(SMALL('DAILY TASK TRACKER'!$BD$5:$BD$1504,8),'DAILY TASK TRACKER'!$BD$5:$BD$1504,0))="","",INDEX('DAILY TASK TRACKER'!$M$5:$M$1504,MATCH(SMALL('DAILY TASK TRACKER'!$BD$5:$BD$1504,8),'DAILY TASK TRACKER'!$BD$5:$BD$1504,0))),"") | R95: =IFERROR(IF(INDEX('DAILY TASK TRACKER'!$L$5:$L$1504,MATCH(SMALL('DAILY TASK TRACKER'!$BD$5:$BD$1504,8),'DAILY TASK TRACKER'!$BD$5:$BD$1504,0))="","",INDEX('DAILY TASK TRACKER'!$L$5:$L$1504,MATCH(SMALL('DAILY TASK TRACKER'!$BD$5:$BD$1504,8),'DAILY TASK TRACKER'!$BD$5:$BD$1504,0))),"")
B97: Q5. Who is working on what? (open work per team member) | K97: Q6. Which client needs attention?
B98: Team Member | D98: Open | E98: Overdue | F98: Blocked | G98: Due <=2d | H98: Clients with open work | K98: Client | M98: Overdue | N98: Blocked | O98: Camp. Attn | P98: Completion | Q98: Current Priority
B99: ='TEAM PERFORMANCE'!A7 -> Ayush Jain | D99: ='TEAM PERFORMANCE'!H7 -> 16 | E99: ='TEAM PERFORMANCE'!F7 -> 0 | F99: ='TEAM PERFORMANCE'!G7 -> 0 | G99: ='TEAM PERFORMANCE'!I7 -> 0 | H99: ='TEAM PERFORMANCE'!U7 -> Chola MS, Magnasoft, Eternelle, Vestrics, Google Chrome Enterprise | K99: =IFERROR(IF(INDEX('CLIENT PERFORMANCE'!$A$7:$A$36,MATCH(SMALL('CLIENT PERFORMANCE'!$AD$7:$AD$36,1),'CLIENT PERFORMANCE'!$AD$7:$AD$36,0))="","",INDEX('CLIENT PERFORMANCE'!$A$7:$A$36,MATCH(SMALL('CLIENT PERFORMANCE'!$AD$7:$AD$36,1),'CLIENT PERFORMANCE'!$AD$7:$AD$36,0))),"- none -") -> SAP | M99: =IFERROR(IF(INDEX('CLIENT PERFORMANCE'!$H$7:$H$36,MATCH(SMALL('CLIENT PERFORMANCE'!$AD$7:$AD$36,1),'CLIENT PERFORMANCE'!$AD$7:$AD$36,0))="","",INDEX('CLIENT PERFORMANCE'!$H$7:$H$36,MATCH(SMALL('CLIENT PERFORMANCE'!$AD$7:$AD$36,1),'CLIENT PERFORMANCE'!$AD$7:$AD$36,0))),"") -> 3 | N99: =IFERROR(IF(INDEX('CLIENT PERFORMANCE'!$I$7:$I$36,MATCH(SMALL('CLIENT PERFORMANCE'!$AD$7:$AD$36,1),'CLIENT PERFORMANCE'!$AD$7:$AD$36,0))="","",INDEX('CLIENT PERFORMANCE'!$I$7:$I$36,MATCH(SMALL('CLIENT PERFORMANCE'!$AD$7:$AD$36,1),'CLIENT PERFORMANCE'!$AD$7:$AD$36,0))),"") -> 0 | O99: =IFERROR(IF(INDEX('CLIENT PERFORMANCE'!$Y$7:$Y$36,MATCH(SMALL('CLIENT PERFORMANCE'!$AD$7:$AD$36,1),'CLIENT PERFORMANCE'!$AD$7:$AD$36,0))="","",INDEX('CLIENT PERFORMANCE'!$Y$7:$Y$36,MATCH(SMALL('CLIENT PERFORMANCE'!$AD$7:$AD$36,1),'CLIENT PERFORMANCE'!$AD$7:$AD$36,0))),"") -> 0 | P99: =IFERROR(IF(INDEX('CLIENT PERFORMANCE'!$J$7:$J$36,MATCH(SMALL('CLIENT PERFORMANCE'!$AD$7:$AD$36,1),'CLIENT PERFORMANCE'!$AD$7:$AD$36,0))="","",INDEX('CLIENT PERFORMANCE'!$J$7:$J$36,MATCH(SMALL('CLIENT PERFORMANCE'!$AD$7:$AD$36,1),'CLIENT PERFORMANCE'!$AD$7:$AD$36,0))),"") -> 0 | Q99: =IFERROR(IF(INDEX('CLIENT PERFORMANCE'!$AB$7:$AB$36,MATCH(SMALL('CLIENT PERFORMANCE'!$AD$7:$AD$36,1),'CLIENT PERFORMANCE'!$AD$7:$AD$36,0))="","",INDEX('CLIENT PERFORMANCE'!$AB$7:$AB$36,MATCH(SMALL('CLIENT PERFORMANCE'!$AD$7:$AD$36,1),'CLIENT PERFORMANCE'!$AD$7:$AD$36,0))),"")
B100: ='TEAM PERFORMANCE'!A8 -> Piyush Sambria | D100: ='TEAM PERFORMANCE'!H8 -> 0 | E100: ='TEAM PERFORMANCE'!F8 -> 0 | F100: ='TEAM PERFORMANCE'!G8 -> 0 | G100: ='TEAM PERFORMANCE'!I8 -> 0 | H100: ='TEAM PERFORMANCE'!U8 | K100: =IFERROR(IF(INDEX('CLIENT PERFORMANCE'!$A$7:$A$36,MATCH(SMALL('CLIENT PERFORMANCE'!$AD$7:$AD$36,2),'CLIENT PERFORMANCE'!$AD$7:$AD$36,0))="","",INDEX('CLIENT PERFORMANCE'!$A$7:$A$36,MATCH(SMALL('CLIENT PERFORMANCE'!$AD$7:$AD$36,2),'CLIENT PERFORMANCE'!$AD$7:$AD$36,0))),"") | M100: =IFERROR(IF(INDEX('CLIENT PERFORMANCE'!$H$7:$H$36,MATCH(SMALL('CLIENT PERFORMANCE'!$AD$7:$AD$36,2),'CLIENT PERFORMANCE'!$AD$7:$AD$36,0))="","",INDEX('CLIENT PERFORMANCE'!$H$7:$H$36,MATCH(SMALL('CLIENT PERFORMANCE'!$AD$7:$AD$36,2),'CLIENT PERFORMANCE'!$AD$7:$AD$36,0))),"") | N100: =IFERROR(IF(INDEX('CLIENT PERFORMANCE'!$I$7:$I$36,MATCH(SMALL('CLIENT PERFORMANCE'!$AD$7:$AD$36,2),'CLIENT PERFORMANCE'!$AD$7:$AD$36,0))="","",INDEX('CLIENT PERFORMANCE'!$I$7:$I$36,MATCH(SMALL('CLIENT PERFORMANCE'!$AD$7:$AD$36,2),'CLIENT PERFORMANCE'!$AD$7:$AD$36,0))),"") | O100: =IFERROR(IF(INDEX('CLIENT PERFORMANCE'!$Y$7:$Y$36,MATCH(SMALL('CLIENT PERFORMANCE'!$AD$7:$AD$36,2),'CLIENT PERFORMANCE'!$AD$7:$AD$36,0))="","",INDEX('CLIENT PERFORMANCE'!$Y$7:$Y$36,MATCH(SMALL('CLIENT PERFORMANCE'!$AD$7:$AD$36,2),'CLIENT PERFORMANCE'!$AD$7:$AD$36,0))),"") | P100: =IFERROR(IF(INDEX('CLIENT PERFORMANCE'!$J$7:$J$36,MATCH(SMALL('CLIENT PERFORMANCE'!$AD$7:$AD$36,2),'CLIENT PERFORMANCE'!$AD$7:$AD$36,0))="","",INDEX('CLIENT PERFORMANCE'!$J$7:$J$36,MATCH(SMALL('CLIENT PERFORMANCE'!$AD$7:$AD$36,2),'CLIENT PERFORMANCE'!$AD$7:$AD$36,0))),"") | Q100: =IFERROR(IF(INDEX('CLIENT PERFORMANCE'!$AB$7:$AB$36,MATCH(SMALL('CLIENT PERFORMANCE'!$AD$7:$AD$36,2),'CLIENT PERFORMANCE'!$AD$7:$AD$36,0))="","",INDEX('CLIENT PERFORMANCE'!$AB$7:$AB$36,MATCH(SMALL('CLIENT PERFORMANCE'!$AD$7:$AD$36,2),'CLIENT PERFORMANCE'!$AD$7:$AD$36,0))),"")
B101: ='TEAM PERFORMANCE'!A9 -> Riya Diwan | D101: ='TEAM PERFORMANCE'!H9 -> 16 | E101: ='TEAM PERFORMANCE'!F9 -> 0 | F101: ='TEAM PERFORMANCE'!G9 -> 0 | G101: ='TEAM PERFORMANCE'!I9 -> 0 | H101: ='TEAM PERFORMANCE'!U9 -> Chola MS, Magnasoft, Eternelle, Vestrics, SAP, Google Chrome Enterprise | K101: =IFERROR(IF(INDEX('CLIENT PERFORMANCE'!$A$7:$A$36,MATCH(SMALL('CLIENT PERFORMANCE'!$AD$7:$AD$36,3),'CLIENT PERFORMANCE'!$AD$7:$AD$36,0))="","",INDEX('CLIENT PERFORMANCE'!$A$7:$A$36,MATCH(SMALL('CLIENT PERFORMANCE'!$AD$7:$AD$36,3),'CLIENT PERFORMANCE'!$AD$7:$AD$36,0))),"") | M101: =IFERROR(IF(INDEX('CLIENT PERFORMANCE'!$H$7:$H$36,MATCH(SMALL('CLIENT PERFORMANCE'!$AD$7:$AD$36,3),'CLIENT PERFORMANCE'!$AD$7:$AD$36,0))="","",INDEX('CLIENT PERFORMANCE'!$H$7:$H$36,MATCH(SMALL('CLIENT PERFORMANCE'!$AD$7:$AD$36,3),'CLIENT PERFORMANCE'!$AD$7:$AD$36,0))),"") | N101: =IFERROR(IF(INDEX('CLIENT PERFORMANCE'!$I$7:$I$36,MATCH(SMALL('CLIENT PERFORMANCE'!$AD$7:$AD$36,3),'CLIENT PERFORMANCE'!$AD$7:$AD$36,0))="","",INDEX('CLIENT PERFORMANCE'!$I$7:$I$36,MATCH(SMALL('CLIENT PERFORMANCE'!$AD$7:$AD$36,3),'CLIENT PERFORMANCE'!$AD$7:$AD$36,0))),"") | O101: =IFERROR(IF(INDEX('CLIENT PERFORMANCE'!$Y$7:$Y$36,MATCH(SMALL('CLIENT PERFORMANCE'!$AD$7:$AD$36,3),'CLIENT PERFORMANCE'!$AD$7:$AD$36,0))="","",INDEX('CLIENT PERFORMANCE'!$Y$7:$Y$36,MATCH(SMALL('CLIENT PERFORMANCE'!$AD$7:$AD$36,3),'CLIENT PERFORMANCE'!$AD$7:$AD$36,0))),"") | P101: =IFERROR(IF(INDEX('CLIENT PERFORMANCE'!$J$7:$J$36,MATCH(SMALL('CLIENT PERFORMANCE'!$AD$7:$AD$36,3),'CLIENT PERFORMANCE'!$AD$7:$AD$36,0))="","",INDEX('CLIENT PERFORMANCE'!$J$7:$J$36,MATCH(SMALL('CLIENT PERFORMANCE'!$AD$7:$AD$36,3),'CLIENT PERFORMANCE'!$AD$7:$AD$36,0))),"") | Q101: =IFERROR(IF(INDEX('CLIENT PERFORMANCE'!$AB$7:$AB$36,MATCH(SMALL('CLIENT PERFORMANCE'!$AD$7:$AD$36,3),'CLIENT PERFORMANCE'!$AD$7:$AD$36,0))="","",INDEX('CLIENT PERFORMANCE'!$AB$7:$AB$36,MATCH(SMALL('CLIENT PERFORMANCE'!$AD$7:$AD$36,3),'CLIENT PERFORMANCE'!$AD$7:$AD$36,0))),"")
B102: ='TEAM PERFORMANCE'!A10 -> Surbhi Pandey | D102: ='TEAM PERFORMANCE'!H10 -> 19 | E102: ='TEAM PERFORMANCE'!F10 -> 3 | F102: ='TEAM PERFORMANCE'!G10 -> 0 | G102: ='TEAM PERFORMANCE'!I10 -> 1 | H102: ='TEAM PERFORMANCE'!U10 -> SAP, Utimaco Singapore | K102: =IFERROR(IF(INDEX('CLIENT PERFORMANCE'!$A$7:$A$36,MATCH(SMALL('CLIENT PERFORMANCE'!$AD$7:$AD$36,4),'CLIENT PERFORMANCE'!$AD$7:$AD$36,0))="","",INDEX('CLIENT PERFORMANCE'!$A$7:$A$36,MATCH(SMALL('CLIENT PERFORMANCE'!$AD$7:$AD$36,4),'CLIENT PERFORMANCE'!$AD$7:$AD$36,0))),"") | M102: =IFERROR(IF(INDEX('CLIENT PERFORMANCE'!$H$7:$H$36,MATCH(SMALL('CLIENT PERFORMANCE'!$AD$7:$AD$36,4),'CLIENT PERFORMANCE'!$AD$7:$AD$36,0))="","",INDEX('CLIENT PERFORMANCE'!$H$7:$H$36,MATCH(SMALL('CLIENT PERFORMANCE'!$AD$7:$AD$36,4),'CLIENT PERFORMANCE'!$AD$7:$AD$36,0))),"") | N102: =IFERROR(IF(INDEX('CLIENT PERFORMANCE'!$I$7:$I$36,MATCH(SMALL('CLIENT PERFORMANCE'!$AD$7:$AD$36,4),'CLIENT PERFORMANCE'!$AD$7:$AD$36,0))="","",INDEX('CLIENT PERFORMANCE'!$I$7:$I$36,MATCH(SMALL('CLIENT PERFORMANCE'!$AD$7:$AD$36,4),'CLIENT PERFORMANCE'!$AD$7:$AD$36,0))),"") | O102: =IFERROR(IF(INDEX('CLIENT PERFORMANCE'!$Y$7:$Y$36,MATCH(SMALL('CLIENT PERFORMANCE'!$AD$7:$AD$36,4),'CLIENT PERFORMANCE'!$AD$7:$AD$36,0))="","",INDEX('CLIENT PERFORMANCE'!$Y$7:$Y$36,MATCH(SMALL('CLIENT PERFORMANCE'!$AD$7:$AD$36,4),'CLIENT PERFORMANCE'!$AD$7:$AD$36,0))),"") | P102: =IFERROR(IF(INDEX('CLIENT PERFORMANCE'!$J$7:$J$36,MATCH(SMALL('CLIENT PERFORMANCE'!$AD$7:$AD$36,4),'CLIENT PERFORMANCE'!$AD$7:$AD$36,0))="","",INDEX('CLIENT PERFORMANCE'!$J$7:$J$36,MATCH(SMALL('CLIENT PERFORMANCE'!$AD$7:$AD$36,4),'CLIENT PERFORMANCE'!$AD$7:$AD$36,0))),"") | Q102: =IFERROR(IF(INDEX('CLIENT PERFORMANCE'!$AB$7:$AB$36,MATCH(SMALL('CLIENT PERFORMANCE'!$AD$7:$AD$36,4),'CLIENT PERFORMANCE'!$AD$7:$AD$36,0))="","",INDEX('CLIENT PERFORMANCE'!$AB$7:$AB$36,MATCH(SMALL('CLIENT PERFORMANCE'!$AD$7:$AD$36,4),'CLIENT PERFORMANCE'!$AD$7:$AD$36,0))),"")
B103: ='TEAM PERFORMANCE'!A11 -> Rahul Sondhi | D103: ='TEAM PERFORMANCE'!H11 -> 0 | E103: ='TEAM PERFORMANCE'!F11 -> 0 | F103: ='TEAM PERFORMANCE'!G11 -> 0 | G103: ='TEAM PERFORMANCE'!I11 -> 0 | H103: ='TEAM PERFORMANCE'!U11 | K103: =IFERROR(IF(INDEX('CLIENT PERFORMANCE'!$A$7:$A$36,MATCH(SMALL('CLIENT PERFORMANCE'!$AD$7:$AD$36,5),'CLIENT PERFORMANCE'!$AD$7:$AD$36,0))="","",INDEX('CLIENT PERFORMANCE'!$A$7:$A$36,MATCH(SMALL('CLIENT PERFORMANCE'!$AD$7:$AD$36,5),'CLIENT PERFORMANCE'!$AD$7:$AD$36,0))),"") | M103: =IFERROR(IF(INDEX('CLIENT PERFORMANCE'!$H$7:$H$36,MATCH(SMALL('CLIENT PERFORMANCE'!$AD$7:$AD$36,5),'CLIENT PERFORMANCE'!$AD$7:$AD$36,0))="","",INDEX('CLIENT PERFORMANCE'!$H$7:$H$36,MATCH(SMALL('CLIENT PERFORMANCE'!$AD$7:$AD$36,5),'CLIENT PERFORMANCE'!$AD$7:$AD$36,0))),"") | N103: =IFERROR(IF(INDEX('CLIENT PERFORMANCE'!$I$7:$I$36,MATCH(SMALL('CLIENT PERFORMANCE'!$AD$7:$AD$36,5),'CLIENT PERFORMANCE'!$AD$7:$AD$36,0))="","",INDEX('CLIENT PERFORMANCE'!$I$7:$I$36,MATCH(SMALL('CLIENT PERFORMANCE'!$AD$7:$AD$36,5),'CLIENT PERFORMANCE'!$AD$7:$AD$36,0))),"") | O103: =IFERROR(IF(INDEX('CLIENT PERFORMANCE'!$Y$7:$Y$36,MATCH(SMALL('CLIENT PERFORMANCE'!$AD$7:$AD$36,5),'CLIENT PERFORMANCE'!$AD$7:$AD$36,0))="","",INDEX('CLIENT PERFORMANCE'!$Y$7:$Y$36,MATCH(SMALL('CLIENT PERFORMANCE'!$AD$7:$AD$36,5),'CLIENT PERFORMANCE'!$AD$7:$AD$36,0))),"") | P103: =IFERROR(IF(INDEX('CLIENT PERFORMANCE'!$J$7:$J$36,MATCH(SMALL('CLIENT PERFORMANCE'!$AD$7:$AD$36,5),'CLIENT PERFORMANCE'!$AD$7:$AD$36,0))="","",INDEX('CLIENT PERFORMANCE'!$J$7:$J$36,MATCH(SMALL('CLIENT PERFORMANCE'!$AD$7:$AD$36,5),'CLIENT PERFORMANCE'!$AD$7:$AD$36,0))),"") | Q103: =IFERROR(IF(INDEX('CLIENT PERFORMANCE'!$AB$7:$AB$36,MATCH(SMALL('CLIENT PERFORMANCE'!$AD$7:$AD$36,5),'CLIENT PERFORMANCE'!$AD$7:$AD$36,0))="","",INDEX('CLIENT PERFORMANCE'!$AB$7:$AB$36,MATCH(SMALL('CLIENT PERFORMANCE'!$AD$7:$AD$36,5),'CLIENT PERFORMANCE'!$AD$7:$AD$36,0))),"")
B104: ='TEAM PERFORMANCE'!A12 -> Priyanshu | D104: ='TEAM PERFORMANCE'!H12 -> 0 | E104: ='TEAM PERFORMANCE'!F12 -> 0 | F104: ='TEAM PERFORMANCE'!G12 -> 0 | G104: ='TEAM PERFORMANCE'!I12 -> 0 | H104: ='TEAM PERFORMANCE'!U12 | K104: =IFERROR(IF(INDEX('CLIENT PERFORMANCE'!$A$7:$A$36,MATCH(SMALL('CLIENT PERFORMANCE'!$AD$7:$AD$36,6),'CLIENT PERFORMANCE'!$AD$7:$AD$36,0))="","",INDEX('CLIENT PERFORMANCE'!$A$7:$A$36,MATCH(SMALL('CLIENT PERFORMANCE'!$AD$7:$AD$36,6),'CLIENT PERFORMANCE'!$AD$7:$AD$36,0))),"") | M104: =IFERROR(IF(INDEX('CLIENT PERFORMANCE'!$H$7:$H$36,MATCH(SMALL('CLIENT PERFORMANCE'!$AD$7:$AD$36,6),'CLIENT PERFORMANCE'!$AD$7:$AD$36,0))="","",INDEX('CLIENT PERFORMANCE'!$H$7:$H$36,MATCH(SMALL('CLIENT PERFORMANCE'!$AD$7:$AD$36,6),'CLIENT PERFORMANCE'!$AD$7:$AD$36,0))),"") | N104: =IFERROR(IF(INDEX('CLIENT PERFORMANCE'!$I$7:$I$36,MATCH(SMALL('CLIENT PERFORMANCE'!$AD$7:$AD$36,6),'CLIENT PERFORMANCE'!$AD$7:$AD$36,0))="","",INDEX('CLIENT PERFORMANCE'!$I$7:$I$36,MATCH(SMALL('CLIENT PERFORMANCE'!$AD$7:$AD$36,6),'CLIENT PERFORMANCE'!$AD$7:$AD$36,0))),"") | O104: =IFERROR(IF(INDEX('CLIENT PERFORMANCE'!$Y$7:$Y$36,MATCH(SMALL('CLIENT PERFORMANCE'!$AD$7:$AD$36,6),'CLIENT PERFORMANCE'!$AD$7:$AD$36,0))="","",INDEX('CLIENT PERFORMANCE'!$Y$7:$Y$36,MATCH(SMALL('CLIENT PERFORMANCE'!$AD$7:$AD$36,6),'CLIENT PERFORMANCE'!$AD$7:$AD$36,0))),"") | P104: =IFERROR(IF(INDEX('CLIENT PERFORMANCE'!$J$7:$J$36,MATCH(SMALL('CLIENT PERFORMANCE'!$AD$7:$AD$36,6),'CLIENT PERFORMANCE'!$AD$7:$AD$36,0))="","",INDEX('CLIENT PERFORMANCE'!$J$7:$J$36,MATCH(SMALL('CLIENT PERFORMANCE'!$AD$7:$AD$36,6),'CLIENT PERFORMANCE'!$AD$7:$AD$36,0))),"") | Q104: =IFERROR(IF(INDEX('CLIENT PERFORMANCE'!$AB$7:$AB$36,MATCH(SMALL('CLIENT PERFORMANCE'!$AD$7:$AD$36,6),'CLIENT PERFORMANCE'!$AD$7:$AD$36,0))="","",INDEX('CLIENT PERFORMANCE'!$AB$7:$AB$36,MATCH(SMALL('CLIENT PERFORMANCE'!$AD$7:$AD$36,6),'CLIENT PERFORMANCE'!$AD$7:$AD$36,0))),"")
B105: ='TEAM PERFORMANCE'!A13 -> Richi Bagla | D105: ='TEAM PERFORMANCE'!H13 -> 7 | E105: ='TEAM PERFORMANCE'!F13 -> 0 | F105: ='TEAM PERFORMANCE'!G13 -> 0 | G105: ='TEAM PERFORMANCE'!I13 -> 0 | H105: ='TEAM PERFORMANCE'!U13 -> Magnasoft, Eternelle, Vestrics, SAP, Ruckus Networks, Equinix | K105: =IFERROR(IF(INDEX('CLIENT PERFORMANCE'!$A$7:$A$36,MATCH(SMALL('CLIENT PERFORMANCE'!$AD$7:$AD$36,7),'CLIENT PERFORMANCE'!$AD$7:$AD$36,0))="","",INDEX('CLIENT PERFORMANCE'!$A$7:$A$36,MATCH(SMALL('CLIENT PERFORMANCE'!$AD$7:$AD$36,7),'CLIENT PERFORMANCE'!$AD$7:$AD$36,0))),"") | M105: =IFERROR(IF(INDEX('CLIENT PERFORMANCE'!$H$7:$H$36,MATCH(SMALL('CLIENT PERFORMANCE'!$AD$7:$AD$36,7),'CLIENT PERFORMANCE'!$AD$7:$AD$36,0))="","",INDEX('CLIENT PERFORMANCE'!$H$7:$H$36,MATCH(SMALL('CLIENT PERFORMANCE'!$AD$7:$AD$36,7),'CLIENT PERFORMANCE'!$AD$7:$AD$36,0))),"") | N105: =IFERROR(IF(INDEX('CLIENT PERFORMANCE'!$I$7:$I$36,MATCH(SMALL('CLIENT PERFORMANCE'!$AD$7:$AD$36,7),'CLIENT PERFORMANCE'!$AD$7:$AD$36,0))="","",INDEX('CLIENT PERFORMANCE'!$I$7:$I$36,MATCH(SMALL('CLIENT PERFORMANCE'!$AD$7:$AD$36,7),'CLIENT PERFORMANCE'!$AD$7:$AD$36,0))),"") | O105: =IFERROR(IF(INDEX('CLIENT PERFORMANCE'!$Y$7:$Y$36,MATCH(SMALL('CLIENT PERFORMANCE'!$AD$7:$AD$36,7),'CLIENT PERFORMANCE'!$AD$7:$AD$36,0))="","",INDEX('CLIENT PERFORMANCE'!$Y$7:$Y$36,MATCH(SMALL('CLIENT PERFORMANCE'!$AD$7:$AD$36,7),'CLIENT PERFORMANCE'!$AD$7:$AD$36,0))),"") | P105: =IFERROR(IF(INDEX('CLIENT PERFORMANCE'!$J$7:$J$36,MATCH(SMALL('CLIENT PERFORMANCE'!$AD$7:$AD$36,7),'CLIENT PERFORMANCE'!$AD$7:$AD$36,0))="","",INDEX('CLIENT PERFORMANCE'!$J$7:$J$36,MATCH(SMALL('CLIENT PERFORMANCE'!$AD$7:$AD$36,7),'CLIENT PERFORMANCE'!$AD$7:$AD$36,0))),"") | Q105: =IFERROR(IF(INDEX('CLIENT PERFORMANCE'!$AB$7:$AB$36,MATCH(SMALL('CLIENT PERFORMANCE'!$AD$7:$AD$36,7),'CLIENT PERFORMANCE'!$AD$7:$AD$36,0))="","",INDEX('CLIENT PERFORMANCE'!$AB$7:$AB$36,MATCH(SMALL('CLIENT PERFORMANCE'!$AD$7:$AD$36,7),'CLIENT PERFORMANCE'!$AD$7:$AD$36,0))),"")
B106: ='TEAM PERFORMANCE'!A14 -> Kapil Chadha | D106: ='TEAM PERFORMANCE'!H14 -> 0 | E106: ='TEAM PERFORMANCE'!F14 -> 0 | F106: ='TEAM PERFORMANCE'!G14 -> 0 | G106: ='TEAM PERFORMANCE'!I14 -> 0 | H106: ='TEAM PERFORMANCE'!U14 | K106: =IFERROR(IF(INDEX('CLIENT PERFORMANCE'!$A$7:$A$36,MATCH(SMALL('CLIENT PERFORMANCE'!$AD$7:$AD$36,8),'CLIENT PERFORMANCE'!$AD$7:$AD$36,0))="","",INDEX('CLIENT PERFORMANCE'!$A$7:$A$36,MATCH(SMALL('CLIENT PERFORMANCE'!$AD$7:$AD$36,8),'CLIENT PERFORMANCE'!$AD$7:$AD$36,0))),"") | M106: =IFERROR(IF(INDEX('CLIENT PERFORMANCE'!$H$7:$H$36,MATCH(SMALL('CLIENT PERFORMANCE'!$AD$7:$AD$36,8),'CLIENT PERFORMANCE'!$AD$7:$AD$36,0))="","",INDEX('CLIENT PERFORMANCE'!$H$7:$H$36,MATCH(SMALL('CLIENT PERFORMANCE'!$AD$7:$AD$36,8),'CLIENT PERFORMANCE'!$AD$7:$AD$36,0))),"") | N106: =IFERROR(IF(INDEX('CLIENT PERFORMANCE'!$I$7:$I$36,MATCH(SMALL('CLIENT PERFORMANCE'!$AD$7:$AD$36,8),'CLIENT PERFORMANCE'!$AD$7:$AD$36,0))="","",INDEX('CLIENT PERFORMANCE'!$I$7:$I$36,MATCH(SMALL('CLIENT PERFORMANCE'!$AD$7:$AD$36,8),'CLIENT PERFORMANCE'!$AD$7:$AD$36,0))),"") | O106: =IFERROR(IF(INDEX('CLIENT PERFORMANCE'!$Y$7:$Y$36,MATCH(SMALL('CLIENT PERFORMANCE'!$AD$7:$AD$36,8),'CLIENT PERFORMANCE'!$AD$7:$AD$36,0))="","",INDEX('CLIENT PERFORMANCE'!$Y$7:$Y$36,MATCH(SMALL('CLIENT PERFORMANCE'!$AD$7:$AD$36,8),'CLIENT PERFORMANCE'!$AD$7:$AD$36,0))),"") | P106: =IFERROR(IF(INDEX('CLIENT PERFORMANCE'!$J$7:$J$36,MATCH(SMALL('CLIENT PERFORMANCE'!$AD$7:$AD$36,8),'CLIENT PERFORMANCE'!$AD$7:$AD$36,0))="","",INDEX('CLIENT PERFORMANCE'!$J$7:$J$36,MATCH(SMALL('CLIENT PERFORMANCE'!$AD$7:$AD$36,8),'CLIENT PERFORMANCE'!$AD$7:$AD$36,0))),"") | Q106: =IFERROR(IF(INDEX('CLIENT PERFORMANCE'!$AB$7:$AB$36,MATCH(SMALL('CLIENT PERFORMANCE'!$AD$7:$AD$36,8),'CLIENT PERFORMANCE'!$AD$7:$AD$36,0))="","",INDEX('CLIENT PERFORMANCE'!$AB$7:$AB$36,MATCH(SMALL('CLIENT PERFORMANCE'!$AD$7:$AD$36,8),'CLIENT PERFORMANCE'!$AD$7:$AD$36,0))),"")
B107: ='TEAM PERFORMANCE'!A15 | D107: ='TEAM PERFORMANCE'!H15 | E107: ='TEAM PERFORMANCE'!F15 | F107: ='TEAM PERFORMANCE'!G15 | G107: ='TEAM PERFORMANCE'!I15 | H107: ='TEAM PERFORMANCE'!U15 | K107: =IFERROR(IF(INDEX('CLIENT PERFORMANCE'!$A$7:$A$36,MATCH(SMALL('CLIENT PERFORMANCE'!$AD$7:$AD$36,9),'CLIENT PERFORMANCE'!$AD$7:$AD$36,0))="","",INDEX('CLIENT PERFORMANCE'!$A$7:$A$36,MATCH(SMALL('CLIENT PERFORMANCE'!$AD$7:$AD$36,9),'CLIENT PERFORMANCE'!$AD$7:$AD$36,0))),"") | M107: =IFERROR(IF(INDEX('CLIENT PERFORMANCE'!$H$7:$H$36,MATCH(SMALL('CLIENT PERFORMANCE'!$AD$7:$AD$36,9),'CLIENT PERFORMANCE'!$AD$7:$AD$36,0))="","",INDEX('CLIENT PERFORMANCE'!$H$7:$H$36,MATCH(SMALL('CLIENT PERFORMANCE'!$AD$7:$AD$36,9),'CLIENT PERFORMANCE'!$AD$7:$AD$36,0))),"") | N107: =IFERROR(IF(INDEX('CLIENT PERFORMANCE'!$I$7:$I$36,MATCH(SMALL('CLIENT PERFORMANCE'!$AD$7:$AD$36,9),'CLIENT PERFORMANCE'!$AD$7:$AD$36,0))="","",INDEX('CLIENT PERFORMANCE'!$I$7:$I$36,MATCH(SMALL('CLIENT PERFORMANCE'!$AD$7:$AD$36,9),'CLIENT PERFORMANCE'!$AD$7:$AD$36,0))),"") | O107: =IFERROR(IF(INDEX('CLIENT PERFORMANCE'!$Y$7:$Y$36,MATCH(SMALL('CLIENT PERFORMANCE'!$AD$7:$AD$36,9),'CLIENT PERFORMANCE'!$AD$7:$AD$36,0))="","",INDEX('CLIENT PERFORMANCE'!$Y$7:$Y$36,MATCH(SMALL('CLIENT PERFORMANCE'!$AD$7:$AD$36,9),'CLIENT PERFORMANCE'!$AD$7:$AD$36,0))),"") | P107: =IFERROR(IF(INDEX('CLIENT PERFORMANCE'!$J$7:$J$36,MATCH(SMALL('CLIENT PERFORMANCE'!$AD$7:$AD$36,9),'CLIENT PERFORMANCE'!$AD$7:$AD$36,0))="","",INDEX('CLIENT PERFORMANCE'!$J$7:$J$36,MATCH(SMALL('CLIENT PERFORMANCE'!$AD$7:$AD$36,9),'CLIENT PERFORMANCE'!$AD$7:$AD$36,0))),"") | Q107: =IFERROR(IF(INDEX('CLIENT PERFORMANCE'!$AB$7:$AB$36,MATCH(SMALL('CLIENT PERFORMANCE'!$AD$7:$AD$36,9),'CLIENT PERFORMANCE'!$AD$7:$AD$36,0))="","",INDEX('CLIENT PERFORMANCE'!$AB$7:$AB$36,MATCH(SMALL('CLIENT PERFORMANCE'!$AD$7:$AD$36,9),'CLIENT PERFORMANCE'!$AD$7:$AD$36,0))),"")
B108: ='TEAM PERFORMANCE'!A16 | D108: ='TEAM PERFORMANCE'!H16 | E108: ='TEAM PERFORMANCE'!F16 | F108: ='TEAM PERFORMANCE'!G16 | G108: ='TEAM PERFORMANCE'!I16 | H108: ='TEAM PERFORMANCE'!U16 | K108: =IFERROR(IF(INDEX('CLIENT PERFORMANCE'!$A$7:$A$36,MATCH(SMALL('CLIENT PERFORMANCE'!$AD$7:$AD$36,10),'CLIENT PERFORMANCE'!$AD$7:$AD$36,0))="","",INDEX('CLIENT PERFORMANCE'!$A$7:$A$36,MATCH(SMALL('CLIENT PERFORMANCE'!$AD$7:$AD$36,10),'CLIENT PERFORMANCE'!$AD$7:$AD$36,0))),"") | M108: =IFERROR(IF(INDEX('CLIENT PERFORMANCE'!$H$7:$H$36,MATCH(SMALL('CLIENT PERFORMANCE'!$AD$7:$AD$36,10),'CLIENT PERFORMANCE'!$AD$7:$AD$36,0))="","",INDEX('CLIENT PERFORMANCE'!$H$7:$H$36,MATCH(SMALL('CLIENT PERFORMANCE'!$AD$7:$AD$36,10),'CLIENT PERFORMANCE'!$AD$7:$AD$36,0))),"") | N108: =IFERROR(IF(INDEX('CLIENT PERFORMANCE'!$I$7:$I$36,MATCH(SMALL('CLIENT PERFORMANCE'!$AD$7:$AD$36,10),'CLIENT PERFORMANCE'!$AD$7:$AD$36,0))="","",INDEX('CLIENT PERFORMANCE'!$I$7:$I$36,MATCH(SMALL('CLIENT PERFORMANCE'!$AD$7:$AD$36,10),'CLIENT PERFORMANCE'!$AD$7:$AD$36,0))),"") | O108: =IFERROR(IF(INDEX('CLIENT PERFORMANCE'!$Y$7:$Y$36,MATCH(SMALL('CLIENT PERFORMANCE'!$AD$7:$AD$36,10),'CLIENT PERFORMANCE'!$AD$7:$AD$36,0))="","",INDEX('CLIENT PERFORMANCE'!$Y$7:$Y$36,MATCH(SMALL('CLIENT PERFORMANCE'!$AD$7:$AD$36,10),'CLIENT PERFORMANCE'!$AD$7:$AD$36,0))),"") | P108: =IFERROR(IF(INDEX('CLIENT PERFORMANCE'!$J$7:$J$36,MATCH(SMALL('CLIENT PERFORMANCE'!$AD$7:$AD$36,10),'CLIENT PERFORMANCE'!$AD$7:$AD$36,0))="","",INDEX('CLIENT PERFORMANCE'!$J$7:$J$36,MATCH(SMALL('CLIENT PERFORMANCE'!$AD$7:$AD$36,10),'CLIENT PERFORMANCE'!$AD$7:$AD$36,0))),"") | Q108: =IFERROR(IF(INDEX('CLIENT PERFORMANCE'!$AB$7:$AB$36,MATCH(SMALL('CLIENT PERFORMANCE'!$AD$7:$AD$36,10),'CLIENT PERFORMANCE'!$AD$7:$AD$36,0))="","",INDEX('CLIENT PERFORMANCE'!$AB$7:$AB$36,MATCH(SMALL('CLIENT PERFORMANCE'!$AD$7:$AD$36,10),'CLIENT PERFORMANCE'!$AD$7:$AD$36,0))),"")
B111: Q7. Which campaign needs attention? | K111: Q10. Which campaigns are performing well?
B112: Campaign | E112: Client | F112: Owner | G112: Performance | H112: Reason | K112: Campaign | N112: Client | O112: Owner | P112: Leads | Q112: Target | R112: Status
B113: =IFERROR(IF(INDEX('CAMPAIGN MASTER'!$B$5:$B$704,MATCH(SMALL('CAMPAIGN MASTER'!$AU$5:$AU$704,1),'CAMPAIGN MASTER'!$AU$5:$AU$704,0))="","",INDEX('CAMPAIGN MASTER'!$B$5:$B$704,MATCH(SMALL('CAMPAIGN MASTER'!$AU$5:$AU$704,1),'CAMPAIGN MASTER'!$AU$5:$AU$704,0))),"- none -") -> - none - | E113: =IFERROR(IF(INDEX('CAMPAIGN MASTER'!$A$5:$A$704,MATCH(SMALL('CAMPAIGN MASTER'!$AU$5:$AU$704,1),'CAMPAIGN MASTER'!$AU$5:$AU$704,0))="","",INDEX('CAMPAIGN MASTER'!$A$5:$A$704,MATCH(SMALL('CAMPAIGN MASTER'!$AU$5:$AU$704,1),'CAMPAIGN MASTER'!$AU$5:$AU$704,0))),"") | F113: =IFERROR(IF(INDEX('CAMPAIGN MASTER'!$I$5:$I$704,MATCH(SMALL('CAMPAIGN MASTER'!$AU$5:$AU$704,1),'CAMPAIGN MASTER'!$AU$5:$AU$704,0))="","",INDEX('CAMPAIGN MASTER'!$I$5:$I$704,MATCH(SMALL('CAMPAIGN MASTER'!$AU$5:$AU$704,1),'CAMPAIGN MASTER'!$AU$5:$AU$704,0))),"") | G113: =IFERROR(IF(INDEX('CAMPAIGN MASTER'!$AA$5:$AA$704,MATCH(SMALL('CAMPAIGN MASTER'!$AU$5:$AU$704,1),'CAMPAIGN MASTER'!$AU$5:$AU$704,0))="","",INDEX('CAMPAIGN MASTER'!$AA$5:$AA$704,MATCH(SMALL('CAMPAIGN MASTER'!$AU$5:$AU$704,1),'CAMPAIGN MASTER'!$AU$5:$AU$704,0))),"") | H113: =IFERROR(IF(INDEX('CAMPAIGN MASTER'!$AT$5:$AT$704,MATCH(SMALL('CAMPAIGN MASTER'!$AU$5:$AU$704,1),'CAMPAIGN MASTER'!$AU$5:$AU$704,0))="","",INDEX('CAMPAIGN MASTER'!$AT$5:$AT$704,MATCH(SMALL('CAMPAIGN MASTER'!$AU$5:$AU$704,1),'CAMPAIGN MASTER'!$AU$5:$AU$704,0))),"") | K113: =IFERROR(IF(INDEX('CAMPAIGN MASTER'!$B$5:$B$704,MATCH(SMALL('CAMPAIGN MASTER'!$AX$5:$AX$704,1),'CAMPAIGN MASTER'!$AX$5:$AX$704,0))="","",INDEX('CAMPAIGN MASTER'!$B$5:$B$704,MATCH(SMALL('CAMPAIGN MASTER'!$AX$5:$AX$704,1),'CAMPAIGN MASTER'!$AX$5:$AX$704,0))),"- none -") -> - none - | N113: =IFERROR(IF(INDEX('CAMPAIGN MASTER'!$A$5:$A$704,MATCH(SMALL('CAMPAIGN MASTER'!$AX$5:$AX$704,1),'CAMPAIGN MASTER'!$AX$5:$AX$704,0))="","",INDEX('CAMPAIGN MASTER'!$A$5:$A$704,MATCH(SMALL('CAMPAIGN MASTER'!$AX$5:$AX$704,1),'CAMPAIGN MASTER'!$AX$5:$AX$704,0))),"") | O113: =IFERROR(IF(INDEX('CAMPAIGN MASTER'!$I$5:$I$704,MATCH(SMALL('CAMPAIGN MASTER'!$AX$5:$AX$704,1),'CAMPAIGN MASTER'!$AX$5:$AX$704,0))="","",INDEX('CAMPAIGN MASTER'!$I$5:$I$704,MATCH(SMALL('CAMPAIGN MASTER'!$AX$5:$AX$704,1),'CAMPAIGN MASTER'!$AX$5:$AX$704,0))),"") | P113: =IFERROR(IF(INDEX('CAMPAIGN MASTER'!$R$5:$R$704,MATCH(SMALL('CAMPAIGN MASTER'!$AX$5:$AX$704,1),'CAMPAIGN MASTER'!$AX$5:$AX$704,0))="","",INDEX('CAMPAIGN MASTER'!$R$5:$R$704,MATCH(SMALL('CAMPAIGN MASTER'!$AX$5:$AX$704,1),'CAMPAIGN MASTER'!$AX$5:$AX$704,0))),"") | Q113: =IFERROR(IF(INDEX('CAMPAIGN MASTER'!$Q$5:$Q$704,MATCH(SMALL('CAMPAIGN MASTER'!$AX$5:$AX$704,1),'CAMPAIGN MASTER'!$AX$5:$AX$704,0))="","",INDEX('CAMPAIGN MASTER'!$Q$5:$Q$704,MATCH(SMALL('CAMPAIGN MASTER'!$AX$5:$AX$704,1),'CAMPAIGN MASTER'!$AX$5:$AX$704,0))),"") | R113: =IFERROR(IF(INDEX('CAMPAIGN MASTER'!$AA$5:$AA$704,MATCH(SMALL('CAMPAIGN MASTER'!$AX$5:$AX$704,1),'CAMPAIGN MASTER'!$AX$5:$AX$704,0))="","",INDEX('CAMPAIGN MASTER'!$AA$5:$AA$704,MATCH(SMALL('CAMPAIGN MASTER'!$AX$5:$AX$704,1),'CAMPAIGN MASTER'!$AX$5:$AX$704,0))),"")
B114: =IFERROR(IF(INDEX('CAMPAIGN MASTER'!$B$5:$B$704,MATCH(SMALL('CAMPAIGN MASTER'!$AU$5:$AU$704,2),'CAMPAIGN MASTER'!$AU$5:$AU$704,0))="","",INDEX('CAMPAIGN MASTER'!$B$5:$B$704,MATCH(SMALL('CAMPAIGN MASTER'!$AU$5:$AU$704,2),'CAMPAIGN MASTER'!$AU$5:$AU$704,0))),"") | E114: =IFERROR(IF(INDEX('CAMPAIGN MASTER'!$A$5:$A$704,MATCH(SMALL('CAMPAIGN MASTER'!$AU$5:$AU$704,2),'CAMPAIGN MASTER'!$AU$5:$AU$704,0))="","",INDEX('CAMPAIGN MASTER'!$A$5:$A$704,MATCH(SMALL('CAMPAIGN MASTER'!$AU$5:$AU$704,2),'CAMPAIGN MASTER'!$AU$5:$AU$704,0))),"") | F114: =IFERROR(IF(INDEX('CAMPAIGN MASTER'!$I$5:$I$704,MATCH(SMALL('CAMPAIGN MASTER'!$AU$5:$AU$704,2),'CAMPAIGN MASTER'!$AU$5:$AU$704,0))="","",INDEX('CAMPAIGN MASTER'!$I$5:$I$704,MATCH(SMALL('CAMPAIGN MASTER'!$AU$5:$AU$704,2),'CAMPAIGN MASTER'!$AU$5:$AU$704,0))),"") | G114: =IFERROR(IF(INDEX('CAMPAIGN MASTER'!$AA$5:$AA$704,MATCH(SMALL('CAMPAIGN MASTER'!$AU$5:$AU$704,2),'CAMPAIGN MASTER'!$AU$5:$AU$704,0))="","",INDEX('CAMPAIGN MASTER'!$AA$5:$AA$704,MATCH(SMALL('CAMPAIGN MASTER'!$AU$5:$AU$704,2),'CAMPAIGN MASTER'!$AU$5:$AU$704,0))),"") | H114: =IFERROR(IF(INDEX('CAMPAIGN MASTER'!$AT$5:$AT$704,MATCH(SMALL('CAMPAIGN MASTER'!$AU$5:$AU$704,2),'CAMPAIGN MASTER'!$AU$5:$AU$704,0))="","",INDEX('CAMPAIGN MASTER'!$AT$5:$AT$704,MATCH(SMALL('CAMPAIGN MASTER'!$AU$5:$AU$704,2),'CAMPAIGN MASTER'!$AU$5:$AU$704,0))),"") | K114: =IFERROR(IF(INDEX('CAMPAIGN MASTER'!$B$5:$B$704,MATCH(SMALL('CAMPAIGN MASTER'!$AX$5:$AX$704,2),'CAMPAIGN MASTER'!$AX$5:$AX$704,0))="","",INDEX('CAMPAIGN MASTER'!$B$5:$B$704,MATCH(SMALL('CAMPAIGN MASTER'!$AX$5:$AX$704,2),'CAMPAIGN MASTER'!$AX$5:$AX$704,0))),"") | N114: =IFERROR(IF(INDEX('CAMPAIGN MASTER'!$A$5:$A$704,MATCH(SMALL('CAMPAIGN MASTER'!$AX$5:$AX$704,2),'CAMPAIGN MASTER'!$AX$5:$AX$704,0))="","",INDEX('CAMPAIGN MASTER'!$A$5:$A$704,MATCH(SMALL('CAMPAIGN MASTER'!$AX$5:$AX$704,2),'CAMPAIGN MASTER'!$AX$5:$AX$704,0))),"") | O114: =IFERROR(IF(INDEX('CAMPAIGN MASTER'!$I$5:$I$704,MATCH(SMALL('CAMPAIGN MASTER'!$AX$5:$AX$704,2),'CAMPAIGN MASTER'!$AX$5:$AX$704,0))="","",INDEX('CAMPAIGN MASTER'!$I$5:$I$704,MATCH(SMALL('CAMPAIGN MASTER'!$AX$5:$AX$704,2),'CAMPAIGN MASTER'!$AX$5:$AX$704,0))),"") | P114: =IFERROR(IF(INDEX('CAMPAIGN MASTER'!$R$5:$R$704,MATCH(SMALL('CAMPAIGN MASTER'!$AX$5:$AX$704,2),'CAMPAIGN MASTER'!$AX$5:$AX$704,0))="","",INDEX('CAMPAIGN MASTER'!$R$5:$R$704,MATCH(SMALL('CAMPAIGN MASTER'!$AX$5:$AX$704,2),'CAMPAIGN MASTER'!$AX$5:$AX$704,0))),"") | Q114: =IFERROR(IF(INDEX('CAMPAIGN MASTER'!$Q$5:$Q$704,MATCH(SMALL('CAMPAIGN MASTER'!$AX$5:$AX$704,2),'CAMPAIGN MASTER'!$AX$5:$AX$704,0))="","",INDEX('CAMPAIGN MASTER'!$Q$5:$Q$704,MATCH(SMALL('CAMPAIGN MASTER'!$AX$5:$AX$704,2),'CAMPAIGN MASTER'!$AX$5:$AX$704,0))),"") | R114: =IFERROR(IF(INDEX('CAMPAIGN MASTER'!$AA$5:$AA$704,MATCH(SMALL('CAMPAIGN MASTER'!$AX$5:$AX$704,2),'CAMPAIGN MASTER'!$AX$5:$AX$704,0))="","",INDEX('CAMPAIGN MASTER'!$AA$5:$AA$704,MATCH(SMALL('CAMPAIGN MASTER'!$AX$5:$AX$704,2),'CAMPAIGN MASTER'!$AX$5:$AX$704,0))),"")
B115: =IFERROR(IF(INDEX('CAMPAIGN MASTER'!$B$5:$B$704,MATCH(SMALL('CAMPAIGN MASTER'!$AU$5:$AU$704,3),'CAMPAIGN MASTER'!$AU$5:$AU$704,0))="","",INDEX('CAMPAIGN MASTER'!$B$5:$B$704,MATCH(SMALL('CAMPAIGN MASTER'!$AU$5:$AU$704,3),'CAMPAIGN MASTER'!$AU$5:$AU$704,0))),"") | E115: =IFERROR(IF(INDEX('CAMPAIGN MASTER'!$A$5:$A$704,MATCH(SMALL('CAMPAIGN MASTER'!$AU$5:$AU$704,3),'CAMPAIGN MASTER'!$AU$5:$AU$704,0))="","",INDEX('CAMPAIGN MASTER'!$A$5:$A$704,MATCH(SMALL('CAMPAIGN MASTER'!$AU$5:$AU$704,3),'CAMPAIGN MASTER'!$AU$5:$AU$704,0))),"") | F115: =IFERROR(IF(INDEX('CAMPAIGN MASTER'!$I$5:$I$704,MATCH(SMALL('CAMPAIGN MASTER'!$AU$5:$AU$704,3),'CAMPAIGN MASTER'!$AU$5:$AU$704,0))="","",INDEX('CAMPAIGN MASTER'!$I$5:$I$704,MATCH(SMALL('CAMPAIGN MASTER'!$AU$5:$AU$704,3),'CAMPAIGN MASTER'!$AU$5:$AU$704,0))),"") | G115: =IFERROR(IF(INDEX('CAMPAIGN MASTER'!$AA$5:$AA$704,MATCH(SMALL('CAMPAIGN MASTER'!$AU$5:$AU$704,3),'CAMPAIGN MASTER'!$AU$5:$AU$704,0))="","",INDEX('CAMPAIGN MASTER'!$AA$5:$AA$704,MATCH(SMALL('CAMPAIGN MASTER'!$AU$5:$AU$704,3),'CAMPAIGN MASTER'!$AU$5:$AU$704,0))),"") | H115: =IFERROR(IF(INDEX('CAMPAIGN MASTER'!$AT$5:$AT$704,MATCH(SMALL('CAMPAIGN MASTER'!$AU$5:$AU$704,3),'CAMPAIGN MASTER'!$AU$5:$AU$704,0))="","",INDEX('CAMPAIGN MASTER'!$AT$5:$AT$704,MATCH(SMALL('CAMPAIGN MASTER'!$AU$5:$AU$704,3),'CAMPAIGN MASTER'!$AU$5:$AU$704,0))),"") | K115: =IFERROR(IF(INDEX('CAMPAIGN MASTER'!$B$5:$B$704,MATCH(SMALL('CAMPAIGN MASTER'!$AX$5:$AX$704,3),'CAMPAIGN MASTER'!$AX$5:$AX$704,0))="","",INDEX('CAMPAIGN MASTER'!$B$5:$B$704,MATCH(SMALL('CAMPAIGN MASTER'!$AX$5:$AX$704,3),'CAMPAIGN MASTER'!$AX$5:$AX$704,0))),"") | N115: =IFERROR(IF(INDEX('CAMPAIGN MASTER'!$A$5:$A$704,MATCH(SMALL('CAMPAIGN MASTER'!$AX$5:$AX$704,3),'CAMPAIGN MASTER'!$AX$5:$AX$704,0))="","",INDEX('CAMPAIGN MASTER'!$A$5:$A$704,MATCH(SMALL('CAMPAIGN MASTER'!$AX$5:$AX$704,3),'CAMPAIGN MASTER'!$AX$5:$AX$704,0))),"") | O115: =IFERROR(IF(INDEX('CAMPAIGN MASTER'!$I$5:$I$704,MATCH(SMALL('CAMPAIGN MASTER'!$AX$5:$AX$704,3),'CAMPAIGN MASTER'!$AX$5:$AX$704,0))="","",INDEX('CAMPAIGN MASTER'!$I$5:$I$704,MATCH(SMALL('CAMPAIGN MASTER'!$AX$5:$AX$704,3),'CAMPAIGN MASTER'!$AX$5:$AX$704,0))),"") | P115: =IFERROR(IF(INDEX('CAMPAIGN MASTER'!$R$5:$R$704,MATCH(SMALL('CAMPAIGN MASTER'!$AX$5:$AX$704,3),'CAMPAIGN MASTER'!$AX$5:$AX$704,0))="","",INDEX('CAMPAIGN MASTER'!$R$5:$R$704,MATCH(SMALL('CAMPAIGN MASTER'!$AX$5:$AX$704,3),'CAMPAIGN MASTER'!$AX$5:$AX$704,0))),"") | Q115: =IFERROR(IF(INDEX('CAMPAIGN MASTER'!$Q$5:$Q$704,MATCH(SMALL('CAMPAIGN MASTER'!$AX$5:$AX$704,3),'CAMPAIGN MASTER'!$AX$5:$AX$704,0))="","",INDEX('CAMPAIGN MASTER'!$Q$5:$Q$704,MATCH(SMALL('CAMPAIGN MASTER'!$AX$5:$AX$704,3),'CAMPAIGN MASTER'!$AX$5:$AX$704,0))),"") | R115: =IFERROR(IF(INDEX('CAMPAIGN MASTER'!$AA$5:$AA$704,MATCH(SMALL('CAMPAIGN MASTER'!$AX$5:$AX$704,3),'CAMPAIGN MASTER'!$AX$5:$AX$704,0))="","",INDEX('CAMPAIGN MASTER'!$AA$5:$AA$704,MATCH(SMALL('CAMPAIGN MASTER'!$AX$5:$AX$704,3),'CAMPAIGN MASTER'!$AX$5:$AX$704,0))),"")
B116: =IFERROR(IF(INDEX('CAMPAIGN MASTER'!$B$5:$B$704,MATCH(SMALL('CAMPAIGN MASTER'!$AU$5:$AU$704,4),'CAMPAIGN MASTER'!$AU$5:$AU$704,0))="","",INDEX('CAMPAIGN MASTER'!$B$5:$B$704,MATCH(SMALL('CAMPAIGN MASTER'!$AU$5:$AU$704,4),'CAMPAIGN MASTER'!$AU$5:$AU$704,0))),"") | E116: =IFERROR(IF(INDEX('CAMPAIGN MASTER'!$A$5:$A$704,MATCH(SMALL('CAMPAIGN MASTER'!$AU$5:$AU$704,4),'CAMPAIGN MASTER'!$AU$5:$AU$704,0))="","",INDEX('CAMPAIGN MASTER'!$A$5:$A$704,MATCH(SMALL('CAMPAIGN MASTER'!$AU$5:$AU$704,4),'CAMPAIGN MASTER'!$AU$5:$AU$704,0))),"") | F116: =IFERROR(IF(INDEX('CAMPAIGN MASTER'!$I$5:$I$704,MATCH(SMALL('CAMPAIGN MASTER'!$AU$5:$AU$704,4),'CAMPAIGN MASTER'!$AU$5:$AU$704,0))="","",INDEX('CAMPAIGN MASTER'!$I$5:$I$704,MATCH(SMALL('CAMPAIGN MASTER'!$AU$5:$AU$704,4),'CAMPAIGN MASTER'!$AU$5:$AU$704,0))),"") | G116: =IFERROR(IF(INDEX('CAMPAIGN MASTER'!$AA$5:$AA$704,MATCH(SMALL('CAMPAIGN MASTER'!$AU$5:$AU$704,4),'CAMPAIGN MASTER'!$AU$5:$AU$704,0))="","",INDEX('CAMPAIGN MASTER'!$AA$5:$AA$704,MATCH(SMALL('CAMPAIGN MASTER'!$AU$5:$AU$704,4),'CAMPAIGN MASTER'!$AU$5:$AU$704,0))),"") | H116: =IFERROR(IF(INDEX('CAMPAIGN MASTER'!$AT$5:$AT$704,MATCH(SMALL('CAMPAIGN MASTER'!$AU$5:$AU$704,4),'CAMPAIGN MASTER'!$AU$5:$AU$704,0))="","",INDEX('CAMPAIGN MASTER'!$AT$5:$AT$704,MATCH(SMALL('CAMPAIGN MASTER'!$AU$5:$AU$704,4),'CAMPAIGN MASTER'!$AU$5:$AU$704,0))),"") | K116: =IFERROR(IF(INDEX('CAMPAIGN MASTER'!$B$5:$B$704,MATCH(SMALL('CAMPAIGN MASTER'!$AX$5:$AX$704,4),'CAMPAIGN MASTER'!$AX$5:$AX$704,0))="","",INDEX('CAMPAIGN MASTER'!$B$5:$B$704,MATCH(SMALL('CAMPAIGN MASTER'!$AX$5:$AX$704,4),'CAMPAIGN MASTER'!$AX$5:$AX$704,0))),"") | N116: =IFERROR(IF(INDEX('CAMPAIGN MASTER'!$A$5:$A$704,MATCH(SMALL('CAMPAIGN MASTER'!$AX$5:$AX$704,4),'CAMPAIGN MASTER'!$AX$5:$AX$704,0))="","",INDEX('CAMPAIGN MASTER'!$A$5:$A$704,MATCH(SMALL('CAMPAIGN MASTER'!$AX$5:$AX$704,4),'CAMPAIGN MASTER'!$AX$5:$AX$704,0))),"") | O116: =IFERROR(IF(INDEX('CAMPAIGN MASTER'!$I$5:$I$704,MATCH(SMALL('CAMPAIGN MASTER'!$AX$5:$AX$704,4),'CAMPAIGN MASTER'!$AX$5:$AX$704,0))="","",INDEX('CAMPAIGN MASTER'!$I$5:$I$704,MATCH(SMALL('CAMPAIGN MASTER'!$AX$5:$AX$704,4),'CAMPAIGN MASTER'!$AX$5:$AX$704,0))),"") | P116: =IFERROR(IF(INDEX('CAMPAIGN MASTER'!$R$5:$R$704,MATCH(SMALL('CAMPAIGN MASTER'!$AX$5:$AX$704,4),'CAMPAIGN MASTER'!$AX$5:$AX$704,0))="","",INDEX('CAMPAIGN MASTER'!$R$5:$R$704,MATCH(SMALL('CAMPAIGN MASTER'!$AX$5:$AX$704,4),'CAMPAIGN MASTER'!$AX$5:$AX$704,0))),"") | Q116: =IFERROR(IF(INDEX('CAMPAIGN MASTER'!$Q$5:$Q$704,MATCH(SMALL('CAMPAIGN MASTER'!$AX$5:$AX$704,4),'CAMPAIGN MASTER'!$AX$5:$AX$704,0))="","",INDEX('CAMPAIGN MASTER'!$Q$5:$Q$704,MATCH(SMALL('CAMPAIGN MASTER'!$AX$5:$AX$704,4),'CAMPAIGN MASTER'!$AX$5:$AX$704,0))),"") | R116: =IFERROR(IF(INDEX('CAMPAIGN MASTER'!$AA$5:$AA$704,MATCH(SMALL('CAMPAIGN MASTER'!$AX$5:$AX$704,4),'CAMPAIGN MASTER'!$AX$5:$AX$704,0))="","",INDEX('CAMPAIGN MASTER'!$AA$5:$AA$704,MATCH(SMALL('CAMPAIGN MASTER'!$AX$5:$AX$704,4),'CAMPAIGN MASTER'!$AX$5:$AX$704,0))),"")
B117: =IFERROR(IF(INDEX('CAMPAIGN MASTER'!$B$5:$B$704,MATCH(SMALL('CAMPAIGN MASTER'!$AU$5:$AU$704,5),'CAMPAIGN MASTER'!$AU$5:$AU$704,0))="","",INDEX('CAMPAIGN MASTER'!$B$5:$B$704,MATCH(SMALL('CAMPAIGN MASTER'!$AU$5:$AU$704,5),'CAMPAIGN MASTER'!$AU$5:$AU$704,0))),"") | E117: =IFERROR(IF(INDEX('CAMPAIGN MASTER'!$A$5:$A$704,MATCH(SMALL('CAMPAIGN MASTER'!$AU$5:$AU$704,5),'CAMPAIGN MASTER'!$AU$5:$AU$704,0))="","",INDEX('CAMPAIGN MASTER'!$A$5:$A$704,MATCH(SMALL('CAMPAIGN MASTER'!$AU$5:$AU$704,5),'CAMPAIGN MASTER'!$AU$5:$AU$704,0))),"") | F117: =IFERROR(IF(INDEX('CAMPAIGN MASTER'!$I$5:$I$704,MATCH(SMALL('CAMPAIGN MASTER'!$AU$5:$AU$704,5),'CAMPAIGN MASTER'!$AU$5:$AU$704,0))="","",INDEX('CAMPAIGN MASTER'!$I$5:$I$704,MATCH(SMALL('CAMPAIGN MASTER'!$AU$5:$AU$704,5),'CAMPAIGN MASTER'!$AU$5:$AU$704,0))),"") | G117: =IFERROR(IF(INDEX('CAMPAIGN MASTER'!$AA$5:$AA$704,MATCH(SMALL('CAMPAIGN MASTER'!$AU$5:$AU$704,5),'CAMPAIGN MASTER'!$AU$5:$AU$704,0))="","",INDEX('CAMPAIGN MASTER'!$AA$5:$AA$704,MATCH(SMALL('CAMPAIGN MASTER'!$AU$5:$AU$704,5),'CAMPAIGN MASTER'!$AU$5:$AU$704,0))),"") | H117: =IFERROR(IF(INDEX('CAMPAIGN MASTER'!$AT$5:$AT$704,MATCH(SMALL('CAMPAIGN MASTER'!$AU$5:$AU$704,5),'CAMPAIGN MASTER'!$AU$5:$AU$704,0))="","",INDEX('CAMPAIGN MASTER'!$AT$5:$AT$704,MATCH(SMALL('CAMPAIGN MASTER'!$AU$5:$AU$704,5),'CAMPAIGN MASTER'!$AU$5:$AU$704,0))),"") | K117: =IFERROR(IF(INDEX('CAMPAIGN MASTER'!$B$5:$B$704,MATCH(SMALL('CAMPAIGN MASTER'!$AX$5:$AX$704,5),'CAMPAIGN MASTER'!$AX$5:$AX$704,0))="","",INDEX('CAMPAIGN MASTER'!$B$5:$B$704,MATCH(SMALL('CAMPAIGN MASTER'!$AX$5:$AX$704,5),'CAMPAIGN MASTER'!$AX$5:$AX$704,0))),"") | N117: =IFERROR(IF(INDEX('CAMPAIGN MASTER'!$A$5:$A$704,MATCH(SMALL('CAMPAIGN MASTER'!$AX$5:$AX$704,5),'CAMPAIGN MASTER'!$AX$5:$AX$704,0))="","",INDEX('CAMPAIGN MASTER'!$A$5:$A$704,MATCH(SMALL('CAMPAIGN MASTER'!$AX$5:$AX$704,5),'CAMPAIGN MASTER'!$AX$5:$AX$704,0))),"") | O117: =IFERROR(IF(INDEX('CAMPAIGN MASTER'!$I$5:$I$704,MATCH(SMALL('CAMPAIGN MASTER'!$AX$5:$AX$704,5),'CAMPAIGN MASTER'!$AX$5:$AX$704,0))="","",INDEX('CAMPAIGN MASTER'!$I$5:$I$704,MATCH(SMALL('CAMPAIGN MASTER'!$AX$5:$AX$704,5),'CAMPAIGN MASTER'!$AX$5:$AX$704,0))),"") | P117: =IFERROR(IF(INDEX('CAMPAIGN MASTER'!$R$5:$R$704,MATCH(SMALL('CAMPAIGN MASTER'!$AX$5:$AX$704,5),'CAMPAIGN MASTER'!$AX$5:$AX$704,0))="","",INDEX('CAMPAIGN MASTER'!$R$5:$R$704,MATCH(SMALL('CAMPAIGN MASTER'!$AX$5:$AX$704,5),'CAMPAIGN MASTER'!$AX$5:$AX$704,0))),"") | Q117: =IFERROR(IF(INDEX('CAMPAIGN MASTER'!$Q$5:$Q$704,MATCH(SMALL('CAMPAIGN MASTER'!$AX$5:$AX$704,5),'CAMPAIGN MASTER'!$AX$5:$AX$704,0))="","",INDEX('CAMPAIGN MASTER'!$Q$5:$Q$704,MATCH(SMALL('CAMPAIGN MASTER'!$AX$5:$AX$704,5),'CAMPAIGN MASTER'!$AX$5:$AX$704,0))),"") | R117: =IFERROR(IF(INDEX('CAMPAIGN MASTER'!$AA$5:$AA$704,MATCH(SMALL('CAMPAIGN MASTER'!$AX$5:$AX$704,5),'CAMPAIGN MASTER'!$AX$5:$AX$704,0))="","",INDEX('CAMPAIGN MASTER'!$AA$5:$AA$704,MATCH(SMALL('CAMPAIGN MASTER'!$AX$5:$AX$704,5),'CAMPAIGN MASTER'!$AX$5:$AX$704,0))),"")
...

Sheet DAILY TASK TRACKER
A1: DAILY ACTIVITY / TASK TRACKER
A2: BLUE cells = team enters data | GREY cells = automatic formulas (do not edit) | Add one row per task per day/update. Status, Due Date and Last Updated drive all alerts.
A3: Example: 05-Oct-26 | Surbhi Pandey | SAP | SAP Viksit Bharat | Campaign Execution | Content Syndication | Deploy mailer batch 2 | ... | High | Rajesh | ... | 09-Oct-26 | In Progress | 50% ...
A4: Date | B4: Team Member | C4: Client | D4: Campaign | E4: Workstream | F4: Channel | G4: Activity / Task | H4: Task Description | I4: Priority | J4: Assigned By | K4: Start Date | L4: Due Date | M4: Status | N4: % Complete | O4: Output / Result | P4: KPI / Metric | Q4: Actual Result | R4: Target | S4: Variance | T4: Blocker | U4: Dependency | V4: Next Action | W4: Next Action Date | X4: Remarks | Y4: Last Updated | Z4: Needs Manager Decision? | AA4: Escalate to Rajesh? | AB4: Target Note (as provided) | AC4: Days Open | AD4: Days Overdue | AE4: Completion % | AF4: Target Achievement % | AG4: Alert | AH4: Month Key | AI4: In Dashboard Filter | AJ4: In List Filter | AK4: Open | AL4: Overdue | AM4: Blocked | AN4: Due Today | AO4: Due Tomorrow | AP4: Due Soon | AQ4: High Priority Pending | AR4: Stale | AS4: Missed Target | AT4: Planned Today | AU4: Planned Tomorrow | AV4: Completed Yesterday | AW4: Decision Needed | AX4: Escalate | AY4: High Priority Blocker | AZ4: TCL Open | BA4: Priority Score | BB4: Sort key overdue | BC4: Sort key blocked | BD4: Sort key soon | BE4: Sort key plantoday | BF4: Sort key plantom | BG4: Sort key yday | BH4: Sort key dec | BI4: Sort key esc | BJ4: Sort key missed | BK4: Sort key highblock | BL4: Sort key tcl
B5: Surbhi Pandey | C5: SAP | D5: SAP Partner Campaign - Citek | E5: Campaign Execution | F5: Content Syndication | G5: Content Syndication - Email | S5: =IF(AND(ISNUMBER($Q5),ISNUMBER($R5)),$Q5-$R5,"") | X5: Baseline: status not provided. | AC5: =IF(OR($G5="",NOT(ISNUMBER($K5)),$AK5=0),"",MAX(0,ReportDate-$K5)) | AD5: =IF($G5="","",IF($AL5=1,ReportDate-$L5,0)) -> 0 | AE5: =IF($G5="","",IF($M5="Completed",1,IF(ISNUMBER($N5),$N5,0))) -> 0 | AF5: =IF(AND(ISNUMBER($Q5),ISNUMBER($R5)),IF($R5<>0,$Q5/$R5,""),"") | AG5: =IF($G5="","",IF($AL5=1,"OVERDUE",IF($AM5=1,"BLOCKED",IF($AN5=1,"DUE TODAY",IF($AO5=1,"DUE TOMORROW",IF($AQ5=1,"HIGH PRIORITY",IF($AR5=1,"NO RECENT UPDATE",""))))))) -> NO RECENT UPDATE | AH5: =IF($G5="","",IF(ISNUMBER($A5),IF(ISNUMBER($A5),YEAR($A5)&"-"&TEXT(MONTH($A5),"00"),""),IF(ISNUMBER($L5),IF(ISNUMBER($L5),YEAR($L5)&"-"&TEXT(MONTH($L5),"00"),""),""))) | AI5: =IF($G5="",0,IF(AND(OR(fClient="All",$C5=fClient),OR(fCampaign="All",$D5=fCampaign),OR(fTeam="All",$B5=fTeam),OR(fChannel="All",$F5=fChannel),OR(fMonth="All",$AH5=fMonth),OR(fTStatus="All",$M5=fTStatus)),1,0)) -> 1 | AJ5: =IF($G5="",0,IF(AND(OR(fClient="All",$C5=fClient),OR(fCampaign="All",$D5=fCampaign),OR(fTeam="All",$B5=fTeam),OR(fChannel="All",$F5=fChannel)),1,0)) -> 1 | AK5: =IF($G5="",0,IF(OR($M5="Completed",$M5="Cancelled"),0,1)) -> 1 | AL5: =IF(AND($AK5=1,ISNUMBER($L5)),IF($L5<ReportDate,1,0),0) -> 0 | AM5: =IF(AND($G5<>"",$M5="Blocked"),1,0) -> 0 | AN5: =IF(AND($AK5=1,ISNUMBER($L5)),IF($L5=ReportDate,1,0),0) -> 0 | AO5: =IF(AND($AK5=1,ISNUMBER($L5)),IF($L5=ReportDate+1,1,0),0) -> 0 | AP5: =IF(AND($AK5=1,ISNUMBER($L5)),IF(AND($L5>=ReportDate,$L5<=ReportDate+DueSoonDays),1,0),0) -> 0 | AQ5: =IF(AND($AK5=1,OR($I5="Critical",$I5="High")),1,0) -> 0 | AR5: =IF($AK5=1,IF(ISNUMBER($Y5),IF(ReportDate-$Y5>StaleDays,1,0),1),0) -> 1 | AS5: =IF(AND($G5<>"",ISNUMBER($Q5),ISNUMBER($R5)),IF(AND($Q5<$R5,OR($M5="Completed",AND(ISNUMBER($L5),$L5<ReportDate))),1,0),0) -> 0 | AT5: =IF($AK5=1,IF(OR($L5=ReportDate,$W5=ReportDate,$K5=ReportDate,$A5=ReportDate),1,0),0) -> 0 | AU5: =IF($AK5=1,IF(OR($L5=ReportDate+1,$W5=ReportDate+1,$K5=ReportDate+1,$A5=ReportDate+1),1,0),0) -> 0 | AV5: =IF(AND($G5<>"",$M5="Completed"),IF(OR($Y5=ReportDate-1,$A5=ReportDate-1),1,0),0) -> 0 | AW5: =IF(AND($AK5=1,$Z5="Yes"),1,0) -> 0 | AX5: =IF(AND($AK5=1,$AA5="Yes"),1,0) -> 0 | AY5: =IF(AND($AM5=1,OR($I5="Critical",$I5="High")),1,0) -> 0 | AZ5: =IF(AND($AK5=1,OR($C5=TCL_Client,$C5=MECCA_Client)),1,0) -> 0 | BA5: =IF($G5="","",IFERROR(MATCH($I5,lst_Priority,0),5)) -> 5 | BB5: =IF(AND($AL5=1,$AJ5=1),$BA5*100000+ROW(),"") | BC5: =IF(AND($AM5=1,$AJ5=1),$BA5*100000+ROW(),"") | BD5: =IF(AND($AP5=1,$AJ5=1),$BA5*100000+ROW(),"") | BE5: =IF(AND($AT5=1,$AJ5=1),$BA5*100000+ROW(),"") | BF5: =IF(AND($AU5=1,$AJ5=1),$BA5*100000+ROW(),"") | BG5: =IF(AND($AV5=1,$AJ5=1),$BA5*100000+ROW(),"") | BH5: =IF(AND($AW5=1,$AJ5=1),$BA5*100000+ROW(),"") | BI5: =IF(AND($AX5=1,$AJ5=1),$BA5*100000+ROW(),"") | BJ5: =IF(AND($AS5=1,$AJ5=1),$BA5*100000+ROW(),"") | BK5: =IF(AND($AY5=1,$AJ5=1),$BA5*100000+ROW(),"") | BL5: =IF(AND($AZ5=1),$BA5*100000+ROW(),"")
B6: Surbhi Pandey | C6: SAP | D6: SAP Partner Campaign - Apptech | E6: Campaign Execution | F6: Content Syndication | G6: Content Syndication - Email | S6: =IF(AND(ISNUMBER($Q6),ISNUMBER($R6)),$Q6-$R6,"") | X6: Baseline: status not provided. | AC6: =IF(OR($G6="",NOT(ISNUMBER($K6)),$AK6=0),"",MAX(0,ReportDate-$K6)) | AD6: =IF($G6="","",IF($AL6=1,ReportDate-$L6,0)) -> 0 | AE6: =IF($G6="","",IF($M6="Completed",1,IF(ISNUMBER($N6),$N6,0))) -> 0 | AF6: =IF(AND(ISNUMBER($Q6),ISNUMBER($R6)),IF($R6<>0,$Q6/$R6,""),"") | AG6: =IF($G6="","",IF($AL6=1,"OVERDUE",IF($AM6=1,"BLOCKED",IF($AN6=1,"DUE TODAY",IF($AO6=1,"DUE TOMORROW",IF($AQ6=1,"HIGH PRIORITY",IF($AR6=1,"NO RECENT UPDATE",""))))))) -> NO RECENT UPDATE | AH6: =IF($G6="","",IF(ISNUMBER($A6),IF(ISNUMBER($A6),YEAR($A6)&"-"&TEXT(MONTH($A6),"00"),""),IF(ISNUMBER($L6),IF(ISNUMBER($L6),YEAR($L6)&"-"&TEXT(MONTH($L6),"00"),""),""))) | AI6: =IF($G6="",0,IF(AND(OR(fClient="All",$C6=fClient),OR(fCampaign="All",$D6=fCampaign),OR(fTeam="All",$B6=fTeam),OR(fChannel="All",$F6=fChannel),OR(fMonth="All",$AH6=fMonth),OR(fTStatus="All",$M6=fTStatus)),1,0)) -> 1 | AJ6: =IF($G6="",0,IF(AND(OR(fClient="All",$C6=fClient),OR(fCampaign="All",$D6=fCampaign),OR(fTeam="All",$B6=fTeam),OR(fChannel="All",$F6=fChannel)),1,0)) -> 1 | AK6: =IF($G6="",0,IF(OR($M6="Completed",$M6="Cancelled"),0,1)) -> 1 | AL6: =IF(AND($AK6=1,ISNUMBER($L6)),IF($L6<ReportDate,1,0),0) -> 0 | AM6: =IF(AND($G6<>"",$M6="Blocked"),1,0) -> 0 | AN6: =IF(AND($AK6=1,ISNUMBER($L6)),IF($L6=ReportDate,1,0),0) -> 0 | AO6: =IF(AND($AK6=1,ISNUMBER($L6)),IF($L6=ReportDate+1,1,0),0) -> 0 | AP6: =IF(AND($AK6=1,ISNUMBER($L6)),IF(AND($L6>=ReportDate,$L6<=ReportDate+DueSoonDays),1,0),0) -> 0 | AQ6: =IF(AND($AK6=1,OR($I6="Critical",$I6="High")),1,0) -> 0 | AR6: =IF($AK6=1,IF(ISNUMBER($Y6),IF(ReportDate-$Y6>StaleDays,1,0),1),0) -> 1 | AS6: =IF(AND($G6<>"",ISNUMBER($Q6),ISNUMBER($R6)),IF(AND($Q6<$R6,OR($M6="Completed",AND(ISNUMBER($L6),$L6<ReportDate))),1,0),0) -> 0 | AT6: =IF($AK6=1,IF(OR($L6=ReportDate,$W6=ReportDate,$K6=ReportDate,$A6=ReportDate),1,0),0) -> 0 | AU6: =IF($AK6=1,IF(OR($L6=ReportDate+1,$W6=ReportDate+1,$K6=ReportDate+1,$A6=ReportDate+1),1,0),0) -> 0 | AV6: =IF(AND($G6<>"",$M6="Completed"),IF(OR($Y6=ReportDate-1,$A6=ReportDate-1),1,0),0) -> 0 | AW6: =IF(AND($AK6=1,$Z6="Yes"),1,0) -> 0 | AX6: =IF(AND($AK6=1,$AA6="Yes"),1,0) -> 0 | AY6: =IF(AND($AM6=1,OR($I6="Critical",$I6="High")),1,0) -> 0 | AZ6: =IF(AND($AK6=1,OR($C6=TCL_Client,$C6=MECCA_Client)),1,0) -> 0 | BA6: =IF($G6="","",IFERROR(MATCH($I6,lst_Priority,0),5)) -> 5 | BB6: =IF(AND($AL6=1,$AJ6=1),$BA6*100000+ROW(),"") | BC6: =IF(AND($AM6=1,$AJ6=1),$BA6*100000+ROW(),"") | BD6: =IF(AND($AP6=1,$AJ6=1),$BA6*100000+ROW(),"") | BE6: =IF(AND($AT6=1,$AJ6=1),$BA6*100000+ROW(),"") | BF6: =IF(AND($AU6=1,$AJ6=1),$BA6*100000+ROW(),"") | BG6: =IF(AND($AV6=1,$AJ6=1),$BA6*100000+ROW(),"") | BH6: =IF(AND($AW6=1,$AJ6=1),$BA6*100000+ROW(),"") | BI6: =IF(AND($AX6=1,$AJ6=1),$BA6*100000+ROW(),"") | BJ6: =IF(AND($AS6=1,$AJ6=1),$BA6*100000+ROW(),"") | BK6: =IF(AND($AY6=1,$AJ6=1),$BA6*100000+ROW(),"") | BL6: =IF(AND($AZ6=1),$BA6*100000+ROW(),"")
B7: Surbhi Pandey | C7: SAP | D7: SAP Partner Campaign - Netizen | E7: Campaign Execution | F7: Content Syndication | G7: Content Syndication - Email | S7: =IF(AND(ISNUMBER($Q7),ISNUMBER($R7)),$Q7-$R7,"") | X7: Baseline: status not provided. | AC7: =IF(OR($G7="",NOT(ISNUMBER($K7)),$AK7=0),"",MAX(0,ReportDate-$K7)) | AD7: =IF($G7="","",IF($AL7=1,ReportDate-$L7,0)) -> 0 | AE7: =IF($G7="","",IF($M7="Completed",1,IF(ISNUMBER($N7),$N7,0))) -> 0 | AF7: =IF(AND(ISNUMBER($Q7),ISNUMBER($R7)),IF($R7<>0,$Q7/$R7,""),"") | AG7: =IF($G7="","",IF($AL7=1,"OVERDUE",IF($AM7=1,"BLOCKED",IF($AN7=1,"DUE TODAY",IF($AO7=1,"DUE TOMORROW",IF($AQ7=1,"HIGH PRIORITY",IF($AR7=1,"NO RECENT UPDATE",""))))))) -> NO RECENT UPDATE | AH7: =IF($G7="","",IF(ISNUMBER($A7),IF(ISNUMBER($A7),YEAR($A7)&"-"&TEXT(MONTH($A7),"00"),""),IF(ISNUMBER($L7),IF(ISNUMBER($L7),YEAR($L7)&"-"&TEXT(MONTH($L7),"00"),""),""))) | AI7: =IF($G7="",0,IF(AND(OR(fClient="All",$C7=fClient),OR(fCampaign="All",$D7=fCampaign),OR(fTeam="All",$B7=fTeam),OR(fChannel="All",$F7=fChannel),OR(fMonth="All",$AH7=fMonth),OR(fTStatus="All",$M7=fTStatus)),1,0)) -> 1 | AJ7: =IF($G7="",0,IF(AND(OR(fClient="All",$C7=fClient),OR(fCampaign="All",$D7=fCampaign),OR(fTeam="All",$B7=fTeam),OR(fChannel="All",$F7=fChannel)),1,0)) -> 1 | AK7: =IF($G7="",0,IF(OR($M7="Completed",$M7="Cancelled"),0,1)) -> 1 | AL7: =IF(AND($AK7=1,ISNUMBER($L7)),IF($L7<ReportDate,1,0),0) -> 0 | AM7: =IF(AND($G7<>"",$M7="Blocked"),1,0) -> 0 | AN7: =IF(AND($AK7=1,ISNUMBER($L7)),IF($L7=ReportDate,1,0),0) -> 0 | AO7: =IF(AND($AK7=1,ISNUMBER($L7)),IF($L7=ReportDate+1,1,0),0) -> 0 | AP7: =IF(AND($AK7=1,ISNUMBER($L7)),IF(AND($L7>=ReportDate,$L7<=ReportDate+DueSoonDays),1,0),0) -> 0 | AQ7: =IF(AND($AK7=1,OR($I7="Critical",$I7="High")),1,0) -> 0 | AR7: =IF($AK7=1,IF(ISNUMBER($Y7),IF(ReportDate-$Y7>StaleDays,1,0),1),0) -> 1 | AS7: =IF(AND($G7<>"",ISNUMBER($Q7),ISNUMBER($R7)),IF(AND($Q7<$R7,OR($M7="Completed",AND(ISNUMBER($L7),$L7<ReportDate))),1,0),0) -> 0 | AT7: =IF($AK7=1,IF(OR($L7=ReportDate,$W7=ReportDate,$K7=ReportDate,$A7=ReportDate),1,0),0) -> 0 | AU7: =IF($AK7=1,IF(OR($L7=ReportDate+1,$W7=ReportDate+1,$K7=ReportDate+1,$A7=ReportDate+1),1,0),0) -> 0 | AV7: =IF(AND($G7<>"",$M7="Completed"),IF(OR($Y7=ReportDate-1,$A7=ReportDate-1),1,0),0) -> 0 | AW7: =IF(AND($AK7=1,$Z7="Yes"),1,0) -> 0 | AX7: =IF(AND($AK7=1,$AA7="Yes"),1,0) -> 0 | AY7: =IF(AND($AM7=1,OR($I7="Critical",$I7="High")),1,0) -> 0 | AZ7: =IF(AND($AK7=1,OR($C7=TCL_Client,$C7=MECCA_Client)),1,0) -> 0 | BA7: =IF($G7="","",IFERROR(MATCH($I7,lst_Priority,0),5)) -> 5 | BB7: =IF(AND($AL7=1,$AJ7=1),$BA7*100000+ROW(),"") | BC7: =IF(AND($AM7=1,$AJ7=1),$BA7*100000+ROW(),"") | BD7: =IF(AND($AP7=1,$AJ7=1),$BA7*100000+ROW(),"") | BE7: =IF(AND($AT7=1,$AJ7=1),$BA7*100000+ROW(),"") | BF7: =IF(AND($AU7=1,$AJ7=1),$BA7*100000+ROW(),"") | BG7: =IF(AND($AV7=1,$AJ7=1),$BA7*100000+ROW(),"") | BH7: =IF(AND($AW7=1,$AJ7=1),$BA7*100000+ROW(),"") | BI7: =IF(AND($AX7=1,$AJ7=1),$BA7*100000+ROW(),"") | BJ7: =IF(AND($AS7=1,$AJ7=1),$BA7*100000+ROW(),"") | BK7: =IF(AND($AY7=1,$AJ7=1),$BA7*100000+ROW(),"") | BL7: =IF(AND($AZ7=1),$BA7*100000+ROW(),"")
B8: Surbhi Pandey | C8: SAP | D8: SAP Partner Campaign - Ikyam | E8: Campaign Execution | F8: Content Syndication | G8: Content Syndication - Email | S8: =IF(AND(ISNUMBER($Q8),ISNUMBER($R8)),$Q8-$R8,"") | X8: Baseline: status not provided. | AC8: =IF(OR($G8="",NOT(ISNUMBER($K8)),$AK8=0),"",MAX(0,ReportDate-$K8)) | AD8: =IF($G8="","",IF($AL8=1,ReportDate-$L8,0)) -> 0 | AE8: =IF($G8="","",IF($M8="Completed",1,IF(ISNUMBER($N8),$N8,0))) -> 0 | AF8: =IF(AND(ISNUMBER($Q8),ISNUMBER($R8)),IF($R8<>0,$Q8/$R8,""),"") | AG8: =IF($G8="","",IF($AL8=1,"OVERDUE",IF($AM8=1,"BLOCKED",IF($AN8=1,"DUE TODAY",IF($AO8=1,"DUE TOMORROW",IF($AQ8=1,"HIGH PRIORITY",IF($AR8=1,"NO RECENT UPDATE",""))))))) -> NO RECENT UPDATE | AH8: =IF($G8="","",IF(ISNUMBER($A8),IF(ISNUMBER($A8),YEAR($A8)&"-"&TEXT(MONTH($A8),"00"),""),IF(ISNUMBER($L8),IF(ISNUMBER($L8),YEAR($L8)&"-"&TEXT(MONTH($L8),"00"),""),""))) | AI8: =IF($G8="",0,IF(AND(OR(fClient="All",$C8=fClient),OR(fCampaign="All",$D8=fCampaign),OR(fTeam="All",$B8=fTeam),OR(fChannel="All",$F8=fChannel),OR(fMonth="All",$AH8=fMonth),OR(fTStatus="All",$M8=fTStatus)),1,0)) -> 1 | AJ8: =IF($G8="",0,IF(AND(OR(fClient="All",$C8=fClient),OR(fCampaign="All",$D8=fCampaign),OR(fTeam="All",$B8=fTeam),OR(fChannel="All",$F8=fChannel)),1,0)) -> 1 | AK8: =IF($G8="",0,IF(OR($M8="Completed",$M8="Cancelled"),0,1)) -> 1 | AL8: =IF(AND($AK8=1,ISNUMBER($L8)),IF($L8<ReportDate,1,0),0) -> 0 | AM8: =IF(AND($G8<>"",$M8="Blocked"),1,0) -> 0 | AN8: =IF(AND($AK8=1,ISNUMBER($L8)),IF($L8=ReportDate,1,0),0) -> 0 | AO8: =IF(AND($AK8=1,ISNUMBER($L8)),IF($L8=ReportDate+1,1,0),0) -> 0 | AP8: =IF(AND($AK8=1,ISNUMBER($L8)),IF(AND($L8>=ReportDate,$L8<=ReportDate+DueSoonDays),1,0),0) -> 0 | AQ8: =IF(AND($AK8=1,OR($I8="Critical",$I8="High")),1,0) -> 0 | AR8: =IF($AK8=1,IF(ISNUMBER($Y8),IF(ReportDate-$Y8>StaleDays,1,0),1),0) -> 1 | AS8: =IF(AND($G8<>"",ISNUMBER($Q8),ISNUMBER($R8)),IF(AND($Q8<$R8,OR($M8="Completed",AND(ISNUMBER($L8),$L8<ReportDate))),1,0),0) -> 0 | AT8: =IF($AK8=1,IF(OR($L8=ReportDate,$W8=ReportDate,$K8=ReportDate,$A8=ReportDate),1,0),0) -> 0 | AU8: =IF($AK8=1,IF(OR($L8=ReportDate+1,$W8=ReportDate+1,$K8=ReportDate+1,$A8=ReportDate+1),1,0),0) -> 0 | AV8: =IF(AND($G8<>"",$M8="Completed"),IF(OR($Y8=ReportDate-1,$A8=ReportDate-1),1,0),0) -> 0 | AW8: =IF(AND($AK8=1,$Z8="Yes"),1,0) -> 0 | AX8: =IF(AND($AK8=1,$AA8="Yes"),1,0) -> 0 | AY8: =IF(AND($AM8=1,OR($I8="Critical",$I8="High")),1,0) -> 0 | AZ8: =IF(AND($AK8=1,OR($C8=TCL_Client,$C8=MECCA_Client)),1,0) -> 0 | BA8: =IF($G8="","",IFERROR(MATCH($I8,lst_Priority,0),5)) -> 5 | BB8: =IF(AND($AL8=1,$AJ8=1),$BA8*100000+ROW(),"") | BC8: =IF(AND($AM8=1,$AJ8=1),$BA8*100000+ROW(),"") | BD8: =IF(AND($AP8=1,$AJ8=1),$BA8*100000+ROW(),"") | BE8: =IF(AND($AT8=1,$AJ8=1),$BA8*100000+ROW(),"") | BF8: =IF(AND($AU8=1,$AJ8=1),$BA8*100000+ROW(),"") | BG8: =IF(AND($AV8=1,$AJ8=1),$BA8*100000+ROW(),"") | BH8: =IF(AND($AW8=1,$AJ8=1),$BA8*100000+ROW(),"") | BI8: =IF(AND($AX8=1,$AJ8=1),$BA8*100000+ROW(),"") | BJ8: =IF(AND($AS8=1,$AJ8=1),$BA8*100000+ROW(),"") | BK8: =IF(AND($AY8=1,$AJ8=1),$BA8*100000+ROW(),"") | BL8: =IF(AND($AZ8=1),$BA8*100000+ROW(),"")
B9: Surbhi Pandey | C9: SAP | D9: SAP Partner Campaign - Castaliaz | E9: Campaign Execution | F9: Content Syndication | G9: Content Syndication - Email | S9: =IF(AND(ISNUMBER($Q9),ISNUMBER($R9)),$Q9-$R9,"") | X9: Baseline: status not provided. | AC9: =IF(OR($G9="",NOT(ISNUMBER($K9)),$AK9=0),"",MAX(0,ReportDate-$K9)) | AD9: =IF($G9="","",IF($AL9=1,ReportDate-$L9,0)) -> 0 | AE9: =IF($G9="","",IF($M9="Completed",1,IF(ISNUMBER($N9),$N9,0))) -> 0 | AF9: =IF(AND(ISNUMBER($Q9),ISNUMBER($R9)),IF($R9<>0,$Q9/$R9,""),"") | AG9: =IF($G9="","",IF($AL9=1,"OVERDUE",IF($AM9=1,"BLOCKED",IF($AN9=1,"DUE TODAY",IF($AO9=1,"DUE TOMORROW",IF($AQ9=1,"HIGH PRIORITY",IF($AR9=1,"NO RECENT UPDATE",""))))))) -> NO RECENT UPDATE | AH9: =IF($G9="","",IF(ISNUMBER($A9),IF(ISNUMBER($A9),YEAR($A9)&"-"&TEXT(MONTH($A9),"00"),""),IF(ISNUMBER($L9),IF(ISNUMBER($L9),YEAR($L9)&"-"&TEXT(MONTH($L9),"00"),""),""))) | AI9: =IF($G9="",0,IF(AND(OR(fClient="All",$C9=fClient),OR(fCampaign="All",$D9=fCampaign),OR(fTeam="All",$B9=fTeam),OR(fChannel="All",$F9=fChannel),OR(fMonth="All",$AH9=fMonth),OR(fTStatus="All",$M9=fTStatus)),1,0)) -> 1 | AJ9: =IF($G9="",0,IF(AND(OR(fClient="All",$C9=fClient),OR(fCampaign="All",$D9=fCampaign),OR(fTeam="All",$B9=fTeam),OR(fChannel="All",$F9=fChannel)),1,0)) -> 1 | AK9: =IF($G9="",0,IF(OR($M9="Completed",$M9="Cancelled"),0,1)) -> 1 | AL9: =IF(AND($AK9=1,ISNUMBER($L9)),IF($L9<ReportDate,1,0),0) -> 0 | AM9: =IF(AND($G9<>"",$M9="Blocked"),1,0) -> 0 | AN9: =IF(AND($AK9=1,ISNUMBER($L9)),IF($L9=ReportDate,1,0),0) -> 0 | AO9: =IF(AND($AK9=1,ISNUMBER($L9)),IF($L9=ReportDate+1,1,0),0) -> 0 | AP9: =IF(AND($AK9=1,ISNUMBER($L9)),IF(AND($L9>=ReportDate,$L9<=ReportDate+DueSoonDays),1,0),0) -> 0 | AQ9: =IF(AND($AK9=1,OR($I9="Critical",$I9="High")),1,0) -> 0 | AR9: =IF($AK9=1,IF(ISNUMBER($Y9),IF(ReportDate-$Y9>StaleDays,1,0),1),0) -> 1 | AS9: =IF(AND($G9<>"",ISNUMBER($Q9),ISNUMBER($R9)),IF(AND($Q9<$R9,OR($M9="Completed",AND(ISNUMBER($L9),$L9<ReportDate))),1,0),0) -> 0 | AT9: =IF($AK9=1,IF(OR($L9=ReportDate,$W9=ReportDate,$K9=ReportDate,$A9=ReportDate),1,0),0) -> 0 | AU9: =IF($AK9=1,IF(OR($L9=ReportDate+1,$W9=ReportDate+1,$K9=ReportDate+1,$A9=ReportDate+1),1,0),0) -> 0 | AV9: =IF(AND($G9<>"",$M9="Completed"),IF(OR($Y9=ReportDate-1,$A9=ReportDate-1),1,0),0) -> 0 | AW9: =IF(AND($AK9=1,$Z9="Yes"),1,0) -> 0 | AX9: =IF(AND($AK9=1,$AA9="Yes"),1,0) -> 0 | AY9: =IF(AND($AM9=1,OR($I9="Critical",$I9="High")),1,0) -> 0 | AZ9: =IF(AND($AK9=1,OR($C9=TCL_Client,$C9=MECCA_Client)),1,0) -> 0 | BA9: =IF($G9="","",IFERROR(MATCH($I9,lst_Priority,0),5)) -> 5 | BB9: =IF(AND($AL9=1,$AJ9=1),$BA9*100000+ROW(),"") | BC9: =IF(AND($AM9=1,$AJ9=1),$BA9*100000+ROW(),"") | BD9: =IF(AND($AP9=1,$AJ9=1),$BA9*100000+ROW(),"") | BE9: =IF(AND($AT9=1,$AJ9=1),$BA9*100000+ROW(),"") | BF9: =IF(AND($AU9=1,$AJ9=1),$BA9*100000+ROW(),"") | BG9: =IF(AND($AV9=1,$AJ9=1),$BA9*100000+ROW(),"") | BH9: =IF(AND($AW9=1,$AJ9=1),$BA9*100000+ROW(),"") | BI9: =IF(AND($AX9=1,$AJ9=1),$BA9*100000+ROW(),"") | BJ9: =IF(AND($AS9=1,$AJ9=1),$BA9*100000+ROW(),"") | BK9: =IF(AND($AY9=1,$AJ9=1),$BA9*100000+ROW(),"") | BL9: =IF(AND($AZ9=1),$BA9*100000+ROW(),"")
B10: Surbhi Pandey | C10: SAP | D10: SAP Partner Campaign - Truspeq | E10: Campaign Execution | F10: Content Syndication | G10: Content Syndication - Email | S10: =IF(AND(ISNUMBER($Q10),ISNUMBER($R10)),$Q10-$R10,"") | X10: Baseline: status not provided. | AC10: =IF(OR($G10="",NOT(ISNUMBER($K10)),$AK10=0),"",MAX(0,ReportDate-$K10)) | AD10: =IF($G10="","",IF($AL10=1,ReportDate-$L10,0)) -> 0 | AE10: =IF($G10="","",IF($M10="Completed",1,IF(ISNUMBER($N10),$N10,0))) -> 0 | AF10: =IF(AND(ISNUMBER($Q10),ISNUMBER($R10)),IF($R10<>0,$Q10/$R10,""),"") | AG10: =IF($G10="","",IF($AL10=1,"OVERDUE",IF($AM10=1,"BLOCKED",IF($AN10=1,"DUE TODAY",IF($AO10=1,"DUE TOMORROW",IF($AQ10=1,"HIGH PRIORITY",IF($AR10=1,"NO RECENT UPDATE",""))))))) -> NO RECENT UPDATE | AH10: =IF($G10="","",IF(ISNUMBER($A10),IF(ISNUMBER($A10),YEAR($A10)&"-"&TEXT(MONTH($A10),"00"),""),IF(ISNUMBER($L10),IF(ISNUMBER($L10),YEAR($L10)&"-"&TEXT(MONTH($L10),"00"),""),""))) | AI10: =IF($G10="",0,IF(AND(OR(fClient="All",$C10=fClient),OR(fCampaign="All",$D10=fCampaign),OR(fTeam="All",$B10=fTeam),OR(fChannel="All",$F10=fChannel),OR(fMonth="All",$AH10=fMonth),OR(fTStatus="All",$M10=fTStatus)),1,0)) -> 1 | AJ10: =IF($G10="",0,IF(AND(OR(fClient="All",$C10=fClient),OR(fCampaign="All",$D10=fCampaign),OR(fTeam="All",$B10=fTeam),OR(fChannel="All",$F10=fChannel)),1,0)) -> 1 | AK10: =IF($G10="",0,IF(OR($M10="Completed",$M10="Cancelled"),0,1)) -> 1 | AL10: =IF(AND($AK10=1,ISNUMBER($L10)),IF($L10<ReportDate,1,0),0) -> 0 | AM10: =IF(AND($G10<>"",$M10="Blocked"),1,0) -> 0 | AN10: =IF(AND($AK10=1,ISNUMBER($L10)),IF($L10=ReportDate,1,0),0) -> 0 | AO10: =IF(AND($AK10=1,ISNUMBER($L10)),IF($L10=ReportDate+1,1,0),0) -> 0 | AP10: =IF(AND($AK10=1,ISNUMBER($L10)),IF(AND($L10>=ReportDate,$L10<=ReportDate+DueSoonDays),1,0),0) -> 0 | AQ10: =IF(AND($AK10=1,OR($I10="Critical",$I10="High")),1,0) -> 0 | AR10: =IF($AK10=1,IF(ISNUMBER($Y10),IF(ReportDate-$Y10>StaleDays,1,0),1),0) -> 1 | AS10: =IF(AND($G10<>"",ISNUMBER($Q10),ISNUMBER($R10)),IF(AND($Q10<$R10,OR($M10="Completed",AND(ISNUMBER($L10),$L10<ReportDate))),1,0),0) -> 0 | AT10: =IF($AK10=1,IF(OR($L10=ReportDate,$W10=ReportDate,$K10=ReportDate,$A10=ReportDate),1,0),0) -> 0 | AU10: =IF($AK10=1,IF(OR($L10=ReportDate+1,$W10=ReportDate+1,$K10=ReportDate+1,$A10=ReportDate+1),1,0),0) -> 0 | AV10: =IF(AND($G10<>"",$M10="Completed"),IF(OR($Y10=ReportDate-1,$A10=ReportDate-1),1,0),0) -> 0 | AW10: =IF(AND($AK10=1,$Z10="Yes"),1,0) -> 0 | AX10: =IF(AND($AK10=1,$AA10="Yes"),1,0) -> 0 | AY10: =IF(AND($AM10=1,OR($I10="Critical",$I10="High")),1,0) -> 0 | AZ10: =IF(AND($AK10=1,OR($C10=TCL_Client,$C10=MECCA_Client)),1,0) -> 0 | BA10: =IF($G10="","",IFERROR(MATCH($I10,lst_Priority,0),5)) -> 5 | BB10: =IF(AND($AL10=1,$AJ10=1),$BA10*100000+ROW(),"") | BC10: =IF(AND($AM10=1,$AJ10=1),$BA10*100000+ROW(),"") | BD10: =IF(AND($AP10=1,$AJ10=1),$BA10*100000+ROW(),"") | BE10: =IF(AND($AT10=1,$AJ10=1),$BA10*100000+ROW(),"") | BF10: =IF(AND($AU10=1,$AJ10=1),$BA10*100000+ROW(),"") | BG10: =IF(AND($AV10=1,$AJ10=1),$BA10*100000+ROW(),"") | BH10: =IF(AND($AW10=1,$AJ10=1),$BA10*100000+ROW(),"") | BI10: =IF(AND($AX10=1,$AJ10=1),$BA10*100000+ROW(),"") | BJ10: =IF(AND($AS10=1,$AJ10=1),$BA10*100000+ROW(),"") | BK10: =IF(AND($AY10=1,$AJ10=1),$BA10*100000+ROW(),"") | BL10: =IF(AND($AZ10=1),$BA10*100000+ROW(),"")
B11: Surbhi Pandey | C11: SAP | D11: SAP Partner Campaign - NTT Data | E11: Campaign Execution | F11: Content Syndication | G11: Content Syndication - Email | S11: =IF(AND(ISNUMBER($Q11),ISNUMBER($R11)),$Q11-$R11,"") | X11: Baseline: status not provided. | AC11: =IF(OR($G11="",NOT(ISNUMBER($K11)),$AK11=0),"",MAX(0,ReportDate-$K11)) | AD11: =IF($G11="","",IF($AL11=1,ReportDate-$L11,0)) -> 0 | AE11: =IF($G11="","",IF($M11="Completed",1,IF(ISNUMBER($N11),$N11,0))) -> 0 | AF11: =IF(AND(ISNUMBER($Q11),ISNUMBER($R11)),IF($R11<>0,$Q11/$R11,""),"") | AG11: =IF($G11="","",IF($AL11=1,"OVERDUE",IF($AM11=1,"BLOCKED",IF($AN11=1,"DUE TODAY",IF($AO11=1,"DUE TOMORROW",IF($AQ11=1,"HIGH PRIORITY",IF($AR11=1,"NO RECENT UPDATE",""))))))) -> NO RECENT UPDATE | AH11: =IF($G11="","",IF(ISNUMBER($A11),IF(ISNUMBER($A11),YEAR($A11)&"-"&TEXT(MONTH($A11),"00"),""),IF(ISNUMBER($L11),IF(ISNUMBER($L11),YEAR($L11)&"-"&TEXT(MONTH($L11),"00"),""),""))) | AI11: =IF($G11="",0,IF(AND(OR(fClient="All",$C11=fClient),OR(fCampaign="All",$D11=fCampaign),OR(fTeam="All",$B11=fTeam),OR(fChannel="All",$F11=fChannel),OR(fMonth="All",$AH11=fMonth),OR(fTStatus="All",$M11=fTStatus)),1,0)) -> 1 | AJ11: =IF($G11="",0,IF(AND(OR(fClient="All",$C11=fClient),OR(fCampaign="All",$D11=fCampaign),OR(fTeam="All",$B11=fTeam),OR(fChannel="All",$F11=fChannel)),1,0)) -> 1 | AK11: =IF($G11="",0,IF(OR($M11="Completed",$M11="Cancelled"),0,1)) -> 1 | AL11: =IF(AND($AK11=1,ISNUMBER($L11)),IF($L11<ReportDate,1,0),0) -> 0 | AM11: =IF(AND($G11<>"",$M11="Blocked"),1,0) -> 0 | AN11: =IF(AND($AK11=1,ISNUMBER($L11)),IF($L11=ReportDate,1,0),0) -> 0 | AO11: =IF(AND($AK11=1,ISNUMBER($L11)),IF($L11=ReportDate+1,1,0),0) -> 0 | AP11: =IF(AND($AK11=1,ISNUMBER($L11)),IF(AND($L11>=ReportDate,$L11<=ReportDate+DueSoonDays),1,0),0) -> 0 | AQ11: =IF(AND($AK11=1,OR($I11="Critical",$I11="High")),1,0) -> 0 | AR11: =IF($AK11=1,IF(ISNUMBER($Y11),IF(ReportDate-$Y11>StaleDays,1,0),1),0) -> 1 | AS11: =IF(AND($G11<>"",ISNUMBER($Q11),ISNUMBER($R11)),IF(AND($Q11<$R11,OR($M11="Completed",AND(ISNUMBER($L11),$L11<ReportDate))),1,0),0) -> 0 | AT11: =IF($AK11=1,IF(OR($L11=ReportDate,$W11=ReportDate,$K11=ReportDate,$A11=ReportDate),1,0),0) -> 0 | AU11: =IF($AK11=1,IF(OR($L11=ReportDate+1,$W11=ReportDate+1,$K11=ReportDate+1,$A11=ReportDate+1),1,0),0) -> 0 | AV11: =IF(AND($G11<>"",$M11="Completed"),IF(OR($Y11=ReportDate-1,$A11=ReportDate-1),1,0),0) -> 0 | AW11: =IF(AND($AK11=1,$Z11="Yes"),1,0) -> 0 | AX11: =IF(AND($AK11=1,$AA11="Yes"),1,0) -> 0 | AY11: =IF(AND($AM11=1,OR($I11="Critical",$I11="High")),1,0) -> 0 | AZ11: =IF(AND($AK11=1,OR($C11=TCL_Client,$C11=MECCA_Client)),1,0) -> 0 | BA11: =IF($G11="","",IFERROR(MATCH($I11,lst_Priority,0),5)) -> 5 | BB11: =IF(AND($AL11=1,$AJ11=1),$BA11*100000+ROW(),"") | BC11: =IF(AND($AM11=1,$AJ11=1),$BA11*100000+ROW(),"") | BD11: =IF(AND($AP11=1,$AJ11=1),$BA11*100000+ROW(),"") | BE11: =IF(AND($AT11=1,$AJ11=1),$BA11*100000+ROW(),"") | BF11: =IF(AND($AU11=1,$AJ11=1),$BA11*100000+ROW(),"") | BG11: =IF(AND($AV11=1,$AJ11=1),$BA11*100000+ROW(),"") | BH11: =IF(AND($AW11=1,$AJ11=1),$BA11*100000+ROW(),"") | BI11: =IF(AND($AX11=1,$AJ11=1),$BA11*100000+ROW(),"") | BJ11: =IF(AND($AS11=1,$AJ11=1),$BA11*100000+ROW(),"") | BK11: =IF(AND($AY11=1,$AJ11=1),$BA11*100000+ROW(),"") | BL11: =IF(AND($AZ11=1),$BA11*100000+ROW(),"")
